Workbook

Sheet Read Me
A1: Southern Water Corp. Economic Analysis
A11: In this unit, you've learned about the fundamentals of economics where you've covered supply, demand, and the principles of elasticity.
A12: In this case study, we'll seek to unpack these concepts, combining the economic analysis skills you've learned and have you apply this through your budding Excel capabilities!
A13: This case study will emphasize the use of AVERAGEIFS Formula and your charting capabilities, where you'll use these charts for a PowerPoint presentation you'll create at the end of this analysis!
A14: Good luck and let's get started!
A16: What do the tab colors in this workbook mean?
A17: Throughout the Case Study, we've split this into three sections. As you cover the relevant Economics concepts, you'll apply what you've learned in the exercise tabs. The order of completion is below: 1) Market Elasticity 2) Economic Cost Analysis 3) What-If Analysis
A18: Unpacking the Data Repository Table
A19: The data repository table might look scary at first, but all the data is logically grouped in a manner where the table can be read from left to right.
A20: Note that we've added in another table, the Water Trading Repository Table that shows the date and price at which either Soft or Hard water has been traded.
A32: Definitions
A33: We've included a high-level breakdown that explains the different columns you will deal with in the data repository and water trading repository table. Please read through this and familiarize yourself with what these columns mean.
A35: Account Type | B35: This column provides information on whether the dataset is referencing Financial Actuals (Money Spent) or Water Actuals (Volume of Water Produced).
A36: Value Drivers | B36: This is a pre-filled column mapping each Accounting Centre Code and Accounting Centre Code Element to either a Revenue Generating Activity (Revenues) or Cost Generating Activity (Expenses).
A37: Unit | B37: There are three desalination units or plants (facilities) owned by Southern Water Corp. These are the Kootha, Surjek and Jutik desalination units. The Unit column indicates, for that row of data, which Unit it applies towards.
A38: Month | B38: This represents the month that data was calculated for.
A39: Month (Number) | B39: This represents the month in numerical form.
A40: Accounting Code Centre | B40: Every row is mapped to an Accounting Code Centre. Based on the Accounting Code Centre (ACC) and the textual description, we know that all ACCs that mention Sales, are Profit Centres, and all ACCs that mention Costs, are Cost Centres. In Financial Accounting, Revenue-Generating Activities are mapped to Profit Centres (i.e. They generate profit), whilst Cost-Generating Activities are mapped to Cost Centres (i.e. They generate costs).
A41: Accounting Code Centre Element | B41: An Accounting Code Centre Element (ACCE) is made up of 'elements' which tie into the Accounting Code Centre.
A42: Unit of Measure | B42: Every Row of Data has a Unit of Measure (UoM) associated with this. E.g. Financial data is measured in dollars, whilst Water Production data is measure in Giga-Litres.
A43: Row Data | B43: This is the unique value that is stored for every row entry.
A44: Trading Interval | B44: The time-stamp where Water has been traded on the Open Water Market exchange database.
A45: Market Water Demand (Giga-Litres) | B45: The amount of water demanded by the Market for that respective time-stamp period.
A46: Water Balancing Price ($/ML) | B46: The Water Market Balancing Price that is settled by the Open Water Market exchange.
... A48: Water Type | B48: What type of Water Product is being traded (i.e. Hard Water or Soft Water)?
A51: Value Driver Trees
A52: Below we've included the Value Driver Trees for the Elasticity of Demand Coefficient; a critical calculation used to determine the elasticity (price sensitivity) of a product.

Sheet Data Repository Table
A1: Account Type | B1: Value Drivers | C1: Unit | D1: Month | E1: Month (Number) | F1: Centre Type | G1: Cost Centre / Profit Centre | H1: Cost Centre / Profit Centre Elements | I1: Unit of Measure | J1: Row Data
A2: Financial Actual | B2: Revenues | C2: Kootha | D2: 41456 | E2: =MONTH(D2) -> 7 | F2: Profit Centre | G2: 001 Private Water Hedge Sales | H2: W-Transact (0211) - Soft | I2: $ | J2: 1473589
A3: Financial Actual | B3: Revenues | C3: Kootha | D3: 41487 | E3: =MONTH(D3) -> 8 | F3: Profit Centre | G3: 001 Private Water Hedge Sales | H3: W-Transact (0211) - Soft | I3: $ | J3: 1419296.1
A4: Financial Actual | B4: Revenues | C4: Kootha | D4: 41518 | E4: =MONTH(D4) -> 9 | F4: Profit Centre | G4: 001 Private Water Hedge Sales | H4: W-Transact (0211) - Soft | I4: $ | J4: 1310673.2
A5: Financial Actual | B5: Revenues | C5: Kootha | D5: 41548 | E5: =MONTH(D5) -> 10 | F5: Profit Centre | G5: 001 Private Water Hedge Sales | H5: W-Transact (0211) - Soft | I5: $ | J5: 1301024.7
A6: Financial Actual | B6: Revenues | C6: Kootha | D6: 41579 | E6: =MONTH(D6) -> 11 | F6: Profit Centre | G6: 001 Private Water Hedge Sales | H6: W-Transact (0211) - Soft | I6: $ | J6: 1373822.9
A7: Financial Actual | B7: Revenues | C7: Kootha | D7: 41609 | E7: =MONTH(D7) -> 12 | F7: Profit Centre | G7: 001 Private Water Hedge Sales | H7: W-Transact (0211) - Soft | I7: $ | J7: 1340623
A8: Financial Actual | B8: Revenues | C8: Kootha | D8: 41640 | E8: =MONTH(D8) -> 1 | F8: Profit Centre | G8: 001 Private Water Hedge Sales | H8: W-Transact (0211) - Soft | I8: $ | J8: 1948962.6
A9: Financial Actual | B9: Revenues | C9: Kootha | D9: 41671 | E9: =MONTH(D9) -> 2 | F9: Profit Centre | G9: 001 Private Water Hedge Sales | H9: W-Transact (0211) - Soft | I9: $ | J9: 1725161.7
A10: Financial Actual | B10: Revenues | C10: Kootha | D10: 41699 | E10: =MONTH(D10) -> 3 | F10: Profit Centre | G10: 001 Private Water Hedge Sales | H10: W-Transact (0211) - Soft | I10: $ | J10: 1818208.6
A11: Financial Actual | B11: Revenues | C11: Kootha | D11: 41730 | E11: =MONTH(D11) -> 4 | F11: Profit Centre | G11: 001 Private Water Hedge Sales | H11: W-Transact (0211) - Soft | I11: $ | J11: 1328501.7
A12: Financial Actual | B12: Revenues | C12: Kootha | D12: 41760 | E12: =MONTH(D12) -> 5 | F12: Profit Centre | G12: 001 Private Water Hedge Sales | H12: W-Transact (0211) - Soft | I12: $ | J12: 1344117.3
A13: Financial Actual | B13: Revenues | C13: Kootha | D13: 41791 | E13: =MONTH(D13) -> 6 | F13: Profit Centre | G13: 001 Private Water Hedge Sales | H13: W-Transact (0211) - Soft | I13: $ | J13: 1291609.1
... A373: Financial Actual | B373: Expenses | C373: Surjek | D373: 41791 | E373: =MONTH(D373) -> 6 | F373: Cost Centre | G373: Labour Costs | H373: Labour-Costs (001) | I373: $ | J373: 1891504.3
A374: Financial Actual | B374: Expenses | C374: Jutik | D374: 41456 | E374: 7 | F374: Cost Centre | G374: Chemical Costs | H374: Chem-Exp (001) | I374: $ | J374: 1625596.3
A375: Financial Actual | B375: Expenses | C375: Jutik | D375: 41487 | E375: 8 | F375: Cost Centre | G375: Chemical Costs | H375: Chem-Exp (001) | I375: $ | J375: 1295067.8
A376: Financial Actual | B376: Expenses | C376: Jutik | D376: 41518 | E376: 9 | F376: Cost Centre | G376: Chemical Costs | H376: Chem-Exp (001) | I376: $ | J376: 1750624.9
A377: Financial Actual | B377: Expenses | C377: Jutik | D377: 41548 | E377: 10 | F377: Cost Centre | G377: Chemical Costs | H377: Chem-Exp (001) | I377: $ | J377: 1472529.4
A378: Financial Actual | B378: Expenses | C378: Jutik | D378: 41579 | E378: 11 | F378: Cost Centre | G378: Chemical Costs | H378: Chem-Exp (001) | I378: $ | J378: 1252200.5
A379: Financial Actual | B379: Expenses | C379: Jutik | D379: 41609 | E379: 12 | F379: Cost Centre | G379: Chemical Costs | H379: Chem-Exp (001) | I379: $ | J379: 1406782.7
A380: Financial Actual | B380: Expenses | C380: Jutik | D380: 41640 | E380: 1 | F380: Cost Centre | G380: Chemical Costs | H380: Chem-Exp (001) | I380: $ | J380: 1877449.5
A381: Financial Actual | B381: Expenses | C381: Jutik | D381: 41671 | E381: 2 | F381: Cost Centre | G381: Chemical Costs | H381: Chem-Exp (001) | I381: $ | J381: 1912219.2
A382: Financial Actual | B382: Expenses | C382: Jutik | D382: 41699 | E382: 3 | F382: Cost Centre | G382: Chemical Costs | H382: Chem-Exp (001) | I382: $ | J382: 2266625.2
A383: Financial Actual | B383: Expenses | C383: Jutik | D383: 41730 | E383: 4 | F383: Cost Centre | G383: Chemical Costs | H383: Chem-Exp (001) | I383: $ | J383: 2234200.6
A384: Financial Actual | B384: Expenses | C384: Jutik | D384: 41760 | E384: 5 | F384: Cost Centre | G384: Chemical Costs | H384: Chem-Exp (001) | I384: $ | J384: 2593715.6
A385: Financial Actual | B385: Expenses | C385: Jutik | D385: 41791 | E385: 6 | F385: Cost Centre | G385: Chemical Costs | H385: Chem-Exp (001) | I385: $ | J385: 2274807.8
... A505: Water Production Actuals | B505: None | C505: Jutik | D505: 41791 | E505: 6 | F505: None | G505: None | H505: None | I505: Giga-Litre | J505: 220.38033

Sheet Water Trading Repository Table
A1: Trading Interval | B1: Market Water Demand (Giga-Litres) | C1: Water Balancing Price ($/ML) | D1: Month | E1: Water Type
A2: 41640 | B2: 2674.4305 | C2: 89.33425 | D2: =MONTH(A2) -> 1 | E2: Soft
A3: 41640.5 | B3: 2576.1278 | C3: 61.946 | D3: =MONTH(A3) -> 1 | E3: Soft
A4: 41641 | B4: 2131.982 | C4: 45.90175 | D4: =MONTH(A4) -> 1 | E4: Soft
A5: 41641.5 | B5: 2772.056 | C5: 80.85825 | D5: =MONTH(A5) -> 1 | E5: Soft
A6: 41642 | B6: 2143.4866 | C6: 55.961833 | D6: =MONTH(A6) -> 1 | E6: Soft
A7: 41642.5 | B7: 2682.0311 | C7: 101.09483 | D7: =MONTH(A7) -> 1 | E7: Soft
A8: 41643 | B8: 1788.0747 | C8: 26.665 | D8: =MONTH(A8) -> 1 | E8: Soft
A9: 41643.5 | B9: 2082.8451 | C9: 38.894545 | D9: =MONTH(A9) -> 1 | E9: Soft
A10: 41644 | B10: 1815.8505 | C10: 46.715 | D10: =MONTH(A10) -> 1 | E10: Soft
A11: 41644.5 | B11: 2219.2754 | C11: 46.208636 | D11: =MONTH(A11) -> 1 | E11: Soft
A12: 41645 | B12: 2142.3453 | C12: 41.856 | D12: =MONTH(A12) -> 1 | E12: Soft
A13: 41645.5 | B13: 2169.7437 | C13: 46.01375 | D13: =MONTH(A13) -> 1 | E13: Soft
... A731: 42004.5 | B731: 2134.082 | C731: 42.499583 | D731: =MONTH(A731) -> 12 | E731: Soft
A732: 41640 | B732: 2814.7106 | C732: 108.1875 | D732: 1 | E732: Hard
A733: 41640.5 | B733: 2820.1593 | C733: 111.245 | D733: 1 | E733: Hard
A734: 41641 | B734: 2147.3532 | C734: 110.51333 | D734: 1 | E734: Hard
A735: 41641.5 | B735: 2545.3108 | C735: 109.415 | D735: 1 | E735: Hard
A736: 41642 | B736: 2222.4136 | C736: 109.89833 | D736: 1 | E736: Hard
A737: 41642.5 | B737: 2257.3158 | C737: 111.87083 | D737: 1 | E737: Hard
A738: 41643 | B738: 2032.1983 | C738: 108.641 | D738: 1 | E738: Hard
A739: 41643.5 | B739: 2117.8163 | C739: 112.475 | D739: 1 | E739: Hard
A740: 41644 | B740: 1881.95 | C740: 111.09333 | D740: 1 | E740: Hard
A741: 41644.5 | B741: 2576.3439 | C741: 111.43364 | D741: 1 | E741: Hard
A742: 41645 | B742: 2044.6648 | C742: 110.707 | D742: 1 | E742: Hard
A743: 41645.5 | B743: 2868.9563 | C743: 108.41083 | D743: 1 | E743: Hard
... A1461: 42004.5 | B1461: 2379.9689 | C1461: 96.1525 | D1461: 12 | E1461: Hard

Sheet Economic Market Analysis
A1: Economic Analysis - Part I
A2: In this economics unit we've introduced you to the concept of Elasticity and Inelasticity and the relation this has to pricing patterns for products.
A3: While you might not immediately understand the relationship between elasticity and pricing, it's important we take a moment to understand how this is linked.
A4: Say for example, if we suddenly had our Netflix account fees raise to $100 per month - a number of us might reconsider whether we still want this subscription. The insight here is that the product is elastic (i.e. If we increase the price too sharply, people will leave and go to other streaming platforms.)
A5: This is tied to the concept of Elasticity (i.e. When the price is low enough, demand is high. Inversely, when the price is high - demand reduces).
A6: Now, there are situations that even IF the price rises, we will still purchase the same quantity of goods.
A7: Take for example, a particular drug for a pre-existing medical condition. If the price were to rise from its current amount to 10% higher than usual - the amount demanded wouldn't decrease as the product is still required.
A8: When this occurs, the product is known as an INELASTIC PRODUCT. (i.e. Regardless of whether the demand increases or decreases, the price will not change in any substantial manner).
A9: With what you've learned, let's take a look at Southern Water Corps Economic Data and see what trends we can identify from an Elasticity and Inelasticity Perspective. Let's be objective and ask ourselves - what does the data tell us?
A10: Let's get started!
A11: Q1. Please calculate the Average Water Balancing Market Price (WBMP) and Average Quantities of Water Demanded for 1) Hard and Soft Water Combined, 2) Hard Water Only and 3) Soft Water Only across the Jan-14 to Dec-14 Period.
A12: Do you notice any trends when comparing the Price and Quantity Per Product? (Pay particular attention to the Pricing and the Quantities and put this in the yellow box we've highlighted below)
A13: Hard + Soft Water Table | C13: 41640 | D13: 41671 | E13: 41699 | F13: 41730 | G13: 41760 | H13: 41791 | I13: 41821 | J13: 41852 | K13: 41883 | L13: 41913 | M13: 41944 | N13: 41974
B14: Month # | C14: 1 | D14: 2 | E14: 3 | F14: 4 | G14: 5 | H14: 6 | I14: 7 | J14: 8 | K14: 9 | L14: 10 | M14: 11 | N14: 12
B15: Avg. Quantity of Soft + Hard Water | C15: =AVERAGEIFS('Water Trading Repository Table'!$B:$B,'Water Trading Repository Table'!$E:$E,"Soft",'Water Trading Repository Table'!$D:$D,C$14)+ AVERAGEIFS('Water Trading Repository Table'!$B:$B,'Water Trading Repository Table'!$E:$E,"Hard",'Water Trading Repository Table'!$D:$D,C$14) -> 4596.3803 | D15: =AVERAGEIFS('Water Trading Repository Table'!$B:$B,'Water Trading Repository Table'!$E:$E,"Soft",'Water Trading Repository Table'!$D:$D,D$14)+ AVERAGEIFS('Water Trading Repository Table'!$B:$B,'Water Trading Repository Table'!$E:$E,"Hard",'Water Trading Repository Table'!$D:$D,D$14) -> 4812.1838 | E15: =AVERAGEIFS('Water Trading Repository Table'!$B:$B,'Water Trading Repository Table'!$E:$E,"Soft",'Water Trading Repository Table'!$D:$D,E$14)+ AVERAGEIFS('Water Trading Repository Table'!$B:$B,'Water Trading Repository Table'!$E:$E,"Hard",'Water Trading Repository Table'!$D:$D,E$14) -> 4255.6291 | F15: =AVERAGEIFS('Water Trading Repository Table'!$B:$B,'Water Trading Repository Table'!$E:$E,"Soft",'Water Trading Repository Table'!$D:$D,F$14)+ AVERAGEIFS('Water Trading Repository Table'!$B:$B,'Water Trading Repository Table'!$E:$E,"Hard",'Water Trading Repository Table'!$D:$D,F$14) -> 4371.5995 | G15: =AVERAGEIFS('Water Trading Repository Table'!$B:$B,'Water Trading Repository Table'!$E:$E,"Soft",'Water Trading Repository Table'!$D:$D,G$14)+ AVERAGEIFS('Water Trading Repository Table'!$B:$B,'Water Trading Repository Table'!$E:$E,"Hard",'Water Trading Repository Table'!$D:$D,G$14) -> 4291.5674 | H15: =AVERAGEIFS('Water Trading Repository Table'!$B:$B,'Water Trading Repository Table'!$E:$E,"Soft",'Water Trading Repository Table'!$D:$D,H$14)+ AVERAGEIFS('Water Trading Repository Table'!$B:$B,'Water Trading Repository Table'!$E:$E,"Hard",'Water Trading Repository Table'!$D:$D,H$14) -> 4459.4993 | I15: =AVERAGEIFS('Water Trading Repository Table'!$B:$B,'Water Trading Repository Table'!$E:$E,"Soft",'Water Trading Repository Table'!$D:$D,I$14)+ AVERAGEIFS('Water Trading Repository Table'!$B:$B,'Water Trading Repository Table'!$E:$E,"Hard",'Water Trading Repository Table'!$D:$D,I$14) -> 4566.1005 | J15: =AVERAGEIFS('Water Trading Repository Table'!$B:$B,'Water Trading Repository Table'!$E:$E,"Soft",'Water Trading Repository Table'!$D:$D,J$14)+ AVERAGEIFS('Water Trading Repository Table'!$B:$B,'Water Trading Repository Table'!$E:$E,"Hard",'Water Trading Repository Table'!$D:$D,J$14) -> 4402.1185 | ... N15: =AVERAGEIFS('Water Trading Repository Table'!$B:$B,'Water Trading Repository Table'!$E:$E,"Soft",'Water Trading Repository Table'!$D:$D,N$14)+ AVERAGEIFS('Water Trading Repository Table'!$B:$B,'Water Trading Repository Table'!$E:$E,"Hard",'Water Trading Repository Table'!$D:$D,N$14) -> 4624.3991
B16: Avg. Water Market Balancing Price (WMBP) | C16: =AVERAGEIFS('Water Trading Repository Table'!$C:$C, 'Water Trading Repository Table'!$E:$E, "Soft", 'Water Trading Repository Table'!$D:$D, C$14) + AVERAGEIFS('Water Trading Repository Table'!$C:$C, 'Water Trading Repository Table'!$E:$E, "Hard", 'Water Trading Repository Table'!$D:$D, C$14) -> 172.78351 | D16: =AVERAGEIFS('Water Trading Repository Table'!$C:$C, 'Water Trading Repository Table'!$E:$E, "Soft", 'Water Trading Repository Table'!$D:$D, D$14) + AVERAGEIFS('Water Trading Repository Table'!$C:$C, 'Water Trading Repository Table'!$E:$E, "Hard", 'Water Trading Repository Table'!$D:$D, D$14) -> 173.65898 | E16: =AVERAGEIFS('Water Trading Repository Table'!$C:$C, 'Water Trading Repository Table'!$E:$E, "Soft", 'Water Trading Repository Table'!$D:$D, E$14) + AVERAGEIFS('Water Trading Repository Table'!$C:$C, 'Water Trading Repository Table'!$E:$E, "Hard", 'Water Trading Repository Table'!$D:$D, E$14) -> 162.99978 | F16: =AVERAGEIFS('Water Trading Repository Table'!$C:$C, 'Water Trading Repository Table'!$E:$E, "Soft", 'Water Trading Repository Table'!$D:$D, F$14) + AVERAGEIFS('Water Trading Repository Table'!$C:$C, 'Water Trading Repository Table'!$E:$E, "Hard", 'Water Trading Repository Table'!$D:$D, F$14) -> 145.13846 | G16: =AVERAGEIFS('Water Trading Repository Table'!$C:$C, 'Water Trading Repository Table'!$E:$E, "Soft", 'Water Trading Repository Table'!$D:$D, G$14) + AVERAGEIFS('Water Trading Repository Table'!$C:$C, 'Water Trading Repository Table'!$E:$E, "Hard", 'Water Trading Repository Table'!$D:$D, G$14) -> 142.51871 | H16: =AVERAGEIFS('Water Trading Repository Table'!$C:$C, 'Water Trading Repository Table'!$E:$E, "Soft", 'Water Trading Repository Table'!$D:$D, H$14) + AVERAGEIFS('Water Trading Repository Table'!$C:$C, 'Water Trading Repository Table'!$E:$E, "Hard", 'Water Trading Repository Table'!$D:$D, H$14) -> 144.31302 | I16: =AVERAGEIFS('Water Trading Repository Table'!$C:$C, 'Water Trading Repository Table'!$E:$E, "Soft", 'Water Trading Repository Table'!$D:$D, I$14) + AVERAGEIFS('Water Trading Repository Table'!$C:$C, 'Water Trading Repository Table'!$E:$E, "Hard", 'Water Trading Repository Table'!$D:$D, I$14) -> 153.20544 | J16: =AVERAGEIFS('Water Trading Repository Table'!$C:$C, 'Water Trading Repository Table'!$E:$E, "Soft", 'Water Trading Repository Table'!$D:$D, J$14) + AVERAGEIFS('Water Trading Repository Table'!$C:$C, 'Water Trading Repository Table'!$E:$E, "Hard", 'Water Trading Repository Table'!$D:$D, J$14) -> 149.86508 | ... N16: =AVERAGEIFS('Water Trading Repository Table'!$C:$C, 'Water Trading Repository Table'!$E:$E, "Soft", 'Water Trading Repository Table'!$D:$D, N$14) + AVERAGEIFS('Water Trading Repository Table'!$C:$C, 'Water Trading Repository Table'!$E:$E, "Hard", 'Water Trading Repository Table'!$D:$D, N$14) -> 148.75331
A17: Hard Water Table
A18: Hard | B18: Avg. Quantity of Hard Water | C18: =AVERAGEIFS('Water Trading Repository Table'!$B:$B,'Water Trading Repository Table'!$E:$E,"Hard",'Water Trading Repository Table'!$D:$D,C$14) -> 2391.3759 | D18: =AVERAGEIFS('Water Trading Repository Table'!$B:$B,'Water Trading Repository Table'!$E:$E,"Hard",'Water Trading Repository Table'!$D:$D,D$14) -> 2533.2689 | E18: =AVERAGEIFS('Water Trading Repository Table'!$B:$B,'Water Trading Repository Table'!$E:$E,"Hard",'Water Trading Repository Table'!$D:$D,E$14) -> 2203.7443 | F18: =AVERAGEIFS('Water Trading Repository Table'!$B:$B,'Water Trading Repository Table'!$E:$E,"Hard",'Water Trading Repository Table'!$D:$D,F$14) -> 2349.5141 | G18: =AVERAGEIFS('Water Trading Repository Table'!$B:$B,'Water Trading Repository Table'!$E:$E,"Hard",'Water Trading Repository Table'!$D:$D,G$14) -> 2243.5845 | H18: =AVERAGEIFS('Water Trading Repository Table'!$B:$B,'Water Trading Repository Table'!$E:$E,"Hard",'Water Trading Repository Table'!$D:$D,H$14) -> 2359.315 | I18: =AVERAGEIFS('Water Trading Repository Table'!$B:$B,'Water Trading Repository Table'!$E:$E,"Hard",'Water Trading Repository Table'!$D:$D,I$14) -> 2443.2652 | J18: =AVERAGEIFS('Water Trading Repository Table'!$B:$B,'Water Trading Repository Table'!$E:$E,"Hard",'Water Trading Repository Table'!$D:$D,J$14) -> 2300.8486 | ... N18: =AVERAGEIFS('Water Trading Repository Table'!$B:$B,'Water Trading Repository Table'!$E:$E,"Hard",'Water Trading Repository Table'!$D:$D,N$14) -> 2443.6005
B19: Avg. Water Market Balancing Price (WMBP) | C19: =AVERAGEIFS('Water Trading Repository Table'!$C:$C, 'Water Trading Repository Table'!$E:$E, "Hard", 'Water Trading Repository Table'!$D:$D, C$14) -> 110.48382 | D19: =AVERAGEIFS('Water Trading Repository Table'!$C:$C, 'Water Trading Repository Table'!$E:$E, "Hard", 'Water Trading Repository Table'!$D:$D, D$14) -> 110.6272 | E19: =AVERAGEIFS('Water Trading Repository Table'!$C:$C, 'Water Trading Repository Table'!$E:$E, "Hard", 'Water Trading Repository Table'!$D:$D, E$14) -> 110.55819 | F19: =AVERAGEIFS('Water Trading Repository Table'!$C:$C, 'Water Trading Repository Table'!$E:$E, "Hard", 'Water Trading Repository Table'!$D:$D, F$14) -> 93.175186 | G19: =AVERAGEIFS('Water Trading Repository Table'!$C:$C, 'Water Trading Repository Table'!$E:$E, "Hard", 'Water Trading Repository Table'!$D:$D, G$14) -> 93.40891 | H19: =AVERAGEIFS('Water Trading Repository Table'!$C:$C, 'Water Trading Repository Table'!$E:$E, "Hard", 'Water Trading Repository Table'!$D:$D, H$14) -> 92.851211 | I19: =AVERAGEIFS('Water Trading Repository Table'!$C:$C, 'Water Trading Repository Table'!$E:$E, "Hard", 'Water Trading Repository Table'!$D:$D, I$14) -> 92.809568 | J19: =AVERAGEIFS('Water Trading Repository Table'!$C:$C, 'Water Trading Repository Table'!$E:$E, "Hard", 'Water Trading Repository Table'!$D:$D, J$14) -> 93.14548 | ... N19: =AVERAGEIFS('Water Trading Repository Table'!$C:$C, 'Water Trading Repository Table'!$E:$E, "Hard", 'Water Trading Repository Table'!$D:$D, N$14) -> 93.232935
A20: Soft Water Table
A21: Soft | B21: Avg. Quantity of Soft Water | C21: =AVERAGEIFS('Water Trading Repository Table'!$B:$B,'Water Trading Repository Table'!$E:$E,"Soft",'Water Trading Repository Table'!$D:$D,C$14) -> 2205.0044 | D21: =AVERAGEIFS('Water Trading Repository Table'!$B:$B,'Water Trading Repository Table'!$E:$E,"Soft",'Water Trading Repository Table'!$D:$D,D$14) -> 2278.9149 | E21: =AVERAGEIFS('Water Trading Repository Table'!$B:$B,'Water Trading Repository Table'!$E:$E,"Soft",'Water Trading Repository Table'!$D:$D,E$14) -> 2051.8848 | F21: =AVERAGEIFS('Water Trading Repository Table'!$B:$B,'Water Trading Repository Table'!$E:$E,"Soft",'Water Trading Repository Table'!$D:$D,F$14) -> 2022.0854 | G21: =AVERAGEIFS('Water Trading Repository Table'!$B:$B,'Water Trading Repository Table'!$E:$E,"Soft",'Water Trading Repository Table'!$D:$D,G$14) -> 2047.9829 | H21: =AVERAGEIFS('Water Trading Repository Table'!$B:$B,'Water Trading Repository Table'!$E:$E,"Soft",'Water Trading Repository Table'!$D:$D,H$14) -> 2100.1844 | I21: =AVERAGEIFS('Water Trading Repository Table'!$B:$B,'Water Trading Repository Table'!$E:$E,"Soft",'Water Trading Repository Table'!$D:$D,I$14) -> 2122.8353 | J21: =AVERAGEIFS('Water Trading Repository Table'!$B:$B,'Water Trading Repository Table'!$E:$E,"Soft",'Water Trading Repository Table'!$D:$D,J$14) -> 2101.2699 | ... N21: =AVERAGEIFS('Water Trading Repository Table'!$B:$B,'Water Trading Repository Table'!$E:$E,"Soft",'Water Trading Repository Table'!$D:$D,N$14) -> 2180.7986
B22: Avg. Water Market Balancing Price (WMBP) | C22: =AVERAGEIFS('Water Trading Repository Table'!$C:$C, 'Water Trading Repository Table'!$E:$E, "Soft", 'Water Trading Repository Table'!$D:$D, C$14) -> 62.299699 | D22: =AVERAGEIFS('Water Trading Repository Table'!$C:$C, 'Water Trading Repository Table'!$E:$E, "Soft", 'Water Trading Repository Table'!$D:$D, D$14) -> 63.031777 | E22: =AVERAGEIFS('Water Trading Repository Table'!$C:$C, 'Water Trading Repository Table'!$E:$E, "Soft", 'Water Trading Repository Table'!$D:$D, E$14) -> 52.441594 | F22: =AVERAGEIFS('Water Trading Repository Table'!$C:$C, 'Water Trading Repository Table'!$E:$E, "Soft", 'Water Trading Repository Table'!$D:$D, F$14) -> 51.963278 | G22: =AVERAGEIFS('Water Trading Repository Table'!$C:$C, 'Water Trading Repository Table'!$E:$E, "Soft", 'Water Trading Repository Table'!$D:$D, G$14) -> 49.109798 | H22: =AVERAGEIFS('Water Trading Repository Table'!$C:$C, 'Water Trading Repository Table'!$E:$E, "Soft", 'Water Trading Repository Table'!$D:$D, H$14) -> 51.46181 | I22: =AVERAGEIFS('Water Trading Repository Table'!$C:$C, 'Water Trading Repository Table'!$E:$E, "Soft", 'Water Trading Repository Table'!$D:$D, I$14) -> 60.395873 | J22: =AVERAGEIFS('Water Trading Repository Table'!$C:$C, 'Water Trading Repository Table'!$E:$E, "Soft", 'Water Trading Repository Table'!$D:$D, J$14) -> 56.7196 | ... N22: =AVERAGEIFS('Water Trading Repository Table'!$C:$C, 'Water Trading Repository Table'!$E:$E, "Soft", 'Water Trading Repository Table'!$D:$D, N$14) -> 55.520378
A24: Place your answer here | B24: 🧩 1. Hard + Soft Water Combined Higher quantity months (e.g., Jan: 4596.38) tend to have higher prices (Jan: $172.78). As quantity decreases (Mar: 4255.63), prices also drop (Mar: $163.00). Suggests a positive relationship: when demand is high, price is high. 💧 2. Hard Water Quantity remains relatively stable (range: ~2200–2500), but price decreases steadily: Jan: $110.48 → Jul: $92.81 Even when quantity slightly increases (e.g., Jul), price does not increase. Implies a weak or no clear link between hard water quantity and price — price seems to be trending downward regardless. 💦 3. Soft Water Quantity increases from Mar (2051.88) to Jul (2122.84). Prices remain very low and relatively flat: ~$49–63 range. The price drop in Mar ($52.44) and May ($49.11) appears even when quantity is low, suggesting price is not tightly correlated with quantity for soft water. 🔍 Key Observations: | C24: 🧩 1. Hard + Soft Water Combined Higher quantity months (e.g., Jan: 4596.38) tend to have higher prices (Jan: $172.78). As quantity decreases (Mar: 4255.63), prices also drop (Mar: $163.00). Suggests a positive relationship: when demand is high, price is high. 💧 2. Hard Water Quantity remains relatively stable (range: ~2200–2500), but price decreases steadily: Jan: $110.48 → Jul: $92.81 Even when quantity slightly increases (e.g., Jul), price does not increase. Implies a weak or no clear link between hard water quantity and price — price seems to be trending downward regardless. 💦 3. Soft Water Quantity increases from Mar (2051.88) to Jul (2122.84). Prices remain very low and relatively flat: ~$49–63 range. The price drop in Mar ($52.44) and May ($49.11) appears even when quantity is low, suggesting price is not tightly correlated with quantity for soft water. 🔍 Key Observations: | D24: 🧩 1. Hard + Soft Water Combined Higher quantity months (e.g., Jan: 4596.38) tend to have higher prices (Jan: $172.78). As quantity decreases (Mar: 4255.63), prices also drop (Mar: $163.00). Suggests a positive relationship: when demand is high, price is high. 💧 2. Hard Water Quantity remains relatively stable (range: ~2200–2500), but price decreases steadily: Jan: $110.48 → Jul: $92.81 Even when quantity slightly increases (e.g., Jul), price does not increase. Implies a weak or no clear link between hard water quantity and price — price seems to be trending downward regardless. 💦 3. Soft Water Quantity increases from Mar (2051.88) to Jul (2122.84). Prices remain very low and relatively flat: ~$49–63 range. The price drop in Mar ($52.44) and May ($49.11) appears even when quantity is low, suggesting price is not tightly correlated with quantity for soft water. 🔍 Key Observations: | E24: 🧩 1. Hard + Soft Water Combined Higher quantity months (e.g., Jan: 4596.38) tend to have higher prices (Jan: $172.78). As quantity decreases (Mar: 4255.63), prices also drop (Mar: $163.00). Suggests a positive relationship: when demand is high, price is high. 💧 2. Hard Water Quantity remains relatively stable (range: ~2200–2500), but price decreases steadily: Jan: $110.48 → Jul: $92.81 Even when quantity slightly increases (e.g., Jul), price does not increase. Implies a weak or no clear link between hard water quantity and price — price seems to be trending downward regardless. 💦 3. Soft Water Quantity increases from Mar (2051.88) to Jul (2122.84). Prices remain very low and relatively flat: ~$49–63 range. The price drop in Mar ($52.44) and May ($49.11) appears even when quantity is low, suggesting price is not tightly correlated with quantity for soft water. 🔍 Key Observations: | F24: 🧩 1. Hard + Soft Water Combined Higher quantity months (e.g., Jan: 4596.38) tend to have higher prices (Jan: $172.78). As quantity decreases (Mar: 4255.63), prices also drop (Mar: $163.00). Suggests a positive relationship: when demand is high, price is high. 💧 2. Hard Water Quantity remains relatively stable (range: ~2200–2500), but price decreases steadily: Jan: $110.48 → Jul: $92.81 Even when quantity slightly increases (e.g., Jul), price does not increase. Implies a weak or no clear link between hard water quantity and price — price seems to be trending downward regardless. 💦 3. Soft Water Quantity increases from Mar (2051.88) to Jul (2122.84). Prices remain very low and relatively flat: ~$49–63 range. The price drop in Mar ($52.44) and May ($49.11) appears even when quantity is low, suggesting price is not tightly correlated with quantity for soft water. 🔍 Key Observations:
B25: 🧩 1. Hard + Soft Water Combined Higher quantity months (e.g., Jan: 4596.38) tend to have higher prices (Jan: $172.78). As quantity decreases (Mar: 4255.63), prices also drop (Mar: $163.00). Suggests a positive relationship: when demand is high, price is high. 💧 2. Hard Water Quantity remains relatively stable (range: ~2200–2500), but price decreases steadily: Jan: $110.48 → Jul: $92.81 Even when quantity slightly increases (e.g., Jul), price does not increase. Implies a weak or no clear link between hard water quantity and price — price seems to be trending downward regardless. 💦 3. Soft Water Quantity increases from Mar (2051.88) to Jul (2122.84). Prices remain very low and relatively flat: ~$49–63 range. The price drop in Mar ($52.44) and May ($49.11) appears even when quantity is low, suggesting price is not tightly correlated with quantity for soft water. 🔍 Key Observations: | C25: 🧩 1. Hard + Soft Water Combined Higher quantity months (e.g., Jan: 4596.38) tend to have higher prices (Jan: $172.78). As quantity decreases (Mar: 4255.63), prices also drop (Mar: $163.00). Suggests a positive relationship: when demand is high, price is high. 💧 2. Hard Water Quantity remains relatively stable (range: ~2200–2500), but price decreases steadily: Jan: $110.48 → Jul: $92.81 Even when quantity slightly increases (e.g., Jul), price does not increase. Implies a weak or no clear link between hard water quantity and price — price seems to be trending downward regardless. 💦 3. Soft Water Quantity increases from Mar (2051.88) to Jul (2122.84). Prices remain very low and relatively flat: ~$49–63 range. The price drop in Mar ($52.44) and May ($49.11) appears even when quantity is low, suggesting price is not tightly correlated with quantity for soft water. 🔍 Key Observations: | D25: 🧩 1. Hard + Soft Water Combined Higher quantity months (e.g., Jan: 4596.38) tend to have higher prices (Jan: $172.78). As quantity decreases (Mar: 4255.63), prices also drop (Mar: $163.00). Suggests a positive relationship: when demand is high, price is high. 💧 2. Hard Water Quantity remains relatively stable (range: ~2200–2500), but price decreases steadily: Jan: $110.48 → Jul: $92.81 Even when quantity slightly increases (e.g., Jul), price does not increase. Implies a weak or no clear link between hard water quantity and price — price seems to be trending downward regardless. 💦 3. Soft Water Quantity increases from Mar (2051.88) to Jul (2122.84). Prices remain very low and relatively flat: ~$49–63 range. The price drop in Mar ($52.44) and May ($49.11) appears even when quantity is low, suggesting price is not tightly correlated with quantity for soft water. 🔍 Key Observations: | E25: 🧩 1. Hard + Soft Water Combined Higher quantity months (e.g., Jan: 4596.38) tend to have higher prices (Jan: $172.78). As quantity decreases (Mar: 4255.63), prices also drop (Mar: $163.00). Suggests a positive relationship: when demand is high, price is high. 💧 2. Hard Water Quantity remains relatively stable (range: ~2200–2500), but price decreases steadily: Jan: $110.48 → Jul: $92.81 Even when quantity slightly increases (e.g., Jul), price does not increase. Implies a weak or no clear link between hard water quantity and price — price seems to be trending downward regardless. 💦 3. Soft Water Quantity increases from Mar (2051.88) to Jul (2122.84). Prices remain very low and relatively flat: ~$49–63 range. The price drop in Mar ($52.44) and May ($49.11) appears even when quantity is low, suggesting price is not tightly correlated with quantity for soft water. 🔍 Key Observations: | F25: 🧩 1. Hard + Soft Water Combined Higher quantity months (e.g., Jan: 4596.38) tend to have higher prices (Jan: $172.78). As quantity decreases (Mar: 4255.63), prices also drop (Mar: $163.00). Suggests a positive relationship: when demand is high, price is high. 💧 2. Hard Water Quantity remains relatively stable (range: ~2200–2500), but price decreases steadily: Jan: $110.48 → Jul: $92.81 Even when quantity slightly increases (e.g., Jul), price does not increase. Implies a weak or no clear link between hard water quantity and price — price seems to be trending downward regardless. 💦 3. Soft Water Quantity increases from Mar (2051.88) to Jul (2122.84). Prices remain very low and relatively flat: ~$49–63 range. The price drop in Mar ($52.44) and May ($49.11) appears even when quantity is low, suggesting price is not tightly correlated with quantity for soft water. 🔍 Key Observations:
A26: Previously we covered how we could make use of scatter plots to help us visually compare the changes between price and quantity to determine whether a relationship is elastic or inelastic.
A27: Let's create a scatter plot to compare the price / quantity columns for the 3 different permutations of: 1) Hard + Soft Water, 2) Hard Water and 3) Soft Water.
A28: Q2. Using the data you've calculated above in Q1, with the Y-axis set to Avg. WMBP and X-axis set to Avg. Qty of Water Demanded, create three (3) separate charts showing the Overall (Hard Water + Soft Water) Scatter Plot, Hard Water Scatter Plot and Soft Water Scatter Plot.
A39: However, simply eyeing the data isn't sufficient. It's important we also take into account a quantitative lens. Whenever we see a visual trend, we can try and ascertain this by asking ourselves; what theorems would help disprove this?
A40: In this case, we're aware of a particular economic construct known as the Elasticity of Demand Coefficient (EoD).
A41: Now the EoD enables us to calculate elasticity and determine that if it is greater than 1, it is elastic, and if it is, less than 1, it is inelastic. This is much more absolute than simply eyeballing the data.
A42: Let's close out our Economic Market Analysis by calculating the EoD coefficient for each water product and determining the overall elasticity for each month, before averaging for the year.
G44: Let's review the example we've demonstrated on the left.
G45: We'll demonstrate with an example here.
G46: We have two months worth of pricing and quantity data we need to analyze to determine February's Elasticity Of Demand Coefficient.
H47: January | I47: February
G48: Price | H48: 74 | I48: 86
G49: Quantity | H49: 80 | I49: 100
G50: Let's now calculate the respective changes.
G51: Price % Change | H51: (86 - 74) / 74 | I51: =(I48-H48)/H48 -> 0.16216216
G52: Quantity % Change | H52: (100 - 80 ) / 80 | I52: =(I49-H49)/H49 -> 0.25
G53: Now let's perform the last part of our calculation: ABS ( Pct Change in Quantity / Pct Change in Price )
G54: We have to use ABS, as we can't have negative elasticities.
G56: EoD Coefficient | I56: =I52/I51 -> 1.5416667
G57: As 1.54 is greater than one, we would say, between January and February, the elasticity for this product is elastic.
G58: It's that simple! Now it's your turn!
A60: Q3) Using the calculation methodology shown above, calculate the Elasticity of Demand Coefficient for each month. Upon completion of this, average out the monthly Elasticity of Demand Coefficient from February to December and identify whether the product is elastic or inelastic.
A61: Note: Use the Monthly Values you've calculated in Q1 to help you out with the % Calculations! You might notice one product has very high elasticity values!
A62: We've included an IF Statement for you that evaluates the Monthly Elasticity and helps classify this as "Elastic" or "Inelastic" based on the value returned.
A63: Soft Water | C63: 41640 | D63: 41671 | E63: 41699 | F63: 41730 | G63: 41760 | H63: 41791 | I63: 41821 | J63: 41852 | K63: 41883 | L63: 41913 | M63: 41944 | N63: 41974
B64: % Change in Qty | C64: =C21 -> 2205.0044 | D64: =(D21-C21)/C21 -> 0.033519414 | E64: =(E21-D21)/D$21 -> -0.099622004 | F64: =(F21-E21)/E$21 -> -0.014522957 | G64: =(G21-F21)/F$21 -> 0.01280734 | H64: =(H21-G21)/G$21 -> 0.025489196 | I64: =(I21-H21)/H$21 -> 0.01078521 | J64: =(J21-I21)/I$21 -> -0.01015877 | K64: =(K21-J21)/J$21 -> -0.026615318 | L64: =(L21-K21)/K$21 -> -0.017677604 | ... N64: =(N21-M21)/M$21 -> 0.039256841
B65: % Change in Price | C65: =C$22 -> 62.299699 | D65: =(D22-C22)/C$22 -> 0.011750902 | E65: =(E22-D22)/D$22 -> -0.16801339 | F65: =(F22-E22)/E$22 -> -0.0091209259 | G65: =(G22-F22)/F$22 -> -0.054913399 | H65: =(H22-G22)/G$22 -> 0.047892925 | I65: =(I22-H22)/H$22 -> 0.17360569 | J65: =(J22-I22)/I$22 -> -0.060869609 | K65: =(K22-J22)/J$22 -> -0.027789004 | ... N65: =(N22-M22)/M$22 -> 0.021119672
B66: EoD | D66: =(D$64/D$65) -> 2.852497 | E66: =(E$64/E$65) -> 0.59294087 | F66: =(F$64/F$65) -> 1.5922678 | G66: =(G$64/G$65) -> -0.23322797 | H66: =(H$64/H$65) -> 0.53221214 | I66: =(I$64/I$65) -> 0.062124749 | J66: =(J$64/J$65) -> 0.16689395 | K66: =(K$64/K$65) -> 0.95776438 | ... N66: =(N$64/N$65) -> 1.8587808
B67: Elasticity Classification | D67: =IF(D66>1,"Elastic","Inelastic") -> Elastic | E67: =IF(E66>1,"Elastic","Inelastic") -> Inelastic | F67: =IF(F66>1,"Elastic","Inelastic") -> Elastic | G67: =IF(G66>1,"Elastic","Inelastic") -> Inelastic | H67: =IF(H66>1,"Elastic","Inelastic") -> Inelastic | I67: =IF(I66>1,"Elastic","Inelastic") -> Inelastic | J67: =IF(J66>1,"Elastic","Inelastic") -> Inelastic | K67: =IF(K66>1,"Elastic","Inelastic") -> Inelastic | ... N67: =IF(N66>1,"Elastic","Inelastic") -> Elastic
B68: Average EoD (Year) | C68: =AVERAGE(D66:N66) -> 0.6446497
A70: Hard Water | C70: 41640 | D70: 41671 | E70: 41699 | F70: 41730 | G70: 41760 | H70: 41791 | I70: 41821 | J70: 41852 | K70: 41883 | L70: 41913 | M70: 41944 | N70: 41974
B71: % Change in Qty | C71: =C$18 -> 2391.3759 | D71: =(D18-C18)/C$18 -> 0.059335305 | E71: =(E18-D18)/D$18 -> -0.13007882 | F71: =(F18-E18)/E$18 -> 0.066146449 | G71: =(G18-F18)/F$18 -> -0.04508575 | H71: =(H18-G18)/G$18 -> 0.051582833 | I71: =(I18-H18)/H$18 -> 0.035582465 | J71: =(J18-I18)/I$18 -> -0.05828946 | K71: =(K18-J18)/J$18 -> -0.017170254 | ... N71: =(N18-M18)/M$18 -> 0.060849507
B72: % Change in Price | C72: =C$19 -> 110.48382 | D72: =(D19-C19)/C$19 -> 0.0012978263 | E72: =(E19-D19)/D$19 -> -0.00062386248 | F72: =(F19-E19)/E$19 -> -0.15722944 | G72: =(G19-F19)/F$19 -> 0.0025084424 | H72: =(H19-G19)/G$19 -> -0.0059705116 | I72: =(I19-H19)/H$19 -> -0.00044850029 | J72: =(J19-I19)/I$19 -> 0.0036193742 | K72: =(K19-J19)/J$19 -> -0.0016775841 | ... N72: =(N19-M19)/M$19 -> 0.0021829674
B73: EoD | D73: =(D$71/D$72) -> 45.718987 | E73: =(E$71/E$72) -> 208.5056 | F73: =(F$71/F$72) -> -0.42070014 | G73: =(G$71/G$72) -> -17.973604 | H73: =(H$71/H$72) -> -8.6396002 | I73: =(I$71/I$72) -> -79.336549 | J73: =(J$71/J$72) -> -16.104845 | K73: =(K$71/K$72) -> 10.235108 | ... N73: =(N$71/N$72) -> 27.874675
B74: Elasticity Classification | D74: =IF(D73>1,"Elastic","Inelastic") -> Elastic | E74: =IF(E73>1,"Elastic","Inelastic") -> Elastic | F74: =IF(F73>1,"Elastic","Inelastic") -> Inelastic | G74: =IF(G73>1,"Elastic","Inelastic") -> Inelastic | H74: =IF(H73>1,"Elastic","Inelastic") -> Inelastic | I74: =IF(I73>1,"Elastic","Inelastic") -> Inelastic | J74: =IF(J73>1,"Elastic","Inelastic") -> Inelastic | K74: =IF(K73>1,"Elastic","Inelastic") -> Elastic | ... N74: =IF(N73>1,"Elastic","Inelastic") -> Elastic
B75: Average EoD (Year) | C75: =AVERAGE(D73:N73) -> 19.221649

Sheet What-If Analysis
A1: What IF Analysis - Part III.
A2: In the previous sections, we've examined the Elasticies and Inelasticies of Products. We've also gone ahead with calculating our first economic metric, Cost to Produce per Desalination Unit.
A3: We're now at the final stage of this economic case study!
A4: Economic Data Analysis, as you know by now, is focused on understanding the drivers which impact supply and demand and translating these into actionable business insights. It is also used for better understanding when certain decisions should be made (e.g. Should we look at selling this product now or in a few months time for improved earnings?)
A5: Now we're aware that Southern Water Corp. has been considering to perform a major maintenance activity for one of its major desalination plants, Surjek. The business hypothesis is that it is best for us to perform the maintenance for Surjek in the first quarter of the year going forward (January-15 to March-15).
A6: However, we don't have data going all the way to January-15 to March-15. What we do have however, is data from July 2013 - June 2014. We also have pricing data from January 2014 - December 2014.
A7: We can't use what we don't have - so let's use what we do have. In other words, we'll be making use of the data in the Water Trading Repository Tables to forecast what the demand profile may look like for the future.
A8: This means when we reference Jan-15, we'll instead use Jan-14's data as a placeholder. For Feb-15, we do the same and use Feb-14 etc.
A9: Let's get started!
A11: Q8. Complete the table below with the Average Monthly Water Balancing Market Price (WBMP) and Average Market Water Demand using data from the Water Trading Repository Table. Create one LINE chart trending the Average Water Balancing Price from Jul-14 to Jun-15. Create one COLUMN chart showing the Average Water Market Demand from Jul-14 to Jun-15. Compare these side-by-side. What do you observe? Note: Consider using the AVERAGEIFS function to help you address this question if you're stuck! https://support.microsoft.com/en-us/office/averageifs-function-48910c45-1fc0-4389-a028-f7c5c3001690
A12: Hint: Use the Water Trading Repository Table Data as your data source. Even though the date/time doesn't align, we can use the information as a proxy for the 2014/2015 data. It may also help to graph out the data and see if any trends become particularly obvious...!
A13: Source | E13: 41821 | F13: 41852 | G13: 41883 | H13: 41913 | I13: 41944 | J13: 41974 | K13: 42005 | L13: 42036 | M13: 42064 | N13: 42095 | O13: 42125 | P13: 42156 | Q13: Total
E14: =MONTH(E13) -> 7 | F14: =MONTH(F13) -> 8 | G14: =MONTH(G13) -> 9 | H14: =MONTH(H13) -> 10 | I14: =MONTH(I13) -> 11 | J14: =MONTH(J13) -> 12 | K14: =MONTH(K13) -> 1 | L14: =MONTH(L13) -> 2 | ... P14: =MONTH(P13) -> 6
A15: Water Trading Repository Table | B15: Average Water Balancing Market Price | E15: =AVERAGEIFS('Water Trading Repository Table'!$C:$C, 'Water Trading Repository Table'!$A:$A, ">=" & E$13, 'Water Trading Repository Table'!$A:$A, "<" & EDATE(E$13, 1)) -> 76.60272 | F15: =AVERAGEIFS('Water Trading Repository Table'!$C:$C, 'Water Trading Repository Table'!$A:$A, ">=" & F$13, 'Water Trading Repository Table'!$A:$A, "<" & EDATE(F$13, 1)) -> 74.93254 | G15: =AVERAGEIFS('Water Trading Repository Table'!$C:$C, 'Water Trading Repository Table'!$A:$A, ">=" & G$13, 'Water Trading Repository Table'!$A:$A, "<" & EDATE(G$13, 1)) -> 74.06632 | H15: =AVERAGEIFS('Water Trading Repository Table'!$C:$C, 'Water Trading Repository Table'!$A:$A, ">=" & H$13, 'Water Trading Repository Table'!$A:$A, "<" & EDATE(H$13, 1)) -> 75.093149 | I15: =AVERAGEIFS('Water Trading Repository Table'!$C:$C, 'Water Trading Repository Table'!$A:$A, ">=" & I$13, 'Water Trading Repository Table'!$A:$A, "<" & EDATE(I$13, 1)) -> 73.700956 | J15: =AVERAGEIFS('Water Trading Repository Table'!$C:$C, 'Water Trading Repository Table'!$A:$A, ">=" & J$13, 'Water Trading Repository Table'!$A:$A, "<" & EDATE(J$13, 1)) -> 74.376657 | K15: =AVERAGEIFS('Water Trading Repository Table'!$C:$C, 'Water Trading Repository Table'!$A:$A, ">=1/1/2014", 'Water Trading Repository Table'!$A:$A, "<2/1/2014") -> 86.391757 | L15: =AVERAGEIFS('Water Trading Repository Table'!$C:$C, 'Water Trading Repository Table'!$A:$A, ">=2/1/2014", 'Water Trading Repository Table'!$A:$A, "<3/1/2014") -> 86.82949 | M15: =AVERAGEIFS('Water Trading Repository Table'!$C:$C, 'Water Trading Repository Table'!$A:$A, ">=3/1/2014", 'Water Trading Repository Table'!$A:$A, "<4/1/2014") -> 81.499891 | N15: =AVERAGEIFS('Water Trading Repository Table'!$C:$C, 'Water Trading Repository Table'!$A:$A, ">=4/1/2014", 'Water Trading Repository Table'!$A:$A, "<5/1/2014") -> 72.569232 | O15: =AVERAGEIFS('Water Trading Repository Table'!$C:$C, 'Water Trading Repository Table'!$A:$A, ">=5/1/2014", 'Water Trading Repository Table'!$A:$A, "<6/1/2014") -> 71.259354 | P15: =AVERAGEIFS('Water Trading Repository Table'!$C:$C, 'Water Trading Repository Table'!$A:$A, ">=6/1/2014", 'Water Trading Repository Table'!$A:$A, "<7/1/2014") -> 72.156511 | Q15: =SUM(E15:P15) -> 919.47858
A16: Water Trading Repository Table | B16: Market Water Demand (Mega-Litres) | E16: =AVERAGEIFS('Water Trading Repository Table'!$B:$B, 'Water Trading Repository Table'!$A:$A, ">=" & E$13, 'Water Trading Repository Table'!$A:$A, "<" & EDATE(E$13, 1)) -> 2283.0502 | F16: =AVERAGEIFS('Water Trading Repository Table'!$B:$B, 'Water Trading Repository Table'!$A:$A, ">=" & F$13, 'Water Trading Repository Table'!$A:$A, "<" & EDATE(F$13, 1)) -> 2201.0592 | G16: =AVERAGEIFS('Water Trading Repository Table'!$B:$B, 'Water Trading Repository Table'!$A:$A, ">=" & G$13, 'Water Trading Repository Table'!$A:$A, "<" & EDATE(G$13, 1)) -> 2153.3432 | H16: =AVERAGEIFS('Water Trading Repository Table'!$B:$B, 'Water Trading Repository Table'!$A:$A, ">=" & H$13, 'Water Trading Repository Table'!$A:$A, "<" & EDATE(H$13, 1)) -> 2098.9914 | I16: =AVERAGEIFS('Water Trading Repository Table'!$B:$B, 'Water Trading Repository Table'!$A:$A, ">=" & I$13, 'Water Trading Repository Table'!$A:$A, "<" & EDATE(I$13, 1)) -> 2200.9293 | J16: =AVERAGEIFS('Water Trading Repository Table'!$B:$B, 'Water Trading Repository Table'!$A:$A, ">=" & J$13, 'Water Trading Repository Table'!$A:$A, "<" & EDATE(J$13, 1)) -> 2312.1995 | K16: =AVERAGEIFS('Water Trading Repository Table'!$B:$B, 'Water Trading Repository Table'!$A:$A, ">=1/1/2014", 'Water Trading Repository Table'!$A:$A, "<2/1/2014") -> 2298.1902 | L16: =AVERAGEIFS('Water Trading Repository Table'!$B:$B, 'Water Trading Repository Table'!$A:$A, ">=2/1/2014", 'Water Trading Repository Table'!$A:$A, "<3/1/2014") -> 2406.0919 | M16: =AVERAGEIFS('Water Trading Repository Table'!$B:$B, 'Water Trading Repository Table'!$A:$A, ">=3/1/2014", 'Water Trading Repository Table'!$A:$A, "<4/1/2014") -> 2127.8145 | N16: =AVERAGEIFS('Water Trading Repository Table'!$B:$B, 'Water Trading Repository Table'!$A:$A, ">=4/1/2014", 'Water Trading Repository Table'!$A:$A, "<5/1/2014") -> 2185.7998 | O16: =AVERAGEIFS('Water Trading Repository Table'!$C:$C, 'Water Trading Repository Table'!$A:$A, ">=5/1/2014", 'Water Trading Repository Table'!$A:$A, "<6/1/2014") -> 71.259354 | P16: =AVERAGEIFS('Water Trading Repository Table'!$C:$C, 'Water Trading Repository Table'!$A:$A, ">=6/1/2014", 'Water Trading Repository Table'!$A:$A, "<7/1/2014") -> 72.156511 | Q16: =SUM(E16:P16) -> 22410.885
A36: Place your answer here | B36: This image contains two related charts that give insights into water market pricing and demand trends from July 2014 to June 2015: Left Chart: Average Water Balancing Price Trend: The line chart shows the monthly average price of water balancing. Key Observations: Prices hovered around $75-$80 from July 2014 to December 2014. There was a sharp increase in January and February 2015, peaking close to $88. Prices dropped significantly after February, reaching the lowest point in May 2015 (around $70), before a slight uptick in June. Right Chart: Average Water Market Demand Trend: The bar chart displays monthly average water demand in Megaliters (MegaL). Key Observations: Demand fluctuated around 2,100–2,300 MegaL in most months. The highest spike in demand occurred in February 2015, reaching about 2,430 MegaL. Demand dropped sharply in March, followed by relatively lower and stable levels until June 2015. Interpretation / Insights: February 2015 stands out: It shows the highest price and highest demand. This suggests a positive relationship between market demand and pricing—when demand surged, so did the price. After February, both demand and price declined, possibly indicating seasonal effects or policy changes. This could reflect a strain on water supply in early 2015, leading to a market spike.
A40: We've identified a particular trend in our earlier analysis; It seems that one of the quarters tends to have the highest prices. As we perform our what-if analysis it's important we can clearly identify the quarter we should recommend to perform our major maintenance. Let's calculate this below and land on a quarter we can propose to focus our analysis on. Q9. Complete the table below identifying which quarter has the highest/lowest prices with the respective Average Quarterly Water Volumes. What do you notice? Note: Reference the Water Trading Repository Table for your calculations.
A41: As you'll be calculating the Quarterly Averages, this will require you to use an AVERAGEIFS statement combined with logical and numerical operators.
A42: For example = AVERAGEIFS(Monthly_Price, Month_Range, ">="&1, Month_Range, "<="&3). This says, give me the Average Price for the periods between January (1) and March (3).
A43: Quarter | C43: Average Quarterly Price Per Trading Period | D43: Average Quarterly Water Demand Per Trading Period
A44: Quarter 1 (January - March) | C44: =AVERAGEIFS('Water Trading Repository Table'!$C:$C, 'Water Trading Repository Table'!$D:$D, ">=1", 'Water Trading Repository Table'!$D:$D, "<=3") -> 84.842965 | D44: =AVERAGEIFS('Water Trading Repository Table'!$B:$B, 'Water Trading Repository Table'!$D:$D, ">=1", 'Water Trading Repository Table'!$D:$D, "<=3") -> 2273.0747
A45: Quarter 2 (April to June) | C45: =AVERAGEIFS('Water Trading Repository Table'!$C:$C, 'Water Trading Repository Table'!$D:$D, ">=4", 'Water Trading Repository Table'!$D:$D, "<=6") -> 71.986948 | D45: =AVERAGEIFS('Water Trading Repository Table'!$B:$B, 'Water Trading Repository Table'!$D:$D, ">=4", 'Water Trading Repository Table'!$D:$D, "<=6") -> 2186.6569
A46: Quarter 3 (July to September) | C46: =AVERAGEIFS('Water Trading Repository Table'!$C:$C, 'Water Trading Repository Table'!$D:$D, ">=7", 'Water Trading Repository Table'!$D:$D, "<=9") -> 75.212855 | D46: =AVERAGEIFS('Water Trading Repository Table'!$B:$B, 'Water Trading Repository Table'!$D:$D, ">=7", 'Water Trading Repository Table'!$D:$D, "<=9") -> 2213.1271
A47: Quarter 4 (October to December) | C47: =AVERAGEIFS('Water Trading Repository Table'!$C:$C, 'Water Trading Repository Table'!$D:$D, ">=10", 'Water Trading Repository Table'!$D:$D, "<=12") -> 74.397746 | D47: =AVERAGEIFS('Water Trading Repository Table'!$B:$B, 'Water Trading Repository Table'!$D:$D, ">=10", 'Water Trading Repository Table'!$D:$D, "<=12") -> 2204.0739
A49: Place your answer here | B49: Q1 (Jan–Mar) is the strongest quarter, showing both the highest prices and demand — likely due to high consumption or limited supply in that period. Q2 (Apr–Jun) is the weakest quarter, with the lowest price and demand, suggesting it may be an ideal time for a maintenance outage since it would have the least market impact. Q3 and Q4 show stable, mid-range performance.
A51: We've now completed the first part of our What-If Analysis. We've identified that the best period for us to perform a maintenance event is during a specific quarter. We now need to finalize our recommendation by showing the What-If Impact of our analysis. In Other words, if we were to perform this Maintenance Outage for Quarter 1, Quarter 2, Quarter Three and Quarter Four - what impact would this have on our revenues?
A53: Q10. Fill out the table(s) below explaining why the Quarter you are proposing is the best option for Southern Water Corp. when considering the impact on Revenues. We recommend accompanying the table with an appropriate visual to help highlight the point you are trying to make. Note: Recall that for the Quarter you are recommending for a maintenance outage, the revenues for that entire quarter for Surjek will be 0. Remember, if we are producing no water - we can't earn revenues.
E54: Q3 | F54: Q3 | G54: Q3 | H54: Q4 | I54: Q4 | J54: Q4 | K54: Q1 | L54: Q1 | M54: Q1 | N54: Q2 | O54: Q2 | P54: Q2
A55: Account Type | B55: Unit | C55: Value Driver | E55: 41456 | F55: 41487 | G55: 41518 | H55: 41548 | I55: 41579 | J55: 41609 | K55: 41640 | L55: 41671 | M55: 41699 | N55: 41730 | O55: 41760 | P55: 41791 | Q55: Total
A56: Financial Actual | B56: Kootha | C56: Revenues | E56: =SUMIFS('Data Repository Table'!$J:$J, 'Data Repository Table'!$A:$A, "Financial Actual", 'Data Repository Table'!$C:$C, "Kootha", 'Data Repository Table'!$B:$B, "Revenues", 'Data Repository Table'!$D:$D, ">=" & E$55, 'Data Repository Table'!$D:$D, "<" & EDATE(E$55, 1)) -> 5914581.2 | F56: =SUMIFS('Data Repository Table'!$J:$J, 'Data Repository Table'!$A:$A, "Financial Actual", 'Data Repository Table'!$C:$C, "Kootha", 'Data Repository Table'!$B:$B, "Revenues", 'Data Repository Table'!$D:$D, ">=" & F$55, 'Data Repository Table'!$D:$D, "<" & EDATE(F$55, 1)) -> 5696664.2 | G56: =SUMIFS('Data Repository Table'!$J:$J, 'Data Repository Table'!$A:$A, "Financial Actual", 'Data Repository Table'!$C:$C, "Kootha", 'Data Repository Table'!$B:$B, "Revenues", 'Data Repository Table'!$D:$D, ">=" & G$55, 'Data Repository Table'!$D:$D, "<" & EDATE(G$55, 1)) -> 5260681.8 | H56: =SUMIFS('Data Repository Table'!$J:$J, 'Data Repository Table'!$A:$A, "Financial Actual", 'Data Repository Table'!$C:$C, "Kootha", 'Data Repository Table'!$B:$B, "Revenues", 'Data Repository Table'!$D:$D, ">=" & H$55, 'Data Repository Table'!$D:$D, "<" & EDATE(H$55, 1)) -> 5221955.5 | I56: =SUMIFS('Data Repository Table'!$J:$J, 'Data Repository Table'!$A:$A, "Financial Actual", 'Data Repository Table'!$C:$C, "Kootha", 'Data Repository Table'!$B:$B, "Revenues", 'Data Repository Table'!$D:$D, ">=" & I$55, 'Data Repository Table'!$D:$D, "<" & EDATE(I$55, 1)) -> 5514147.2 | J56: =SUMIFS('Data Repository Table'!$J:$J, 'Data Repository Table'!$A:$A, "Financial Actual", 'Data Repository Table'!$C:$C, "Kootha", 'Data Repository Table'!$B:$B, "Revenues", 'Data Repository Table'!$D:$D, ">=" & J$55, 'Data Repository Table'!$D:$D, "<" & EDATE(J$55, 1)) -> 5380892.2 | K56: =SUMIFS('Data Repository Table'!$J:$J, 'Data Repository Table'!$A:$A, "Financial Actual", 'Data Repository Table'!$C:$C, "Kootha", 'Data Repository Table'!$B:$B, "Revenues", 'Data Repository Table'!$D:$D, ">=" & K$55, 'Data Repository Table'!$D:$D, "<" & EDATE(K$55, 1)) -> 7822599.7 | L56: =SUMIFS('Data Repository Table'!$J:$J, 'Data Repository Table'!$A:$A, "Financial Actual", 'Data Repository Table'!$C:$C, "Kootha", 'Data Repository Table'!$B:$B, "Revenues", 'Data Repository Table'!$D:$D, ">=" & L$55, 'Data Repository Table'!$D:$D, "<" & EDATE(L$55, 1)) -> 6924324.6 | ... P56: =SUMIFS('Data Repository Table'!$J:$J, 'Data Repository Table'!$A:$A, "Financial Actual", 'Data Repository Table'!$C:$C, "Kootha", 'Data Repository Table'!$B:$B, "Revenues", 'Data Repository Table'!$D:$D, ">=" & P$55, 'Data Repository Table'!$D:$D, "<" & EDATE(P$55, 1)) -> 5184163.9 | Q56: =SUM(E56:P56) -> 70944957
A57: Financial Actual | B57: Surjek | C57: Revenues | E57: =SUMIFS('Data Repository Table'!$J:$J, 'Data Repository Table'!$A:$A, "Financial Actual", 'Data Repository Table'!$C:$C, "Surjek", 'Data Repository Table'!$B:$B, "Revenues", 'Data Repository Table'!$D:$D, ">=" & E$55, 'Data Repository Table'!$D:$D, "<" & EDATE(E$55, 1)) -> 17328051 | F57: =SUMIFS('Data Repository Table'!$J:$J, 'Data Repository Table'!$A:$A, "Financial Actual", 'Data Repository Table'!$C:$C, "Surjek", 'Data Repository Table'!$B:$B, "Revenues", 'Data Repository Table'!$D:$D, ">=" & F$55, 'Data Repository Table'!$D:$D, "<" & EDATE(F$55, 1)) -> 14604314 | G57: =SUMIFS('Data Repository Table'!$J:$J, 'Data Repository Table'!$A:$A, "Financial Actual", 'Data Repository Table'!$C:$C, "Surjek", 'Data Repository Table'!$B:$B, "Revenues", 'Data Repository Table'!$D:$D, ">=" & G$55, 'Data Repository Table'!$D:$D, "<" & EDATE(G$55, 1)) -> 16135900 | H57: =SUMIFS('Data Repository Table'!$J:$J, 'Data Repository Table'!$A:$A, "Financial Actual", 'Data Repository Table'!$C:$C, "Surjek", 'Data Repository Table'!$B:$B, "Revenues", 'Data Repository Table'!$D:$D, ">=" & H$55, 'Data Repository Table'!$D:$D, "<" & EDATE(H$55, 1)) -> 15151633 | I57: =SUMIFS('Data Repository Table'!$J:$J, 'Data Repository Table'!$A:$A, "Financial Actual", 'Data Repository Table'!$C:$C, "Surjek", 'Data Repository Table'!$B:$B, "Revenues", 'Data Repository Table'!$D:$D, ">=" & I$55, 'Data Repository Table'!$D:$D, "<" & EDATE(I$55, 1)) -> 13832901 | J57: =SUMIFS('Data Repository Table'!$J:$J, 'Data Repository Table'!$A:$A, "Financial Actual", 'Data Repository Table'!$C:$C, "Surjek", 'Data Repository Table'!$B:$B, "Revenues", 'Data Repository Table'!$D:$D, ">=" & J$55, 'Data Repository Table'!$D:$D, "<" & EDATE(J$55, 1)) -> 15562960 | K57: 0 | L57: 0 | M57: 0 | N57: =SUMIFS('Data Repository Table'!$J:$J, 'Data Repository Table'!$A:$A, "Financial Actual", 'Data Repository Table'!$C:$C, "Surjek", 'Data Repository Table'!$B:$B, "Revenues", 'Data Repository Table'!$D:$D, ">=" & N$55, 'Data Repository Table'!$D:$D, "<" & EDATE(N$55, 1)) -> 18268435 | O57: =SUMIFS('Data Repository Table'!$J:$J, 'Data Repository Table'!$A:$A, "Financial Actual", 'Data Repository Table'!$C:$C, "Surjek", 'Data Repository Table'!$B:$B, "Revenues", 'Data Repository Table'!$D:$D, ">=" & O$55, 'Data Repository Table'!$D:$D, "<" & EDATE(O$55, 1)) -> 14627298 | P57: =SUMIFS('Data Repository Table'!$J:$J, 'Data Repository Table'!$A:$A, "Financial Actual", 'Data Repository Table'!$C:$C, "Surjek", 'Data Repository Table'!$B:$B, "Revenues", 'Data Repository Table'!$D:$D, ">=" & P$55, 'Data Repository Table'!$D:$D, "<" & EDATE(P$55, 1)) -> 16164167 | Q57: =SUM(E57:P57) -> 1.4167566e+08
A58: Financial Actual | B58: Jutik | C58: Revenues | E58: =SUMIFS('Data Repository Table'!$J:$J, 'Data Repository Table'!$A:$A, "Financial Actual", 'Data Repository Table'!$C:$C, "Jutik", 'Data Repository Table'!$B:$B, "Revenues", 'Data Repository Table'!$D:$D, ">=" & E$55, 'Data Repository Table'!$D:$D, "<" & EDATE(E$55, 1)) -> 12716847 | F58: =SUMIFS('Data Repository Table'!$J:$J, 'Data Repository Table'!$A:$A, "Financial Actual", 'Data Repository Table'!$C:$C, "Jutik", 'Data Repository Table'!$B:$B, "Revenues", 'Data Repository Table'!$D:$D, ">=" & F$55, 'Data Repository Table'!$D:$D, "<" & EDATE(F$55, 1)) -> 13050244 | G58: =SUMIFS('Data Repository Table'!$J:$J, 'Data Repository Table'!$A:$A, "Financial Actual", 'Data Repository Table'!$C:$C, "Jutik", 'Data Repository Table'!$B:$B, "Revenues", 'Data Repository Table'!$D:$D, ">=" & G$55, 'Data Repository Table'!$D:$D, "<" & EDATE(G$55, 1)) -> 13235473 | H58: =SUMIFS('Data Repository Table'!$J:$J, 'Data Repository Table'!$A:$A, "Financial Actual", 'Data Repository Table'!$C:$C, "Jutik", 'Data Repository Table'!$B:$B, "Revenues", 'Data Repository Table'!$D:$D, ">=" & H$55, 'Data Repository Table'!$D:$D, "<" & EDATE(H$55, 1)) -> 11815762 | I58: =SUMIFS('Data Repository Table'!$J:$J, 'Data Repository Table'!$A:$A, "Financial Actual", 'Data Repository Table'!$C:$C, "Jutik", 'Data Repository Table'!$B:$B, "Revenues", 'Data Repository Table'!$D:$D, ">=" & I$55, 'Data Repository Table'!$D:$D, "<" & EDATE(I$55, 1)) -> 11881724 | J58: =SUMIFS('Data Repository Table'!$J:$J, 'Data Repository Table'!$A:$A, "Financial Actual", 'Data Repository Table'!$C:$C, "Jutik", 'Data Repository Table'!$B:$B, "Revenues", 'Data Repository Table'!$D:$D, ">=" & J$55, 'Data Repository Table'!$D:$D, "<" & EDATE(J$55, 1)) -> 11127132 | K58: =SUMIFS('Data Repository Table'!$J:$J, 'Data Repository Table'!$A:$A, "Financial Actual", 'Data Repository Table'!$C:$C, "Jutik", 'Data Repository Table'!$B:$B, "Revenues", 'Data Repository Table'!$D:$D, ">=" & K$55, 'Data Repository Table'!$D:$D, "<" & EDATE(K$55, 1)) -> 15491089 | L58: =SUMIFS('Data Repository Table'!$J:$J, 'Data Repository Table'!$A:$A, "Financial Actual", 'Data Repository Table'!$C:$C, "Jutik", 'Data Repository Table'!$B:$B, "Revenues", 'Data Repository Table'!$D:$D, ">=" & L$55, 'Data Repository Table'!$D:$D, "<" & EDATE(L$55, 1)) -> 15776843 | ... P58: =SUMIFS('Data Repository Table'!$J:$J, 'Data Repository Table'!$A:$A, "Financial Actual", 'Data Repository Table'!$C:$C, "Jutik", 'Data Repository Table'!$B:$B, "Revenues", 'Data Repository Table'!$D:$D, ">=" & P$55, 'Data Repository Table'!$D:$D, "<" & EDATE(P$55, 1)) -> 15120322 | Q58: =SUM(E58:P58) -> 1.6366523e+08
A62: Fill this table out with Surjek's Sales Revenue from Jul-13 to Jun-14. However, when evaluating Q1, Q2, Q3 or Q4 is best, note that if you choose Q1, you'll need to put down a 0 in the values from January to March. This is because we're saying the unit will be offline then and not producing any water. This means at any point in our simulation for Q1 to Q4, we will only have 9 Month's worth of revenue-producing months, as the other 3 are offline due to outages. Please repeat this from Q2 to Q4.
A63: Now If we perform the Maintenance Outage for Surjek in Q1, Q2, Q3 or Q4 our Revenues will be…
A64: Account Type | B64: Unit | C64: Value Driver | D64: Quarter | E64: 41456 | F64: 41487 | G64: 41518 | H64: 41548 | I64: 41579 | J64: 41609 | K64: 41640 | L64: 41671 | M64: 41699 | N64: 41730 | O64: 41760 | P64: 41791 | Q64: Total | R64: % Revenue Reduction
A65: Financial Actual | B65: Surjek | C65: Revenues | D65: Q1 | E65: =SUMIFS('Data Repository Table'!$J:$J, 'Data Repository Table'!$A:$A, "Financial Actual", 'Data Repository Table'!$C:$C, "Surjek", 'Data Repository Table'!$B:$B, "Revenues", 'Data Repository Table'!$D:$D, ">=" & E$64, 'Data Repository Table'!$D:$D, "<" & EDATE(E$64, 1)) -> 17328051 | F65: =SUMIFS('Data Repository Table'!$J:$J, 'Data Repository Table'!$A:$A, "Financial Actual", 'Data Repository Table'!$C:$C, "Surjek", 'Data Repository Table'!$B:$B, "Revenues", 'Data Repository Table'!$D:$D, ">=" & F$64, 'Data Repository Table'!$D:$D, "<" & EDATE(F$64, 1)) -> 14604314 | G65: =SUMIFS('Data Repository Table'!$J:$J, 'Data Repository Table'!$A:$A, "Financial Actual", 'Data Repository Table'!$C:$C, "Surjek", 'Data Repository Table'!$B:$B, "Revenues", 'Data Repository Table'!$D:$D, ">=" & G$64, 'Data Repository Table'!$D:$D, "<" & EDATE(G$64, 1)) -> 16135900 | H65: =SUMIFS('Data Repository Table'!$J:$J, 'Data Repository Table'!$A:$A, "Financial Actual", 'Data Repository Table'!$C:$C, "Surjek", 'Data Repository Table'!$B:$B, "Revenues", 'Data Repository Table'!$D:$D, ">=" & H$64, 'Data Repository Table'!$D:$D, "<" & EDATE(H$64, 1)) -> 15151633 | I65: =SUMIFS('Data Repository Table'!$J:$J, 'Data Repository Table'!$A:$A, "Financial Actual", 'Data Repository Table'!$C:$C, "Surjek", 'Data Repository Table'!$B:$B, "Revenues", 'Data Repository Table'!$D:$D, ">=" & I$64, 'Data Repository Table'!$D:$D, "<" & EDATE(I$64, 1)) -> 13832901 | J65: =SUMIFS('Data Repository Table'!$J:$J, 'Data Repository Table'!$A:$A, "Financial Actual", 'Data Repository Table'!$C:$C, "Surjek", 'Data Repository Table'!$B:$B, "Revenues", 'Data Repository Table'!$D:$D, ">=" & J$64, 'Data Repository Table'!$D:$D, "<" & EDATE(J$64, 1)) -> 15562960 | K65: 0 | L65: 0 | M65: 0 | N65: =SUMIFS('Data Repository Table'!$J:$J, 'Data Repository Table'!$A:$A, "Financial Actual", 'Data Repository Table'!$C:$C, "Surjek", 'Data Repository Table'!$B:$B, "Revenues", 'Data Repository Table'!$D:$D, ">=" & N$64, 'Data Repository Table'!$D:$D, "<" & EDATE(N$64, 1)) -> 18268435 | O65: =SUMIFS('Data Repository Table'!$J:$J, 'Data Repository Table'!$A:$A, "Financial Actual", 'Data Repository Table'!$C:$C, "Surjek", 'Data Repository Table'!$B:$B, "Revenues", 'Data Repository Table'!$D:$D, ">=" & O$64, 'Data Repository Table'!$D:$D, "<" & EDATE(O$64, 1)) -> 14627298 | P65: =SUMIFS('Data Repository Table'!$J:$J, 'Data Repository Table'!$A:$A, "Financial Actual", 'Data Repository Table'!$C:$C, "Surjek", 'Data Repository Table'!$B:$B, "Revenues", 'Data Repository Table'!$D:$D, ">=" & P$64, 'Data Repository Table'!$D:$D, "<" & EDATE(P$64, 1)) -> 16164167 | Q65: =SUM(E65:P65) -> 1.4167566e+08 | R65: =(Q69 - Q65) / Q69 -> 0.29952083
A66: Financial Actual | B66: Surjek | C66: Revenues | D66: Q2 | E66: =SUMIFS('Data Repository Table'!$J:$J, 'Data Repository Table'!$A:$A, "Financial Actual", 'Data Repository Table'!$C:$C, "Surjek", 'Data Repository Table'!$B:$B, "Revenues", 'Data Repository Table'!$D:$D, ">=" & E$64, 'Data Repository Table'!$D:$D, "<" & EDATE(E$64, 1)) -> 17328051 | F66: =SUMIFS('Data Repository Table'!$J:$J, 'Data Repository Table'!$A:$A, "Financial Actual", 'Data Repository Table'!$C:$C, "Surjek", 'Data Repository Table'!$B:$B, "Revenues", 'Data Repository Table'!$D:$D, ">=" & F$64, 'Data Repository Table'!$D:$D, "<" & EDATE(F$64, 1)) -> 14604314 | G66: =SUMIFS('Data Repository Table'!$J:$J, 'Data Repository Table'!$A:$A, "Financial Actual", 'Data Repository Table'!$C:$C, "Surjek", 'Data Repository Table'!$B:$B, "Revenues", 'Data Repository Table'!$D:$D, ">=" & G$64, 'Data Repository Table'!$D:$D, "<" & EDATE(G$64, 1)) -> 16135900 | H66: =SUMIFS('Data Repository Table'!$J:$J, 'Data Repository Table'!$A:$A, "Financial Actual", 'Data Repository Table'!$C:$C, "Surjek", 'Data Repository Table'!$B:$B, "Revenues", 'Data Repository Table'!$D:$D, ">=" & H$64, 'Data Repository Table'!$D:$D, "<" & EDATE(H$64, 1)) -> 15151633 | I66: =SUMIFS('Data Repository Table'!$J:$J, 'Data Repository Table'!$A:$A, "Financial Actual", 'Data Repository Table'!$C:$C, "Surjek", 'Data Repository Table'!$B:$B, "Revenues", 'Data Repository Table'!$D:$D, ">=" & I$64, 'Data Repository Table'!$D:$D, "<" & EDATE(I$64, 1)) -> 13832901 | J66: =SUMIFS('Data Repository Table'!$J:$J, 'Data Repository Table'!$A:$A, "Financial Actual", 'Data Repository Table'!$C:$C, "Surjek", 'Data Repository Table'!$B:$B, "Revenues", 'Data Repository Table'!$D:$D, ">=" & J$64, 'Data Repository Table'!$D:$D, "<" & EDATE(J$64, 1)) -> 15562960 | K66: =SUMIFS('Data Repository Table'!$J:$J, 'Data Repository Table'!$A:$A, "Financial Actual", 'Data Repository Table'!$C:$C, "Surjek", 'Data Repository Table'!$B:$B, "Revenues", 'Data Repository Table'!$D:$D, ">=" & K$64, 'Data Repository Table'!$D:$D, "<" & EDATE(K$64, 1)) -> 22354058 | L66: =SUMIFS('Data Repository Table'!$J:$J, 'Data Repository Table'!$A:$A, "Financial Actual", 'Data Repository Table'!$C:$C, "Surjek", 'Data Repository Table'!$B:$B, "Revenues", 'Data Repository Table'!$D:$D, ">=" & L$64, 'Data Repository Table'!$D:$D, "<" & EDATE(L$64, 1)) -> 18580951 | M66: =SUMIFS('Data Repository Table'!$J:$J, 'Data Repository Table'!$A:$A, "Financial Actual", 'Data Repository Table'!$C:$C, "Surjek", 'Data Repository Table'!$B:$B, "Revenues", 'Data Repository Table'!$D:$D, ">=" & M$64, 'Data Repository Table'!$D:$D, "<" & EDATE(M$64, 1)) -> 19644681 | N66: 0 | O66: 0 | P66: 0 | Q66: =SUM(E66:P66) -> 1.5319545e+08 | R66: =(Q69 - Q66) / Q69 -> 0.24256417
A67: Financial Actual | B67: Surjek | C67: Revenues | D67: Q3 | E67: 0 | F67: 0 | G67: 0 | H67: =SUMIFS('Data Repository Table'!$J:$J, 'Data Repository Table'!$A:$A, "Financial Actual", 'Data Repository Table'!$C:$C, "Surjek", 'Data Repository Table'!$B:$B, "Revenues", 'Data Repository Table'!$D:$D, ">=" & H$64, 'Data Repository Table'!$D:$D, "<" & EDATE(H$64, 1)) -> 15151633 | I67: =SUMIFS('Data Repository Table'!$J:$J, 'Data Repository Table'!$A:$A, "Financial Actual", 'Data Repository Table'!$C:$C, "Surjek", 'Data Repository Table'!$B:$B, "Revenues", 'Data Repository Table'!$D:$D, ">=" & I$64, 'Data Repository Table'!$D:$D, "<" & EDATE(I$64, 1)) -> 13832901 | J67: =SUMIFS('Data Repository Table'!$J:$J, 'Data Repository Table'!$A:$A, "Financial Actual", 'Data Repository Table'!$C:$C, "Surjek", 'Data Repository Table'!$B:$B, "Revenues", 'Data Repository Table'!$D:$D, ">=" & J$64, 'Data Repository Table'!$D:$D, "<" & EDATE(J$64, 1)) -> 15562960 | K67: =SUMIFS('Data Repository Table'!$J:$J, 'Data Repository Table'!$A:$A, "Financial Actual", 'Data Repository Table'!$C:$C, "Surjek", 'Data Repository Table'!$B:$B, "Revenues", 'Data Repository Table'!$D:$D, ">=" & K$64, 'Data Repository Table'!$D:$D, "<" & EDATE(K$64, 1)) -> 22354058 | L67: =SUMIFS('Data Repository Table'!$J:$J, 'Data Repository Table'!$A:$A, "Financial Actual", 'Data Repository Table'!$C:$C, "Surjek", 'Data Repository Table'!$B:$B, "Revenues", 'Data Repository Table'!$D:$D, ">=" & L$64, 'Data Repository Table'!$D:$D, "<" & EDATE(L$64, 1)) -> 18580951 | M67: =SUMIFS('Data Repository Table'!$J:$J, 'Data Repository Table'!$A:$A, "Financial Actual", 'Data Repository Table'!$C:$C, "Surjek", 'Data Repository Table'!$B:$B, "Revenues", 'Data Repository Table'!$D:$D, ">=" & M$64, 'Data Repository Table'!$D:$D, "<" & EDATE(M$64, 1)) -> 19644681 | N67: =SUMIFS('Data Repository Table'!$J:$J, 'Data Repository Table'!$A:$A, "Financial Actual", 'Data Repository Table'!$C:$C, "Surjek", 'Data Repository Table'!$B:$B, "Revenues", 'Data Repository Table'!$D:$D, ">=" & N$64, 'Data Repository Table'!$D:$D, "<" & EDATE(N$64, 1)) -> 18268435 | O67: =SUMIFS('Data Repository Table'!$J:$J, 'Data Repository Table'!$A:$A, "Financial Actual", 'Data Repository Table'!$C:$C, "Surjek", 'Data Repository Table'!$B:$B, "Revenues", 'Data Repository Table'!$D:$D, ">=" & O$64, 'Data Repository Table'!$D:$D, "<" & EDATE(O$64, 1)) -> 14627298 | P67: =SUMIFS('Data Repository Table'!$J:$J, 'Data Repository Table'!$A:$A, "Financial Actual", 'Data Repository Table'!$C:$C, "Surjek", 'Data Repository Table'!$B:$B, "Revenues", 'Data Repository Table'!$D:$D, ">=" & P$64, 'Data Repository Table'!$D:$D, "<" & EDATE(P$64, 1)) -> 16164167 | Q67: =SUM(E67:P67) -> 1.5418708e+08 | R67: =(Q69 - Q67) / Q69 -> 0.23766128
A68: Financial Actual | B68: Surjek | C68: Revenues | D68: Q4 | E68: =SUMIFS('Data Repository Table'!$J:$J, 'Data Repository Table'!$A:$A, "Financial Actual", 'Data Repository Table'!$C:$C, "Surjek", 'Data Repository Table'!$B:$B, "Revenues", 'Data Repository Table'!$D:$D, ">=" & E$64, 'Data Repository Table'!$D:$D, "<" & EDATE(E$64, 1)) -> 17328051 | F68: =SUMIFS('Data Repository Table'!$J:$J, 'Data Repository Table'!$A:$A, "Financial Actual", 'Data Repository Table'!$C:$C, "Surjek", 'Data Repository Table'!$B:$B, "Revenues", 'Data Repository Table'!$D:$D, ">=" & F$64, 'Data Repository Table'!$D:$D, "<" & EDATE(F$64, 1)) -> 14604314 | G68: =SUMIFS('Data Repository Table'!$J:$J, 'Data Repository Table'!$A:$A, "Financial Actual", 'Data Repository Table'!$C:$C, "Surjek", 'Data Repository Table'!$B:$B, "Revenues", 'Data Repository Table'!$D:$D, ">=" & G$64, 'Data Repository Table'!$D:$D, "<" & EDATE(G$64, 1)) -> 16135900 | H68: 0 | I68: 0 | J68: 0 | K68: =SUMIFS('Data Repository Table'!$J:$J, 'Data Repository Table'!$A:$A, "Financial Actual", 'Data Repository Table'!$C:$C, "Surjek", 'Data Repository Table'!$B:$B, "Revenues", 'Data Repository Table'!$D:$D, ">=" & K$64, 'Data Repository Table'!$D:$D, "<" & EDATE(K$64, 1)) -> 22354058 | L68: =SUMIFS('Data Repository Table'!$J:$J, 'Data Repository Table'!$A:$A, "Financial Actual", 'Data Repository Table'!$C:$C, "Surjek", 'Data Repository Table'!$B:$B, "Revenues", 'Data Repository Table'!$D:$D, ">=" & L$64, 'Data Repository Table'!$D:$D, "<" & EDATE(L$64, 1)) -> 18580951 | M68: =SUMIFS('Data Repository Table'!$J:$J, 'Data Repository Table'!$A:$A, "Financial Actual", 'Data Repository Table'!$C:$C, "Surjek", 'Data Repository Table'!$B:$B, "Revenues", 'Data Repository Table'!$D:$D, ">=" & M$64, 'Data Repository Table'!$D:$D, "<" & EDATE(M$64, 1)) -> 19644681 | N68: =SUMIFS('Data Repository Table'!$J:$J, 'Data Repository Table'!$A:$A, "Financial Actual", 'Data Repository Table'!$C:$C, "Surjek", 'Data Repository Table'!$B:$B, "Revenues", 'Data Repository Table'!$D:$D, ">=" & N$64, 'Data Repository Table'!$D:$D, "<" & EDATE(N$64, 1)) -> 18268435 | O68: =SUMIFS('Data Repository Table'!$J:$J, 'Data Repository Table'!$A:$A, "Financial Actual", 'Data Repository Table'!$C:$C, "Surjek", 'Data Repository Table'!$B:$B, "Revenues", 'Data Repository Table'!$D:$D, ">=" & O$64, 'Data Repository Table'!$D:$D, "<" & EDATE(O$64, 1)) -> 14627298 | P68: =SUMIFS('Data Repository Table'!$J:$J, 'Data Repository Table'!$A:$A, "Financial Actual", 'Data Repository Table'!$C:$C, "Surjek", 'Data Repository Table'!$B:$B, "Revenues", 'Data Repository Table'!$D:$D, ">=" & P$64, 'Data Repository Table'!$D:$D, "<" & EDATE(P$64, 1)) -> 16164167 | Q68: =SUM(E68:P68) -> 1.5770786e+08 | R68: =(Q69 - Q68) / Q69 -> 0.22025372
D69: TOTAL with no outages | E69: =SUMIFS('Data Repository Table'!$J:$J, 'Data Repository Table'!$A:$A, "Financial Actual", 'Data Repository Table'!$C:$C, "Surjek", 'Data Repository Table'!$B:$B, "Revenues", 'Data Repository Table'!$D:$D, ">=" & E$64, 'Data Repository Table'!$D:$D, "<" & EDATE(E$64, 1)) -> 17328051 | F69: =SUMIFS('Data Repository Table'!$J:$J, 'Data Repository Table'!$A:$A, "Financial Actual", 'Data Repository Table'!$C:$C, "Surjek", 'Data Repository Table'!$B:$B, "Revenues", 'Data Repository Table'!$D:$D, ">=" & F$64, 'Data Repository Table'!$D:$D, "<" & EDATE(F$64, 1)) -> 14604314 | G69: =SUMIFS('Data Repository Table'!$J:$J, 'Data Repository Table'!$A:$A, "Financial Actual", 'Data Repository Table'!$C:$C, "Surjek", 'Data Repository Table'!$B:$B, "Revenues", 'Data Repository Table'!$D:$D, ">=" & G$64, 'Data Repository Table'!$D:$D, "<" & EDATE(G$64, 1)) -> 16135900 | H69: =SUMIFS('Data Repository Table'!$J:$J, 'Data Repository Table'!$A:$A, "Financial Actual", 'Data Repository Table'!$C:$C, "Surjek", 'Data Repository Table'!$B:$B, "Revenues", 'Data Repository Table'!$D:$D, ">=" & H$64, 'Data Repository Table'!$D:$D, "<" & EDATE(H$64, 1)) -> 15151633 | I69: =SUMIFS('Data Repository Table'!$J:$J, 'Data Repository Table'!$A:$A, "Financial Actual", 'Data Repository Table'!$C:$C, "Surjek", 'Data Repository Table'!$B:$B, "Revenues", 'Data Repository Table'!$D:$D, ">=" & I$64, 'Data Repository Table'!$D:$D, "<" & EDATE(I$64, 1)) -> 13832901 | J69: =SUMIFS('Data Repository Table'!$J:$J, 'Data Repository Table'!$A:$A, "Financial Actual", 'Data Repository Table'!$C:$C, "Surjek", 'Data Repository Table'!$B:$B, "Revenues", 'Data Repository Table'!$D:$D, ">=" & J$64, 'Data Repository Table'!$D:$D, "<" & EDATE(J$64, 1)) -> 15562960 | K69: =SUMIFS('Data Repository Table'!$J:$J, 'Data Repository Table'!$A:$A, "Financial Actual", 'Data Repository Table'!$C:$C, "Surjek", 'Data Repository Table'!$B:$B, "Revenues", 'Data Repository Table'!$D:$D, ">=" & K$64, 'Data Repository Table'!$D:$D, "<" & EDATE(K$64, 1)) -> 22354058 | L69: =SUMIFS('Data Repository Table'!$J:$J, 'Data Repository Table'!$A:$A, "Financial Actual", 'Data Repository Table'!$C:$C, "Surjek", 'Data Repository Table'!$B:$B, "Revenues", 'Data Repository Table'!$D:$D, ">=" & L$64, 'Data Repository Table'!$D:$D, "<" & EDATE(L$64, 1)) -> 18580951 | ... P69: =SUMIFS('Data Repository Table'!$J:$J, 'Data Repository Table'!$A:$A, "Financial Actual", 'Data Repository Table'!$C:$C, "Surjek", 'Data Repository Table'!$B:$B, "Revenues", 'Data Repository Table'!$D:$D, ">=" & P$64, 'Data Repository Table'!$D:$D, "<" & EDATE(P$64, 1)) -> 16164167 | Q69: =SUM(E69:P69) -> 2.0225535e+08
A70: Note: We've included an additional hint below which shows what your graphic might look like upon completion (With the exception being we have removed the axes for you). It might also be helpful for you to calculate the 'Revenue % Reduction' to see how much less revenue you might receive if you perform the outage in a particular quarter.
A89: Place your answer here | C89: The % Revenue Reduction shows how much money is lost in each scenario compared to the best-case scenario where all months generate revenue. It’s calculated by comparing the actual revenue (with outages or $0 months) to the maximum possible revenue ($202,255,349.17). A higher percentage means greater revenue loss. A lower percentage means the scenario has less financial impact and is more favorable.
A91: Well done! You've now completed the Economics Case Study Analysis! Let's top this off now by creating an insightful story we can present back to Southern Water Corps. Management using the templates provided.

Sheet Economic Cost Analysis
A1: Economic Cost Analysis - Part II
A2: In Economic Data Analysis, we seek to make use of as much data as possible to help us better understand and extract key business insights.
A3: In the previous section, we've tackled the concepts of elastic and inelastic products. This helps us understand which products are more susceptible to price swings, and which ones are less susceptible.
A4: Now a common phrase in economic data analysis is, "We need to compare things in an apples to apples like methodology". With Southern Water Corp, we have a bunch of economic and financial data. We're going to use the tools of Economic Data Analysis to create insights from this and identify which of our three desalination plants are most cost-effective.
A5: Previously we've calculated the proportion of revenues that are generated, the expenses and the associated amount of water production. Using economics - we are now going to combine all this information together and create an economic metric to evaluate each plants performance to create our own 'apples-to-apples' comparison.
A7: Let's get started!
A9: For each of the three Southern Water Corp. Desalination Plants, we have an econometric measure called the Desalinated Plant Cost to Produce, or Cost to Produce for short.
A10: The Cost to Produce ties together the different costs for each Plant and enables us to create a metric to evaluate how cost-effective the plant is.
A11: Q4. Please calculate the Cost to Produce for each of the three (3) desalination plants below using the following formula per plant: Plant Cost to Produce = ( Chemical Costs + Facility Costs + Operational Maintenance Costs + Labour Costs ) / (Total Volume of Water Produced for the Month (GL) * 1,000) (To Convert to Mega-Litres from Giga Litres)
A12: Note: If you have difficulty understanding how to calculate the Cost to Produce, it may be helpful to create a Value Driver Tree to showcase how all the drivers are connected.
A13: Account Type | B13: Unit | C13: Value Driver | D13: Cost Centre | E13: Cost Centre Element | G13: 41456 | H13: 41487 | I13: 41518 | J13: 41548 | K13: 41579 | L13: 41609 | M13: 41640 | N13: 41671 | O13: 41699 | P13: 41730 | Q13: 41760 | R13: 41791 | S13: Total
A16: Financial Actuals | B16: Kootha | C16: Expenses | D16: Chemical Costs | E16: Chem-Exp (001) | G16: =SUMIFS( 'Data Repository Table'!$J:$J, 'Data Repository Table'!$A:$A, "Financial Actual", 'Data Repository Table'!$C:$C, "Kootha", 'Data Repository Table'!$B:$B, "Expenses", 'Data Repository Table'!$G:$G, "Chemical Costs", 'Data Repository Table'!$H:$H, "Chem-Exp (001)", 'Data Repository Table'!$D:$D, G13 ) -> 593751.84 | H16: =SUMIFS( 'Data Repository Table'!$J:$J, 'Data Repository Table'!$A:$A, "Financial Actual", 'Data Repository Table'!$C:$C, "Kootha", 'Data Repository Table'!$B:$B, "Expenses", 'Data Repository Table'!$G:$G, "Chemical Costs", 'Data Repository Table'!$H:$H, "Chem-Exp (001)", 'Data Repository Table'!$D:$D, H13 ) -> 820393.03 | I16: =SUMIFS( 'Data Repository Table'!$J:$J, 'Data Repository Table'!$A:$A, "Financial Actual", 'Data Repository Table'!$C:$C, "Kootha", 'Data Repository Table'!$B:$B, "Expenses", 'Data Repository Table'!$G:$G, "Chemical Costs", 'Data Repository Table'!$H:$H, "Chem-Exp (001)", 'Data Repository Table'!$D:$D, I13 ) -> 642291.58 | J16: =SUMIFS( 'Data Repository Table'!$J:$J, 'Data Repository Table'!$A:$A, "Financial Actual", 'Data Repository Table'!$C:$C, "Kootha", 'Data Repository Table'!$B:$B, "Expenses", 'Data Repository Table'!$G:$G, "Chemical Costs", 'Data Repository Table'!$H:$H, "Chem-Exp (001)", 'Data Repository Table'!$D:$D, J13 ) -> 609639.97 | K16: =SUMIFS( 'Data Repository Table'!$J:$J, 'Data Repository Table'!$A:$A, "Financial Actual", 'Data Repository Table'!$C:$C, "Kootha", 'Data Repository Table'!$B:$B, "Expenses", 'Data Repository Table'!$G:$G, "Chemical Costs", 'Data Repository Table'!$H:$H, "Chem-Exp (001)", 'Data Repository Table'!$D:$D, K13 ) -> 626073.17 | L16: =SUMIFS( 'Data Repository Table'!$J:$J, 'Data Repository Table'!$A:$A, "Financial Actual", 'Data Repository Table'!$C:$C, "Kootha", 'Data Repository Table'!$B:$B, "Expenses", 'Data Repository Table'!$G:$G, "Chemical Costs", 'Data Repository Table'!$H:$H, "Chem-Exp (001)", 'Data Repository Table'!$D:$D, L13 ) -> 602153.38 | M16: =SUMIFS( 'Data Repository Table'!$J:$J, 'Data Repository Table'!$A:$A, "Financial Actual", 'Data Repository Table'!$C:$C, "Kootha", 'Data Repository Table'!$B:$B, "Expenses", 'Data Repository Table'!$G:$G, "Chemical Costs", 'Data Repository Table'!$H:$H, "Chem-Exp (001)", 'Data Repository Table'!$D:$D, M13 ) -> 1146144 | N16: =SUMIFS( 'Data Repository Table'!$J:$J, 'Data Repository Table'!$A:$A, "Financial Actual", 'Data Repository Table'!$C:$C, "Kootha", 'Data Repository Table'!$B:$B, "Expenses", 'Data Repository Table'!$G:$G, "Chemical Costs", 'Data Repository Table'!$H:$H, "Chem-Exp (001)", 'Data Repository Table'!$D:$D, N13 ) -> 964931.84 | ... R16: =SUMIFS( 'Data Repository Table'!$J:$J, 'Data Repository Table'!$A:$A, "Financial Actual", 'Data Repository Table'!$C:$C, "Kootha", 'Data Repository Table'!$B:$B, "Expenses", 'Data Repository Table'!$G:$G, "Chemical Costs", 'Data Repository Table'!$H:$H, "Chem-Exp (001)", 'Data Repository Table'!$D:$D, R13 ) -> 1168045.2 | S16: =SUM(G16:R16) -> 10125518
A17: Financial Actuals | B17: Kootha | C17: Expenses | D17: Facility Costs | E17: Utility-Exp (002) - Heating | G17: =SUMIFS( 'Data Repository Table'!$J:$J, 'Data Repository Table'!$A:$A, "Financial Actual", 'Data Repository Table'!$C:$C, "Kootha", 'Data Repository Table'!$B:$B, "Expenses", 'Data Repository Table'!$G:$G, "Facility Costs", 'Data Repository Table'!$H:$H, "Utility-Exp (002) - Heating", 'Data Repository Table'!$D:$D, G$13 ) -> 276807.38 | H17: =SUMIFS( 'Data Repository Table'!$J:$J, 'Data Repository Table'!$A:$A, "Financial Actual", 'Data Repository Table'!$C:$C, "Kootha", 'Data Repository Table'!$B:$B, "Expenses", 'Data Repository Table'!$G:$G, "Facility Costs", 'Data Repository Table'!$H:$H, "Utility-Exp (002) - Heating", 'Data Repository Table'!$D:$D, H$13 ) -> 382467.61 | I17: =SUMIFS( 'Data Repository Table'!$J:$J, 'Data Repository Table'!$A:$A, "Financial Actual", 'Data Repository Table'!$C:$C, "Kootha", 'Data Repository Table'!$B:$B, "Expenses", 'Data Repository Table'!$G:$G, "Facility Costs", 'Data Repository Table'!$H:$H, "Utility-Exp (002) - Heating", 'Data Repository Table'!$D:$D, I$13 ) -> 299436.64 | J17: =SUMIFS( 'Data Repository Table'!$J:$J, 'Data Repository Table'!$A:$A, "Financial Actual", 'Data Repository Table'!$C:$C, "Kootha", 'Data Repository Table'!$B:$B, "Expenses", 'Data Repository Table'!$G:$G, "Facility Costs", 'Data Repository Table'!$H:$H, "Utility-Exp (002) - Heating", 'Data Repository Table'!$D:$D, J$13 ) -> 284214.44 | K17: =SUMIFS( 'Data Repository Table'!$J:$J, 'Data Repository Table'!$A:$A, "Financial Actual", 'Data Repository Table'!$C:$C, "Kootha", 'Data Repository Table'!$B:$B, "Expenses", 'Data Repository Table'!$G:$G, "Facility Costs", 'Data Repository Table'!$H:$H, "Utility-Exp (002) - Heating", 'Data Repository Table'!$D:$D, K$13 ) -> 291875.6 | L17: =SUMIFS( 'Data Repository Table'!$J:$J, 'Data Repository Table'!$A:$A, "Financial Actual", 'Data Repository Table'!$C:$C, "Kootha", 'Data Repository Table'!$B:$B, "Expenses", 'Data Repository Table'!$G:$G, "Facility Costs", 'Data Repository Table'!$H:$H, "Utility-Exp (002) - Heating", 'Data Repository Table'!$D:$D, L$13 ) -> 280724.19 | M17: =SUMIFS( 'Data Repository Table'!$J:$J, 'Data Repository Table'!$A:$A, "Financial Actual", 'Data Repository Table'!$C:$C, "Kootha", 'Data Repository Table'!$B:$B, "Expenses", 'Data Repository Table'!$G:$G, "Facility Costs", 'Data Repository Table'!$H:$H, "Utility-Exp (002) - Heating", 'Data Repository Table'!$D:$D, M$13 ) -> 534332.86 | N17: =SUMIFS( 'Data Repository Table'!$J:$J, 'Data Repository Table'!$A:$A, "Financial Actual", 'Data Repository Table'!$C:$C, "Kootha", 'Data Repository Table'!$B:$B, "Expenses", 'Data Repository Table'!$G:$G, "Facility Costs", 'Data Repository Table'!$H:$H, "Utility-Exp (002) - Heating", 'Data Repository Table'!$D:$D, N$13 ) -> 449851.67 | ... R17: =SUMIFS( 'Data Repository Table'!$J:$J, 'Data Repository Table'!$A:$A, "Financial Actual", 'Data Repository Table'!$C:$C, "Kootha", 'Data Repository Table'!$B:$B, "Expenses", 'Data Repository Table'!$G:$G, "Facility Costs", 'Data Repository Table'!$H:$H, "Utility-Exp (002) - Heating", 'Data Repository Table'!$D:$D, R$13 ) -> 544543.23 | S17: =SUM(G17:R17) -> 4720521.2
A18: Financial Actuals | B18: Kootha | C18: Expenses | D18: Facility Costs | E18: Utility-Exp (002) - Electricity | G18: =SUMIFS( 'Data Repository Table'!$J:$J, 'Data Repository Table'!$A:$A, "Financial Actual", 'Data Repository Table'!$C:$C, "Kootha", 'Data Repository Table'!$B:$B, "Expenses", 'Data Repository Table'!$G:$G, "Facility Costs", 'Data Repository Table'!$H:$H, "Utility-Exp (002) - Electricity", 'Data Repository Table'!$D:$D, G$13 ) -> 415211.08 | H18: =SUMIFS( 'Data Repository Table'!$J:$J, 'Data Repository Table'!$A:$A, "Financial Actual", 'Data Repository Table'!$C:$C, "Kootha", 'Data Repository Table'!$B:$B, "Expenses", 'Data Repository Table'!$G:$G, "Facility Costs", 'Data Repository Table'!$H:$H, "Utility-Exp (002) - Electricity", 'Data Repository Table'!$D:$D, H$13 ) -> 573701.42 | I18: =SUMIFS( 'Data Repository Table'!$J:$J, 'Data Repository Table'!$A:$A, "Financial Actual", 'Data Repository Table'!$C:$C, "Kootha", 'Data Repository Table'!$B:$B, "Expenses", 'Data Repository Table'!$G:$G, "Facility Costs", 'Data Repository Table'!$H:$H, "Utility-Exp (002) - Electricity", 'Data Repository Table'!$D:$D, I$13 ) -> 449154.95 | J18: =SUMIFS( 'Data Repository Table'!$J:$J, 'Data Repository Table'!$A:$A, "Financial Actual", 'Data Repository Table'!$C:$C, "Kootha", 'Data Repository Table'!$B:$B, "Expenses", 'Data Repository Table'!$G:$G, "Facility Costs", 'Data Repository Table'!$H:$H, "Utility-Exp (002) - Electricity", 'Data Repository Table'!$D:$D, J$13 ) -> 426321.66 | K18: =SUMIFS( 'Data Repository Table'!$J:$J, 'Data Repository Table'!$A:$A, "Financial Actual", 'Data Repository Table'!$C:$C, "Kootha", 'Data Repository Table'!$B:$B, "Expenses", 'Data Repository Table'!$G:$G, "Facility Costs", 'Data Repository Table'!$H:$H, "Utility-Exp (002) - Electricity", 'Data Repository Table'!$D:$D, K$13 ) -> 437813.4 | L18: =SUMIFS( 'Data Repository Table'!$J:$J, 'Data Repository Table'!$A:$A, "Financial Actual", 'Data Repository Table'!$C:$C, "Kootha", 'Data Repository Table'!$B:$B, "Expenses", 'Data Repository Table'!$G:$G, "Facility Costs", 'Data Repository Table'!$H:$H, "Utility-Exp (002) - Electricity", 'Data Repository Table'!$D:$D, L$13 ) -> 421086.28 | M18: =SUMIFS( 'Data Repository Table'!$J:$J, 'Data Repository Table'!$A:$A, "Financial Actual", 'Data Repository Table'!$C:$C, "Kootha", 'Data Repository Table'!$B:$B, "Expenses", 'Data Repository Table'!$G:$G, "Facility Costs", 'Data Repository Table'!$H:$H, "Utility-Exp (002) - Electricity", 'Data Repository Table'!$D:$D, M$13 ) -> 801499.29 | N18: =SUMIFS( 'Data Repository Table'!$J:$J, 'Data Repository Table'!$A:$A, "Financial Actual", 'Data Repository Table'!$C:$C, "Kootha", 'Data Repository Table'!$B:$B, "Expenses", 'Data Repository Table'!$G:$G, "Facility Costs", 'Data Repository Table'!$H:$H, "Utility-Exp (002) - Electricity", 'Data Repository Table'!$D:$D, N$13 ) -> 674777.51 | ... R18: =SUMIFS( 'Data Repository Table'!$J:$J, 'Data Repository Table'!$A:$A, "Financial Actual", 'Data Repository Table'!$C:$C, "Kootha", 'Data Repository Table'!$B:$B, "Expenses", 'Data Repository Table'!$G:$G, "Facility Costs", 'Data Repository Table'!$H:$H, "Utility-Exp (002) - Electricity", 'Data Repository Table'!$D:$D, R$13 ) -> 816814.84 | S18: =SUM(G18:R18) -> 7080781.8
A19: Financial Actuals | B19: Kootha | C19: Expenses | D19: Operational Maintenance Costs | E19: Plant Maintenance (001) | G19: =SUMIFS( 'Data Repository Table'!$J:$J, 'Data Repository Table'!$A:$A, "Financial Actual", 'Data Repository Table'!$C:$C, "Kootha", 'Data Repository Table'!$B:$B, "Expenses", 'Data Repository Table'!$G:$G, "Operational Maintenance Costs", 'Data Repository Table'!$H:$H, "Plant Maintenance (001)", 'Data Repository Table'!$D:$D, G$13 ) -> 360688.41 | H19: =SUMIFS( 'Data Repository Table'!$J:$J, 'Data Repository Table'!$A:$A, "Financial Actual", 'Data Repository Table'!$C:$C, "Kootha", 'Data Repository Table'!$B:$B, "Expenses", 'Data Repository Table'!$G:$G, "Operational Maintenance Costs", 'Data Repository Table'!$H:$H, "Plant Maintenance (001)", 'Data Repository Table'!$D:$D, H$13 ) -> 498366.89 | I19: =SUMIFS( 'Data Repository Table'!$J:$J, 'Data Repository Table'!$A:$A, "Financial Actual", 'Data Repository Table'!$C:$C, "Kootha", 'Data Repository Table'!$B:$B, "Expenses", 'Data Repository Table'!$G:$G, "Operational Maintenance Costs", 'Data Repository Table'!$H:$H, "Plant Maintenance (001)", 'Data Repository Table'!$D:$D, I$13 ) -> 390175.01 | J19: =SUMIFS( 'Data Repository Table'!$J:$J, 'Data Repository Table'!$A:$A, "Financial Actual", 'Data Repository Table'!$C:$C, "Kootha", 'Data Repository Table'!$B:$B, "Expenses", 'Data Repository Table'!$G:$G, "Operational Maintenance Costs", 'Data Repository Table'!$H:$H, "Plant Maintenance (001)", 'Data Repository Table'!$D:$D, J$13 ) -> 370340.03 | K19: =SUMIFS( 'Data Repository Table'!$J:$J, 'Data Repository Table'!$A:$A, "Financial Actual", 'Data Repository Table'!$C:$C, "Kootha", 'Data Repository Table'!$B:$B, "Expenses", 'Data Repository Table'!$G:$G, "Operational Maintenance Costs", 'Data Repository Table'!$H:$H, "Plant Maintenance (001)", 'Data Repository Table'!$D:$D, K$13 ) -> 380322.76 | L19: =SUMIFS( 'Data Repository Table'!$J:$J, 'Data Repository Table'!$A:$A, "Financial Actual", 'Data Repository Table'!$C:$C, "Kootha", 'Data Repository Table'!$B:$B, "Expenses", 'Data Repository Table'!$G:$G, "Operational Maintenance Costs", 'Data Repository Table'!$H:$H, "Plant Maintenance (001)", 'Data Repository Table'!$D:$D, L$13 ) -> 365792.12 | M19: =SUMIFS( 'Data Repository Table'!$J:$J, 'Data Repository Table'!$A:$A, "Financial Actual", 'Data Repository Table'!$C:$C, "Kootha", 'Data Repository Table'!$B:$B, "Expenses", 'Data Repository Table'!$G:$G, "Operational Maintenance Costs", 'Data Repository Table'!$H:$H, "Plant Maintenance (001)", 'Data Repository Table'!$D:$D, M$13 ) -> 459526.26 | N19: =SUMIFS( 'Data Repository Table'!$J:$J, 'Data Repository Table'!$A:$A, "Financial Actual", 'Data Repository Table'!$C:$C, "Kootha", 'Data Repository Table'!$B:$B, "Expenses", 'Data Repository Table'!$G:$G, "Operational Maintenance Costs", 'Data Repository Table'!$H:$H, "Plant Maintenance (001)", 'Data Repository Table'!$D:$D, N$13 ) -> 386872.44 | ... R19: =SUMIFS( 'Data Repository Table'!$J:$J, 'Data Repository Table'!$A:$A, "Financial Actual", 'Data Repository Table'!$C:$C, "Kootha", 'Data Repository Table'!$B:$B, "Expenses", 'Data Repository Table'!$G:$G, "Operational Maintenance Costs", 'Data Repository Table'!$H:$H, "Plant Maintenance (001)", 'Data Repository Table'!$D:$D, R$13 ) -> 468307.18 | S19: =SUM(G19:R19) -> 4863981.2
A20: Financial Actuals | B20: Kootha | C20: Expenses | D20: Operational Maintenance Costs | E20: Plant Outages (002) | G20: =SUMIFS( 'Data Repository Table'!$J:$J, 'Data Repository Table'!$A:$A, "Financial Actual", 'Data Repository Table'!$C:$C, "Kootha", 'Data Repository Table'!$B:$B, "Expenses", 'Data Repository Table'!$G:$G, "Operational Maintenance Costs", 'Data Repository Table'!$H:$H, "Plant Outages (002)", 'Data Repository Table'!$D:$D, G$13 ) -> 226478.77 | H20: =SUMIFS( 'Data Repository Table'!$J:$J, 'Data Repository Table'!$A:$A, "Financial Actual", 'Data Repository Table'!$C:$C, "Kootha", 'Data Repository Table'!$B:$B, "Expenses", 'Data Repository Table'!$G:$G, "Operational Maintenance Costs", 'Data Repository Table'!$H:$H, "Plant Outages (002)", 'Data Repository Table'!$D:$D, H$13 ) -> 312928.05 | I20: =SUMIFS( 'Data Repository Table'!$J:$J, 'Data Repository Table'!$A:$A, "Financial Actual", 'Data Repository Table'!$C:$C, "Kootha", 'Data Repository Table'!$B:$B, "Expenses", 'Data Repository Table'!$G:$G, "Operational Maintenance Costs", 'Data Repository Table'!$H:$H, "Plant Outages (002)", 'Data Repository Table'!$D:$D, I$13 ) -> 244993.61 | J20: =SUMIFS( 'Data Repository Table'!$J:$J, 'Data Repository Table'!$A:$A, "Financial Actual", 'Data Repository Table'!$C:$C, "Kootha", 'Data Repository Table'!$B:$B, "Expenses", 'Data Repository Table'!$G:$G, "Operational Maintenance Costs", 'Data Repository Table'!$H:$H, "Plant Outages (002)", 'Data Repository Table'!$D:$D, J$13 ) -> 232539.09 | K20: =SUMIFS( 'Data Repository Table'!$J:$J, 'Data Repository Table'!$A:$A, "Financial Actual", 'Data Repository Table'!$C:$C, "Kootha", 'Data Repository Table'!$B:$B, "Expenses", 'Data Repository Table'!$G:$G, "Operational Maintenance Costs", 'Data Repository Table'!$H:$H, "Plant Outages (002)", 'Data Repository Table'!$D:$D, K$13 ) -> 238807.31 | L20: =SUMIFS( 'Data Repository Table'!$J:$J, 'Data Repository Table'!$A:$A, "Financial Actual", 'Data Repository Table'!$C:$C, "Kootha", 'Data Repository Table'!$B:$B, "Expenses", 'Data Repository Table'!$G:$G, "Operational Maintenance Costs", 'Data Repository Table'!$H:$H, "Plant Outages (002)", 'Data Repository Table'!$D:$D, L$13 ) -> 229683.42 | M20: =SUMIFS( 'Data Repository Table'!$J:$J, 'Data Repository Table'!$A:$A, "Financial Actual", 'Data Repository Table'!$C:$C, "Kootha", 'Data Repository Table'!$B:$B, "Expenses", 'Data Repository Table'!$G:$G, "Operational Maintenance Costs", 'Data Repository Table'!$H:$H, "Plant Outages (002)", 'Data Repository Table'!$D:$D, M$13 ) -> 288539.74 | N20: =SUMIFS( 'Data Repository Table'!$J:$J, 'Data Repository Table'!$A:$A, "Financial Actual", 'Data Repository Table'!$C:$C, "Kootha", 'Data Repository Table'!$B:$B, "Expenses", 'Data Repository Table'!$G:$G, "Operational Maintenance Costs", 'Data Repository Table'!$H:$H, "Plant Outages (002)", 'Data Repository Table'!$D:$D, N$13 ) -> 242919.9 | ... R20: =SUMIFS( 'Data Repository Table'!$J:$J, 'Data Repository Table'!$A:$A, "Financial Actual", 'Data Repository Table'!$C:$C, "Kootha", 'Data Repository Table'!$B:$B, "Expenses", 'Data Repository Table'!$G:$G, "Operational Maintenance Costs", 'Data Repository Table'!$H:$H, "Plant Outages (002)", 'Data Repository Table'!$D:$D, R$13 ) -> 294053.34 | S20: =SUM(G20:R20) -> 3054127.7
A21: Financial Actuals | B21: Kootha | C21: Expenses | D21: Operational Maintenance Costs | E21: Plant Op. Costs (003) | G21: =SUMIFS( 'Data Repository Table'!$J:$J, 'Data Repository Table'!$A:$A, "Financial Actual", 'Data Repository Table'!$C:$C, "Kootha", 'Data Repository Table'!$B:$B, "Expenses", 'Data Repository Table'!$G:$G, "Operational Maintenance Costs", 'Data Repository Table'!$H:$H, "Plant Op. Costs (003)", 'Data Repository Table'!$D:$D, G$13 ) -> 255837.13 | H21: =SUMIFS( 'Data Repository Table'!$J:$J, 'Data Repository Table'!$A:$A, "Financial Actual", 'Data Repository Table'!$C:$C, "Kootha", 'Data Repository Table'!$B:$B, "Expenses", 'Data Repository Table'!$G:$G, "Operational Maintenance Costs", 'Data Repository Table'!$H:$H, "Plant Op. Costs (003)", 'Data Repository Table'!$D:$D, H$13 ) -> 353492.8 | I21: =SUMIFS( 'Data Repository Table'!$J:$J, 'Data Repository Table'!$A:$A, "Financial Actual", 'Data Repository Table'!$C:$C, "Kootha", 'Data Repository Table'!$B:$B, "Expenses", 'Data Repository Table'!$G:$G, "Operational Maintenance Costs", 'Data Repository Table'!$H:$H, "Plant Op. Costs (003)", 'Data Repository Table'!$D:$D, I$13 ) -> 276752.04 | J21: =SUMIFS( 'Data Repository Table'!$J:$J, 'Data Repository Table'!$A:$A, "Financial Actual", 'Data Repository Table'!$C:$C, "Kootha", 'Data Repository Table'!$B:$B, "Expenses", 'Data Repository Table'!$G:$G, "Operational Maintenance Costs", 'Data Repository Table'!$H:$H, "Plant Op. Costs (003)", 'Data Repository Table'!$D:$D, J$13 ) -> 262683.04 | K21: =SUMIFS( 'Data Repository Table'!$J:$J, 'Data Repository Table'!$A:$A, "Financial Actual", 'Data Repository Table'!$C:$C, "Kootha", 'Data Repository Table'!$B:$B, "Expenses", 'Data Repository Table'!$G:$G, "Operational Maintenance Costs", 'Data Repository Table'!$H:$H, "Plant Op. Costs (003)", 'Data Repository Table'!$D:$D, K$13 ) -> 269763.82 | L21: =SUMIFS( 'Data Repository Table'!$J:$J, 'Data Repository Table'!$A:$A, "Financial Actual", 'Data Repository Table'!$C:$C, "Kootha", 'Data Repository Table'!$B:$B, "Expenses", 'Data Repository Table'!$G:$G, "Operational Maintenance Costs", 'Data Repository Table'!$H:$H, "Plant Op. Costs (003)", 'Data Repository Table'!$D:$D, L$13 ) -> 259457.2 | M21: =SUMIFS( 'Data Repository Table'!$J:$J, 'Data Repository Table'!$A:$A, "Financial Actual", 'Data Repository Table'!$C:$C, "Kootha", 'Data Repository Table'!$B:$B, "Expenses", 'Data Repository Table'!$G:$G, "Operational Maintenance Costs", 'Data Repository Table'!$H:$H, "Plant Op. Costs (003)", 'Data Repository Table'!$D:$D, M$13 ) -> 325943.04 | N21: =SUMIFS( 'Data Repository Table'!$J:$J, 'Data Repository Table'!$A:$A, "Financial Actual", 'Data Repository Table'!$C:$C, "Kootha", 'Data Repository Table'!$B:$B, "Expenses", 'Data Repository Table'!$G:$G, "Operational Maintenance Costs", 'Data Repository Table'!$H:$H, "Plant Op. Costs (003)", 'Data Repository Table'!$D:$D, N$13 ) -> 274409.52 | ... R21: =SUMIFS( 'Data Repository Table'!$J:$J, 'Data Repository Table'!$A:$A, "Financial Actual", 'Data Repository Table'!$C:$C, "Kootha", 'Data Repository Table'!$B:$B, "Expenses", 'Data Repository Table'!$G:$G, "Operational Maintenance Costs", 'Data Repository Table'!$H:$H, "Plant Op. Costs (003)", 'Data Repository Table'!$D:$D, R$13 ) -> 332171.37 | S21: =SUM(G21:R21) -> 3450033.2
A22: Financial Actuals | B22: Kootha | C22: Expenses | D22: Operational Maintenance Costs | E22: Plant Admin Costs (004) | G22: =SUMIFS( 'Data Repository Table'!$J:$J, 'Data Repository Table'!$A:$A, "Financial Actual", 'Data Repository Table'!$C:$C, "Kootha", 'Data Repository Table'!$B:$B, "Expenses", 'Data Repository Table'!$G:$G, "Operational Maintenance Costs", 'Data Repository Table'!$H:$H, "Plant Admin Costs (004)", 'Data Repository Table'!$D:$D, G$13 ) -> 176150.15 | H22: =SUMIFS( 'Data Repository Table'!$J:$J, 'Data Repository Table'!$A:$A, "Financial Actual", 'Data Repository Table'!$C:$C, "Kootha", 'Data Repository Table'!$B:$B, "Expenses", 'Data Repository Table'!$G:$G, "Operational Maintenance Costs", 'Data Repository Table'!$H:$H, "Plant Admin Costs (004)", 'Data Repository Table'!$D:$D, H$13 ) -> 243388.48 | I22: =SUMIFS( 'Data Repository Table'!$J:$J, 'Data Repository Table'!$A:$A, "Financial Actual", 'Data Repository Table'!$C:$C, "Kootha", 'Data Repository Table'!$B:$B, "Expenses", 'Data Repository Table'!$G:$G, "Operational Maintenance Costs", 'Data Repository Table'!$H:$H, "Plant Admin Costs (004)", 'Data Repository Table'!$D:$D, I$13 ) -> 190550.59 | J22: =SUMIFS( 'Data Repository Table'!$J:$J, 'Data Repository Table'!$A:$A, "Financial Actual", 'Data Repository Table'!$C:$C, "Kootha", 'Data Repository Table'!$B:$B, "Expenses", 'Data Repository Table'!$G:$G, "Operational Maintenance Costs", 'Data Repository Table'!$H:$H, "Plant Admin Costs (004)", 'Data Repository Table'!$D:$D, J$13 ) -> 180863.73 | K22: =SUMIFS( 'Data Repository Table'!$J:$J, 'Data Repository Table'!$A:$A, "Financial Actual", 'Data Repository Table'!$C:$C, "Kootha", 'Data Repository Table'!$B:$B, "Expenses", 'Data Repository Table'!$G:$G, "Operational Maintenance Costs", 'Data Repository Table'!$H:$H, "Plant Admin Costs (004)", 'Data Repository Table'!$D:$D, K$13 ) -> 185739.02 | L22: =SUMIFS( 'Data Repository Table'!$J:$J, 'Data Repository Table'!$A:$A, "Financial Actual", 'Data Repository Table'!$C:$C, "Kootha", 'Data Repository Table'!$B:$B, "Expenses", 'Data Repository Table'!$G:$G, "Operational Maintenance Costs", 'Data Repository Table'!$H:$H, "Plant Admin Costs (004)", 'Data Repository Table'!$D:$D, L$13 ) -> 178642.66 | M22: =SUMIFS( 'Data Repository Table'!$J:$J, 'Data Repository Table'!$A:$A, "Financial Actual", 'Data Repository Table'!$C:$C, "Kootha", 'Data Repository Table'!$B:$B, "Expenses", 'Data Repository Table'!$G:$G, "Operational Maintenance Costs", 'Data Repository Table'!$H:$H, "Plant Admin Costs (004)", 'Data Repository Table'!$D:$D, M$13 ) -> 224419.8 | N22: =SUMIFS( 'Data Repository Table'!$J:$J, 'Data Repository Table'!$A:$A, "Financial Actual", 'Data Repository Table'!$C:$C, "Kootha", 'Data Repository Table'!$B:$B, "Expenses", 'Data Repository Table'!$G:$G, "Operational Maintenance Costs", 'Data Repository Table'!$H:$H, "Plant Admin Costs (004)", 'Data Repository Table'!$D:$D, N$13 ) -> 188937.7 | ... R22: =SUMIFS( 'Data Repository Table'!$J:$J, 'Data Repository Table'!$A:$A, "Financial Actual", 'Data Repository Table'!$C:$C, "Kootha", 'Data Repository Table'!$B:$B, "Expenses", 'Data Repository Table'!$G:$G, "Operational Maintenance Costs", 'Data Repository Table'!$H:$H, "Plant Admin Costs (004)", 'Data Repository Table'!$D:$D, R$13 ) -> 228708.16 | S22: =SUM(G22:R22) -> 2375432.7
A23: Financial Actuals | B23: Kootha | C23: Expenses | D23: Labour Costs | E23: Labour-Costs (001) | G23: =SUMIFS( 'Data Repository Table'!$J:$J, 'Data Repository Table'!$A:$A, "Financial Actual", 'Data Repository Table'!$C:$C, "Kootha", 'Data Repository Table'!$B:$B, "Expenses", 'Data Repository Table'!$G:$G, "Labour Costs", 'Data Repository Table'!$H:$H, "Labour-Costs (001)", 'Data Repository Table'!$D:$D, G$13 ) -> 1153364.1 | H23: =SUMIFS( 'Data Repository Table'!$J:$J, 'Data Repository Table'!$A:$A, "Financial Actual", 'Data Repository Table'!$C:$C, "Kootha", 'Data Repository Table'!$B:$B, "Expenses", 'Data Repository Table'!$G:$G, "Labour Costs", 'Data Repository Table'!$H:$H, "Labour-Costs (001)", 'Data Repository Table'!$D:$D, H$13 ) -> 1593615.1 | I23: =SUMIFS( 'Data Repository Table'!$J:$J, 'Data Repository Table'!$A:$A, "Financial Actual", 'Data Repository Table'!$C:$C, "Kootha", 'Data Repository Table'!$B:$B, "Expenses", 'Data Repository Table'!$G:$G, "Labour Costs", 'Data Repository Table'!$H:$H, "Labour-Costs (001)", 'Data Repository Table'!$D:$D, I$13 ) -> 1247652.6 | J23: =SUMIFS( 'Data Repository Table'!$J:$J, 'Data Repository Table'!$A:$A, "Financial Actual", 'Data Repository Table'!$C:$C, "Kootha", 'Data Repository Table'!$B:$B, "Expenses", 'Data Repository Table'!$G:$G, "Labour Costs", 'Data Repository Table'!$H:$H, "Labour-Costs (001)", 'Data Repository Table'!$D:$D, J$13 ) -> 1184226.8 | K23: =SUMIFS( 'Data Repository Table'!$J:$J, 'Data Repository Table'!$A:$A, "Financial Actual", 'Data Repository Table'!$C:$C, "Kootha", 'Data Repository Table'!$B:$B, "Expenses", 'Data Repository Table'!$G:$G, "Labour Costs", 'Data Repository Table'!$H:$H, "Labour-Costs (001)", 'Data Repository Table'!$D:$D, K$13 ) -> 1216148.3 | L23: =SUMIFS( 'Data Repository Table'!$J:$J, 'Data Repository Table'!$A:$A, "Financial Actual", 'Data Repository Table'!$C:$C, "Kootha", 'Data Repository Table'!$B:$B, "Expenses", 'Data Repository Table'!$G:$G, "Labour Costs", 'Data Repository Table'!$H:$H, "Labour-Costs (001)", 'Data Repository Table'!$D:$D, L$13 ) -> 1169684.1 | M23: =SUMIFS( 'Data Repository Table'!$J:$J, 'Data Repository Table'!$A:$A, "Financial Actual", 'Data Repository Table'!$C:$C, "Kootha", 'Data Repository Table'!$B:$B, "Expenses", 'Data Repository Table'!$G:$G, "Labour Costs", 'Data Repository Table'!$H:$H, "Labour-Costs (001)", 'Data Repository Table'!$D:$D, M$13 ) -> 1469415.4 | N23: =SUMIFS( 'Data Repository Table'!$J:$J, 'Data Repository Table'!$A:$A, "Financial Actual", 'Data Repository Table'!$C:$C, "Kootha", 'Data Repository Table'!$B:$B, "Expenses", 'Data Repository Table'!$G:$G, "Labour Costs", 'Data Repository Table'!$H:$H, "Labour-Costs (001)", 'Data Repository Table'!$D:$D, N$13 ) -> 1237092.1 | ... R23: =SUMIFS( 'Data Repository Table'!$J:$J, 'Data Repository Table'!$A:$A, "Financial Actual", 'Data Repository Table'!$C:$C, "Kootha", 'Data Repository Table'!$B:$B, "Expenses", 'Data Repository Table'!$G:$G, "Labour Costs", 'Data Repository Table'!$H:$H, "Labour-Costs (001)", 'Data Repository Table'!$D:$D, R$13 ) -> 1497493.9 | S23: =SUM(G23:R23) -> 15553428
A24: Water Production Actuals | B24: Kootha | G24: =SUMIFS( 'Data Repository Table'!$J:$J, 'Data Repository Table'!$A:$A, "Water Production Actuals", 'Data Repository Table'!$C:$C, "Kootha", 'Data Repository Table'!$D:$D, G$13 ) -> 181.93329 | H24: =SUMIFS( 'Data Repository Table'!$J:$J, 'Data Repository Table'!$A:$A, "Water Production Actuals", 'Data Repository Table'!$C:$C, "Kootha", 'Data Repository Table'!$D:$D, H$13 ) -> 187.44394 | I24: =SUMIFS( 'Data Repository Table'!$J:$J, 'Data Repository Table'!$A:$A, "Water Production Actuals", 'Data Repository Table'!$C:$C, "Kootha", 'Data Repository Table'!$D:$D, I$13 ) -> 184.77366 | J24: =SUMIFS( 'Data Repository Table'!$J:$J, 'Data Repository Table'!$A:$A, "Water Production Actuals", 'Data Repository Table'!$C:$C, "Kootha", 'Data Repository Table'!$D:$D, J$13 ) -> 191.54109 | K24: =SUMIFS( 'Data Repository Table'!$J:$J, 'Data Repository Table'!$A:$A, "Water Production Actuals", 'Data Repository Table'!$C:$C, "Kootha", 'Data Repository Table'!$D:$D, K$13 ) -> 98.096062 | L24: =SUMIFS( 'Data Repository Table'!$J:$J, 'Data Repository Table'!$A:$A, "Water Production Actuals", 'Data Repository Table'!$C:$C, "Kootha", 'Data Repository Table'!$D:$D, L$13 ) -> 185.30685 | M24: =SUMIFS( 'Data Repository Table'!$J:$J, 'Data Repository Table'!$A:$A, "Water Production Actuals", 'Data Repository Table'!$C:$C, "Kootha", 'Data Repository Table'!$D:$D, M$13 ) -> 186.90144 | N24: =SUMIFS( 'Data Repository Table'!$J:$J, 'Data Repository Table'!$A:$A, "Water Production Actuals", 'Data Repository Table'!$C:$C, "Kootha", 'Data Repository Table'!$D:$D, N$13 ) -> 158.58677 | ... R24: =SUMIFS( 'Data Repository Table'!$J:$J, 'Data Repository Table'!$A:$A, "Water Production Actuals", 'Data Repository Table'!$C:$C, "Kootha", 'Data Repository Table'!$D:$D, R$13 ) -> 142.50872 | S24: =SUM(G24:R24) -> 2048.8404
B25: Kootha | E25: Desalination Cost to Produce ($/ML) | G25: =SUM(G$16:G$23)/(G$24 * 1000) -> 19.008554 | H25: =SUM(H$16:H$23)/(H$24 * 1000) -> 25.492173 | I25: =SUM(I$16:I$23)/(I$24 * 1000) -> 20.246431 | J25: =SUM(J$16:J$23)/(J$24 * 1000) -> 18.538209 | K25: =SUM(K$16:K$23)/(K$24 * 1000) -> 37.173189 | L25: =SUM(L$16:L$23)/(L$24 * 1000) -> 18.926571 | M25: =SUM(M$16:M$23)/(M$24 * 1000) -> 28.08871 | N25: =SUM(N$16:N$23)/(N$24 * 1000) -> 27.869871 | ... R25: =SUM(R$16:R$23)/(R$24 * 1000) -> 37.542526 | S25: =SUM(S16:S23)/S24 -> 25001.374
A27: Financial Actuals | B27: Surjek | C27: Expenses | D27: Chemical Costs | E27: Chem-Exp (001) | G27: =SUMIFS( 'Data Repository Table'!$J:$J, 'Data Repository Table'!$A:$A, "Financial Actual", 'Data Repository Table'!$C:$C, "Surjek", 'Data Repository Table'!$B:$B, "Expenses", 'Data Repository Table'!$G:$G, "Chemical Costs", 'Data Repository Table'!$H:$H, "Chem-Exp (001)", 'Data Repository Table'!$D:$D, G$13 ) -> 2533034.5 | H27: =SUMIFS( 'Data Repository Table'!$J:$J, 'Data Repository Table'!$A:$A, "Financial Actual", 'Data Repository Table'!$C:$C, "Surjek", 'Data Repository Table'!$B:$B, "Expenses", 'Data Repository Table'!$G:$G, "Chemical Costs", 'Data Repository Table'!$H:$H, "Chem-Exp (001)", 'Data Repository Table'!$D:$D, H$13 ) -> 3051574.2 | I27: =SUMIFS( 'Data Repository Table'!$J:$J, 'Data Repository Table'!$A:$A, "Financial Actual", 'Data Repository Table'!$C:$C, "Surjek", 'Data Repository Table'!$B:$B, "Expenses", 'Data Repository Table'!$G:$G, "Chemical Costs", 'Data Repository Table'!$H:$H, "Chem-Exp (001)", 'Data Repository Table'!$D:$D, I$13 ) -> 3084202.8 | J27: =SUMIFS( 'Data Repository Table'!$J:$J, 'Data Repository Table'!$A:$A, "Financial Actual", 'Data Repository Table'!$C:$C, "Surjek", 'Data Repository Table'!$B:$B, "Expenses", 'Data Repository Table'!$G:$G, "Chemical Costs", 'Data Repository Table'!$H:$H, "Chem-Exp (001)", 'Data Repository Table'!$D:$D, J$13 ) -> 4135202.8 | K27: =SUMIFS( 'Data Repository Table'!$J:$J, 'Data Repository Table'!$A:$A, "Financial Actual", 'Data Repository Table'!$C:$C, "Surjek", 'Data Repository Table'!$B:$B, "Expenses", 'Data Repository Table'!$G:$G, "Chemical Costs", 'Data Repository Table'!$H:$H, "Chem-Exp (001)", 'Data Repository Table'!$D:$D, K$13 ) -> 4473275.9 | L27: =SUMIFS( 'Data Repository Table'!$J:$J, 'Data Repository Table'!$A:$A, "Financial Actual", 'Data Repository Table'!$C:$C, "Surjek", 'Data Repository Table'!$B:$B, "Expenses", 'Data Repository Table'!$G:$G, "Chemical Costs", 'Data Repository Table'!$H:$H, "Chem-Exp (001)", 'Data Repository Table'!$D:$D, L$13 ) -> 3464957.9 | M27: =SUMIFS( 'Data Repository Table'!$J:$J, 'Data Repository Table'!$A:$A, "Financial Actual", 'Data Repository Table'!$C:$C, "Surjek", 'Data Repository Table'!$B:$B, "Expenses", 'Data Repository Table'!$G:$G, "Chemical Costs", 'Data Repository Table'!$H:$H, "Chem-Exp (001)", 'Data Repository Table'!$D:$D, M$13 ) -> 4049642.8 | N27: =SUMIFS( 'Data Repository Table'!$J:$J, 'Data Repository Table'!$A:$A, "Financial Actual", 'Data Repository Table'!$C:$C, "Surjek", 'Data Repository Table'!$B:$B, "Expenses", 'Data Repository Table'!$G:$G, "Chemical Costs", 'Data Repository Table'!$H:$H, "Chem-Exp (001)", 'Data Repository Table'!$D:$D, N$13 ) -> 4767948.2 | ... R27: =SUMIFS( 'Data Repository Table'!$J:$J, 'Data Repository Table'!$A:$A, "Financial Actual", 'Data Repository Table'!$C:$C, "Surjek", 'Data Repository Table'!$B:$B, "Expenses", 'Data Repository Table'!$G:$G, "Chemical Costs", 'Data Repository Table'!$H:$H, "Chem-Exp (001)", 'Data Repository Table'!$D:$D, R$13 ) -> 2269805.2 | S27: =SUM(G27:R27) -> 46326013
A28: Financial Actuals | B28: Surjek | C28: Expenses | D28: Facility Costs | E28: Utility-Exp (002) - Heating | G28: =SUMIFS( 'Data Repository Table'!$J:$J, 'Data Repository Table'!$A:$A, "Financial Actual", 'Data Repository Table'!$C:$C, "Surjek", 'Data Repository Table'!$B:$B, "Expenses", 'Data Repository Table'!$G:$G, "Facility Costs", 'Data Repository Table'!$H:$H, "Utility-Exp (002) - Heating", 'Data Repository Table'!$D:$D, G$13 ) -> 1266517.3 | H28: =SUMIFS( 'Data Repository Table'!$J:$J, 'Data Repository Table'!$A:$A, "Financial Actual", 'Data Repository Table'!$C:$C, "Surjek", 'Data Repository Table'!$B:$B, "Expenses", 'Data Repository Table'!$G:$G, "Facility Costs", 'Data Repository Table'!$H:$H, "Utility-Exp (002) - Heating", 'Data Repository Table'!$D:$D, H$13 ) -> 1525787.1 | I28: =SUMIFS( 'Data Repository Table'!$J:$J, 'Data Repository Table'!$A:$A, "Financial Actual", 'Data Repository Table'!$C:$C, "Surjek", 'Data Repository Table'!$B:$B, "Expenses", 'Data Repository Table'!$G:$G, "Facility Costs", 'Data Repository Table'!$H:$H, "Utility-Exp (002) - Heating", 'Data Repository Table'!$D:$D, I$13 ) -> 1542101.4 | J28: =SUMIFS( 'Data Repository Table'!$J:$J, 'Data Repository Table'!$A:$A, "Financial Actual", 'Data Repository Table'!$C:$C, "Surjek", 'Data Repository Table'!$B:$B, "Expenses", 'Data Repository Table'!$G:$G, "Facility Costs", 'Data Repository Table'!$H:$H, "Utility-Exp (002) - Heating", 'Data Repository Table'!$D:$D, J$13 ) -> 2067601.4 | K28: =SUMIFS( 'Data Repository Table'!$J:$J, 'Data Repository Table'!$A:$A, "Financial Actual", 'Data Repository Table'!$C:$C, "Surjek", 'Data Repository Table'!$B:$B, "Expenses", 'Data Repository Table'!$G:$G, "Facility Costs", 'Data Repository Table'!$H:$H, "Utility-Exp (002) - Heating", 'Data Repository Table'!$D:$D, K$13 ) -> 2236637.9 | L28: =SUMIFS( 'Data Repository Table'!$J:$J, 'Data Repository Table'!$A:$A, "Financial Actual", 'Data Repository Table'!$C:$C, "Surjek", 'Data Repository Table'!$B:$B, "Expenses", 'Data Repository Table'!$G:$G, "Facility Costs", 'Data Repository Table'!$H:$H, "Utility-Exp (002) - Heating", 'Data Repository Table'!$D:$D, L$13 ) -> 1732479 | M28: =SUMIFS( 'Data Repository Table'!$J:$J, 'Data Repository Table'!$A:$A, "Financial Actual", 'Data Repository Table'!$C:$C, "Surjek", 'Data Repository Table'!$B:$B, "Expenses", 'Data Repository Table'!$G:$G, "Facility Costs", 'Data Repository Table'!$H:$H, "Utility-Exp (002) - Heating", 'Data Repository Table'!$D:$D, M$13 ) -> 2024821.4 | N28: =SUMIFS( 'Data Repository Table'!$J:$J, 'Data Repository Table'!$A:$A, "Financial Actual", 'Data Repository Table'!$C:$C, "Surjek", 'Data Repository Table'!$B:$B, "Expenses", 'Data Repository Table'!$G:$G, "Facility Costs", 'Data Repository Table'!$H:$H, "Utility-Exp (002) - Heating", 'Data Repository Table'!$D:$D, N$13 ) -> 2383974.1 | ... R28: =SUMIFS( 'Data Repository Table'!$J:$J, 'Data Repository Table'!$A:$A, "Financial Actual", 'Data Repository Table'!$C:$C, "Surjek", 'Data Repository Table'!$B:$B, "Expenses", 'Data Repository Table'!$G:$G, "Facility Costs", 'Data Repository Table'!$H:$H, "Utility-Exp (002) - Heating", 'Data Repository Table'!$D:$D, R$13 ) -> 1134902.6 | S28: =SUM(G28:R28) -> 23163006
A29: Financial Actuals | B29: Surjek | C29: Expenses | D29: Facility Costs | E29: Utility-Exp (002) - Electricity | G29: =SUMIFS( 'Data Repository Table'!$J:$J, 'Data Repository Table'!$A:$A, "Financial Actual", 'Data Repository Table'!$C:$C, "Surjek", 'Data Repository Table'!$B:$B, "Expenses", 'Data Repository Table'!$G:$G, "Facility Costs", 'Data Repository Table'!$H:$H, "Utility-Exp (002) - Electricity", 'Data Repository Table'!$D:$D, G$13 ) -> 1055431 | H29: =SUMIFS( 'Data Repository Table'!$J:$J, 'Data Repository Table'!$A:$A, "Financial Actual", 'Data Repository Table'!$C:$C, "Surjek", 'Data Repository Table'!$B:$B, "Expenses", 'Data Repository Table'!$G:$G, "Facility Costs", 'Data Repository Table'!$H:$H, "Utility-Exp (002) - Electricity", 'Data Repository Table'!$D:$D, H$13 ) -> 1271489.2 | I29: =SUMIFS( 'Data Repository Table'!$J:$J, 'Data Repository Table'!$A:$A, "Financial Actual", 'Data Repository Table'!$C:$C, "Surjek", 'Data Repository Table'!$B:$B, "Expenses", 'Data Repository Table'!$G:$G, "Facility Costs", 'Data Repository Table'!$H:$H, "Utility-Exp (002) - Electricity", 'Data Repository Table'!$D:$D, I$13 ) -> 1285084.5 | J29: =SUMIFS( 'Data Repository Table'!$J:$J, 'Data Repository Table'!$A:$A, "Financial Actual", 'Data Repository Table'!$C:$C, "Surjek", 'Data Repository Table'!$B:$B, "Expenses", 'Data Repository Table'!$G:$G, "Facility Costs", 'Data Repository Table'!$H:$H, "Utility-Exp (002) - Electricity", 'Data Repository Table'!$D:$D, J$13 ) -> 1723001.2 | K29: =SUMIFS( 'Data Repository Table'!$J:$J, 'Data Repository Table'!$A:$A, "Financial Actual", 'Data Repository Table'!$C:$C, "Surjek", 'Data Repository Table'!$B:$B, "Expenses", 'Data Repository Table'!$G:$G, "Facility Costs", 'Data Repository Table'!$H:$H, "Utility-Exp (002) - Electricity", 'Data Repository Table'!$D:$D, K$13 ) -> 1863865 | L29: =SUMIFS( 'Data Repository Table'!$J:$J, 'Data Repository Table'!$A:$A, "Financial Actual", 'Data Repository Table'!$C:$C, "Surjek", 'Data Repository Table'!$B:$B, "Expenses", 'Data Repository Table'!$G:$G, "Facility Costs", 'Data Repository Table'!$H:$H, "Utility-Exp (002) - Electricity", 'Data Repository Table'!$D:$D, L$13 ) -> 1443732.5 | M29: =SUMIFS( 'Data Repository Table'!$J:$J, 'Data Repository Table'!$A:$A, "Financial Actual", 'Data Repository Table'!$C:$C, "Surjek", 'Data Repository Table'!$B:$B, "Expenses", 'Data Repository Table'!$G:$G, "Facility Costs", 'Data Repository Table'!$H:$H, "Utility-Exp (002) - Electricity", 'Data Repository Table'!$D:$D, M$13 ) -> 1687351.2 | N29: =SUMIFS( 'Data Repository Table'!$J:$J, 'Data Repository Table'!$A:$A, "Financial Actual", 'Data Repository Table'!$C:$C, "Surjek", 'Data Repository Table'!$B:$B, "Expenses", 'Data Repository Table'!$G:$G, "Facility Costs", 'Data Repository Table'!$H:$H, "Utility-Exp (002) - Electricity", 'Data Repository Table'!$D:$D, N$13 ) -> 1986645.1 | ... R29: =SUMIFS( 'Data Repository Table'!$J:$J, 'Data Repository Table'!$A:$A, "Financial Actual", 'Data Repository Table'!$C:$C, "Surjek", 'Data Repository Table'!$B:$B, "Expenses", 'Data Repository Table'!$G:$G, "Facility Costs", 'Data Repository Table'!$H:$H, "Utility-Exp (002) - Electricity", 'Data Repository Table'!$D:$D, R$13 ) -> 945752.15 | S29: =SUM(G29:R29) -> 19302505
A30: Financial Actuals | B30: Surjek | C30: Expenses | D30: Operational Maintenance Costs | E30: Plant Maintenance (001) | G30: =SUMIFS( 'Data Repository Table'!$J:$J, 'Data Repository Table'!$A:$A, "Financial Actual", 'Data Repository Table'!$C:$C, "Surjek", 'Data Repository Table'!$B:$B, "Expenses", 'Data Repository Table'!$G:$G, "Operational Maintenance Costs", 'Data Repository Table'!$H:$H, "Plant Maintenance (001)", 'Data Repository Table'!$D:$D, G$13 ) -> 996326.91 | H30: =SUMIFS( 'Data Repository Table'!$J:$J, 'Data Repository Table'!$A:$A, "Financial Actual", 'Data Repository Table'!$C:$C, "Surjek", 'Data Repository Table'!$B:$B, "Expenses", 'Data Repository Table'!$G:$G, "Operational Maintenance Costs", 'Data Repository Table'!$H:$H, "Plant Maintenance (001)", 'Data Repository Table'!$D:$D, H$13 ) -> 1200285.8 | I30: =SUMIFS( 'Data Repository Table'!$J:$J, 'Data Repository Table'!$A:$A, "Financial Actual", 'Data Repository Table'!$C:$C, "Surjek", 'Data Repository Table'!$B:$B, "Expenses", 'Data Repository Table'!$G:$G, "Operational Maintenance Costs", 'Data Repository Table'!$H:$H, "Plant Maintenance (001)", 'Data Repository Table'!$D:$D, I$13 ) -> 1213119.8 | J30: =SUMIFS( 'Data Repository Table'!$J:$J, 'Data Repository Table'!$A:$A, "Financial Actual", 'Data Repository Table'!$C:$C, "Surjek", 'Data Repository Table'!$B:$B, "Expenses", 'Data Repository Table'!$G:$G, "Operational Maintenance Costs", 'Data Repository Table'!$H:$H, "Plant Maintenance (001)", 'Data Repository Table'!$D:$D, J$13 ) -> 1626513.1 | K30: =SUMIFS( 'Data Repository Table'!$J:$J, 'Data Repository Table'!$A:$A, "Financial Actual", 'Data Repository Table'!$C:$C, "Surjek", 'Data Repository Table'!$B:$B, "Expenses", 'Data Repository Table'!$G:$G, "Operational Maintenance Costs", 'Data Repository Table'!$H:$H, "Plant Maintenance (001)", 'Data Repository Table'!$D:$D, K$13 ) -> 1759488.5 | L30: =SUMIFS( 'Data Repository Table'!$J:$J, 'Data Repository Table'!$A:$A, "Financial Actual", 'Data Repository Table'!$C:$C, "Surjek", 'Data Repository Table'!$B:$B, "Expenses", 'Data Repository Table'!$G:$G, "Operational Maintenance Costs", 'Data Repository Table'!$H:$H, "Plant Maintenance (001)", 'Data Repository Table'!$D:$D, L$13 ) -> 1362883.5 | M30: =SUMIFS( 'Data Repository Table'!$J:$J, 'Data Repository Table'!$A:$A, "Financial Actual", 'Data Repository Table'!$C:$C, "Surjek", 'Data Repository Table'!$B:$B, "Expenses", 'Data Repository Table'!$G:$G, "Operational Maintenance Costs", 'Data Repository Table'!$H:$H, "Plant Maintenance (001)", 'Data Repository Table'!$D:$D, M$13 ) -> 1592859.5 | N30: =SUMIFS( 'Data Repository Table'!$J:$J, 'Data Repository Table'!$A:$A, "Financial Actual", 'Data Repository Table'!$C:$C, "Surjek", 'Data Repository Table'!$B:$B, "Expenses", 'Data Repository Table'!$G:$G, "Operational Maintenance Costs", 'Data Repository Table'!$H:$H, "Plant Maintenance (001)", 'Data Repository Table'!$D:$D, N$13 ) -> 1875393 | ... R30: =SUMIFS( 'Data Repository Table'!$J:$J, 'Data Repository Table'!$A:$A, "Financial Actual", 'Data Repository Table'!$C:$C, "Surjek", 'Data Repository Table'!$B:$B, "Expenses", 'Data Repository Table'!$G:$G, "Operational Maintenance Costs", 'Data Repository Table'!$H:$H, "Plant Maintenance (001)", 'Data Repository Table'!$D:$D, R$13 ) -> 892790.03 | S30: =SUM(G30:R30) -> 18221565
A31: Financial Actuals | B31: Surjek | C31: Expenses | D31: Operational Maintenance Costs | E31: Plant Outages (002) | G31: =SUMIFS( 'Data Repository Table'!$J:$J, 'Data Repository Table'!$A:$A, "Financial Actual", 'Data Repository Table'!$C:$C, "Surjek", 'Data Repository Table'!$B:$B, "Expenses", 'Data Repository Table'!$G:$G, "Operational Maintenance Costs", 'Data Repository Table'!$H:$H, "Plant Outages (002)", 'Data Repository Table'!$D:$D, G$13 ) -> 869931.04 | H31: =SUMIFS( 'Data Repository Table'!$J:$J, 'Data Repository Table'!$A:$A, "Financial Actual", 'Data Repository Table'!$C:$C, "Surjek", 'Data Repository Table'!$B:$B, "Expenses", 'Data Repository Table'!$G:$G, "Operational Maintenance Costs", 'Data Repository Table'!$H:$H, "Plant Outages (002)", 'Data Repository Table'!$D:$D, H$13 ) -> 1048015.4 | I31: =SUMIFS( 'Data Repository Table'!$J:$J, 'Data Repository Table'!$A:$A, "Financial Actual", 'Data Repository Table'!$C:$C, "Surjek", 'Data Repository Table'!$B:$B, "Expenses", 'Data Repository Table'!$G:$G, "Operational Maintenance Costs", 'Data Repository Table'!$H:$H, "Plant Outages (002)", 'Data Repository Table'!$D:$D, I$13 ) -> 1059221.1 | J31: =SUMIFS( 'Data Repository Table'!$J:$J, 'Data Repository Table'!$A:$A, "Financial Actual", 'Data Repository Table'!$C:$C, "Surjek", 'Data Repository Table'!$B:$B, "Expenses", 'Data Repository Table'!$G:$G, "Operational Maintenance Costs", 'Data Repository Table'!$H:$H, "Plant Outages (002)", 'Data Repository Table'!$D:$D, J$13 ) -> 1420170.6 | K31: =SUMIFS( 'Data Repository Table'!$J:$J, 'Data Repository Table'!$A:$A, "Financial Actual", 'Data Repository Table'!$C:$C, "Surjek", 'Data Repository Table'!$B:$B, "Expenses", 'Data Repository Table'!$G:$G, "Operational Maintenance Costs", 'Data Repository Table'!$H:$H, "Plant Outages (002)", 'Data Repository Table'!$D:$D, K$13 ) -> 1536276.6 | L31: =SUMIFS( 'Data Repository Table'!$J:$J, 'Data Repository Table'!$A:$A, "Financial Actual", 'Data Repository Table'!$C:$C, "Surjek", 'Data Repository Table'!$B:$B, "Expenses", 'Data Repository Table'!$G:$G, "Operational Maintenance Costs", 'Data Repository Table'!$H:$H, "Plant Outages (002)", 'Data Repository Table'!$D:$D, L$13 ) -> 785390.46 | M31: =SUMIFS( 'Data Repository Table'!$J:$J, 'Data Repository Table'!$A:$A, "Financial Actual", 'Data Repository Table'!$C:$C, "Surjek", 'Data Repository Table'!$B:$B, "Expenses", 'Data Repository Table'!$G:$G, "Operational Maintenance Costs", 'Data Repository Table'!$H:$H, "Plant Outages (002)", 'Data Repository Table'!$D:$D, M$13 ) -> 734335.23 | N31: =SUMIFS( 'Data Repository Table'!$J:$J, 'Data Repository Table'!$A:$A, "Financial Actual", 'Data Repository Table'!$C:$C, "Surjek", 'Data Repository Table'!$B:$B, "Expenses", 'Data Repository Table'!$G:$G, "Operational Maintenance Costs", 'Data Repository Table'!$H:$H, "Plant Outages (002)", 'Data Repository Table'!$D:$D, N$13 ) -> 864587.94 | ... R31: =SUMIFS( 'Data Repository Table'!$J:$J, 'Data Repository Table'!$A:$A, "Financial Actual", 'Data Repository Table'!$C:$C, "Surjek", 'Data Repository Table'!$B:$B, "Expenses", 'Data Repository Table'!$G:$G, "Operational Maintenance Costs", 'Data Repository Table'!$H:$H, "Plant Outages (002)", 'Data Repository Table'!$D:$D, R$13 ) -> 514489.17 | S31: =SUM(G31:R31) -> 11461092
A32: Financial Actuals | B32: Surjek | C32: Expenses | D32: Operational Maintenance Costs | E32: Plant Op. Costs (003) | G32: =SUMIFS( 'Data Repository Table'!$J:$J, 'Data Repository Table'!$A:$A, "Financial Actual", 'Data Repository Table'!$C:$C, "Surjek", 'Data Repository Table'!$B:$B, "Expenses", 'Data Repository Table'!$G:$G, "Operational Maintenance Costs", 'Data Repository Table'!$H:$H, "Plant Op. Costs (003)", 'Data Repository Table'!$D:$D, G$13 ) -> 921103.46 | H32: =SUMIFS( 'Data Repository Table'!$J:$J, 'Data Repository Table'!$A:$A, "Financial Actual", 'Data Repository Table'!$C:$C, "Surjek", 'Data Repository Table'!$B:$B, "Expenses", 'Data Repository Table'!$G:$G, "Operational Maintenance Costs", 'Data Repository Table'!$H:$H, "Plant Op. Costs (003)", 'Data Repository Table'!$D:$D, H$13 ) -> 1109663.3 | I32: =SUMIFS( 'Data Repository Table'!$J:$J, 'Data Repository Table'!$A:$A, "Financial Actual", 'Data Repository Table'!$C:$C, "Surjek", 'Data Repository Table'!$B:$B, "Expenses", 'Data Repository Table'!$G:$G, "Operational Maintenance Costs", 'Data Repository Table'!$H:$H, "Plant Op. Costs (003)", 'Data Repository Table'!$D:$D, I$13 ) -> 1121528.3 | J32: =SUMIFS( 'Data Repository Table'!$J:$J, 'Data Repository Table'!$A:$A, "Financial Actual", 'Data Repository Table'!$C:$C, "Surjek", 'Data Repository Table'!$B:$B, "Expenses", 'Data Repository Table'!$G:$G, "Operational Maintenance Costs", 'Data Repository Table'!$H:$H, "Plant Op. Costs (003)", 'Data Repository Table'!$D:$D, J$13 ) -> 1503710.1 | K32: =SUMIFS( 'Data Repository Table'!$J:$J, 'Data Repository Table'!$A:$A, "Financial Actual", 'Data Repository Table'!$C:$C, "Surjek", 'Data Repository Table'!$B:$B, "Expenses", 'Data Repository Table'!$G:$G, "Operational Maintenance Costs", 'Data Repository Table'!$H:$H, "Plant Op. Costs (003)", 'Data Repository Table'!$D:$D, K$13 ) -> 1626645.8 | L32: =SUMIFS( 'Data Repository Table'!$J:$J, 'Data Repository Table'!$A:$A, "Financial Actual", 'Data Repository Table'!$C:$C, "Surjek", 'Data Repository Table'!$B:$B, "Expenses", 'Data Repository Table'!$G:$G, "Operational Maintenance Costs", 'Data Repository Table'!$H:$H, "Plant Op. Costs (003)", 'Data Repository Table'!$D:$D, L$13 ) -> 831589.9 | M32: =SUMIFS( 'Data Repository Table'!$J:$J, 'Data Repository Table'!$A:$A, "Financial Actual", 'Data Repository Table'!$C:$C, "Surjek", 'Data Repository Table'!$B:$B, "Expenses", 'Data Repository Table'!$G:$G, "Operational Maintenance Costs", 'Data Repository Table'!$H:$H, "Plant Op. Costs (003)", 'Data Repository Table'!$D:$D, M$13 ) -> 777531.42 | N32: =SUMIFS( 'Data Repository Table'!$J:$J, 'Data Repository Table'!$A:$A, "Financial Actual", 'Data Repository Table'!$C:$C, "Surjek", 'Data Repository Table'!$B:$B, "Expenses", 'Data Repository Table'!$G:$G, "Operational Maintenance Costs", 'Data Repository Table'!$H:$H, "Plant Op. Costs (003)", 'Data Repository Table'!$D:$D, N$13 ) -> 915446.06 | ... R32: =SUMIFS( 'Data Repository Table'!$J:$J, 'Data Repository Table'!$A:$A, "Financial Actual", 'Data Repository Table'!$C:$C, "Surjek", 'Data Repository Table'!$B:$B, "Expenses", 'Data Repository Table'!$G:$G, "Operational Maintenance Costs", 'Data Repository Table'!$H:$H, "Plant Op. Costs (003)", 'Data Repository Table'!$D:$D, R$13 ) -> 544753.24 | S32: =SUM(G32:R32) -> 12135274
A33: Financial Actuals | B33: Surjek | C33: Expenses | D33: Operational Maintenance Costs | E33: Plant Admin Costs (004) | G33: =SUMIFS( 'Data Repository Table'!$J:$J, 'Data Repository Table'!$A:$A, "Financial Actual", 'Data Repository Table'!$C:$C, "Surjek", 'Data Repository Table'!$B:$B, "Expenses", 'Data Repository Table'!$G:$G, "Operational Maintenance Costs", 'Data Repository Table'!$H:$H, "Plant Admin Costs (004)", 'Data Repository Table'!$D:$D, G$13 ) -> 498931.04 | H33: =SUMIFS( 'Data Repository Table'!$J:$J, 'Data Repository Table'!$A:$A, "Financial Actual", 'Data Repository Table'!$C:$C, "Surjek", 'Data Repository Table'!$B:$B, "Expenses", 'Data Repository Table'!$G:$G, "Operational Maintenance Costs", 'Data Repository Table'!$H:$H, "Plant Admin Costs (004)", 'Data Repository Table'!$D:$D, H$13 ) -> 601067.64 | I33: =SUMIFS( 'Data Repository Table'!$J:$J, 'Data Repository Table'!$A:$A, "Financial Actual", 'Data Repository Table'!$C:$C, "Surjek", 'Data Repository Table'!$B:$B, "Expenses", 'Data Repository Table'!$G:$G, "Operational Maintenance Costs", 'Data Repository Table'!$H:$H, "Plant Admin Costs (004)", 'Data Repository Table'!$D:$D, I$13 ) -> 607494.48 | J33: =SUMIFS( 'Data Repository Table'!$J:$J, 'Data Repository Table'!$A:$A, "Financial Actual", 'Data Repository Table'!$C:$C, "Surjek", 'Data Repository Table'!$B:$B, "Expenses", 'Data Repository Table'!$G:$G, "Operational Maintenance Costs", 'Data Repository Table'!$H:$H, "Plant Admin Costs (004)", 'Data Repository Table'!$D:$D, J$13 ) -> 814509.64 | K33: =SUMIFS( 'Data Repository Table'!$J:$J, 'Data Repository Table'!$A:$A, "Financial Actual", 'Data Repository Table'!$C:$C, "Surjek", 'Data Repository Table'!$B:$B, "Expenses", 'Data Repository Table'!$G:$G, "Operational Maintenance Costs", 'Data Repository Table'!$H:$H, "Plant Admin Costs (004)", 'Data Repository Table'!$D:$D, K$13 ) -> 881099.8 | L33: =SUMIFS( 'Data Repository Table'!$J:$J, 'Data Repository Table'!$A:$A, "Financial Actual", 'Data Repository Table'!$C:$C, "Surjek", 'Data Repository Table'!$B:$B, "Expenses", 'Data Repository Table'!$G:$G, "Operational Maintenance Costs", 'Data Repository Table'!$H:$H, "Plant Admin Costs (004)", 'Data Repository Table'!$D:$D, L$13 ) -> 450444.53 | M33: =SUMIFS( 'Data Repository Table'!$J:$J, 'Data Repository Table'!$A:$A, "Financial Actual", 'Data Repository Table'!$C:$C, "Surjek", 'Data Repository Table'!$B:$B, "Expenses", 'Data Repository Table'!$G:$G, "Operational Maintenance Costs", 'Data Repository Table'!$H:$H, "Plant Admin Costs (004)", 'Data Repository Table'!$D:$D, M$13 ) -> 421162.85 | N33: =SUMIFS( 'Data Repository Table'!$J:$J, 'Data Repository Table'!$A:$A, "Financial Actual", 'Data Repository Table'!$C:$C, "Surjek", 'Data Repository Table'!$B:$B, "Expenses", 'Data Repository Table'!$G:$G, "Operational Maintenance Costs", 'Data Repository Table'!$H:$H, "Plant Admin Costs (004)", 'Data Repository Table'!$D:$D, N$13 ) -> 495866.62 | ... R33: =SUMIFS( 'Data Repository Table'!$J:$J, 'Data Repository Table'!$A:$A, "Financial Actual", 'Data Repository Table'!$C:$C, "Surjek", 'Data Repository Table'!$B:$B, "Expenses", 'Data Repository Table'!$G:$G, "Operational Maintenance Costs", 'Data Repository Table'!$H:$H, "Plant Admin Costs (004)", 'Data Repository Table'!$D:$D, R$13 ) -> 295074.67 | S33: =SUM(G33:R33) -> 6573273.6
A34: Financial Actuals | B34: Surjek | C34: Expenses | D34: Labour Costs | E34: Labour-Costs (001) | G34: =SUMIFS( 'Data Repository Table'!$J:$J, 'Data Repository Table'!$A:$A, "Financial Actual", 'Data Repository Table'!$C:$C, "Surjek", 'Data Repository Table'!$B:$B, "Expenses", 'Data Repository Table'!$G:$G, "Labour Costs", 'Data Repository Table'!$H:$H, "Labour-Costs (001)", 'Data Repository Table'!$D:$D, G$13 ) -> 3198275.9 | H34: =SUMIFS( 'Data Repository Table'!$J:$J, 'Data Repository Table'!$A:$A, "Financial Actual", 'Data Repository Table'!$C:$C, "Surjek", 'Data Repository Table'!$B:$B, "Expenses", 'Data Repository Table'!$G:$G, "Labour Costs", 'Data Repository Table'!$H:$H, "Labour-Costs (001)", 'Data Repository Table'!$D:$D, H$13 ) -> 3852997.7 | I34: =SUMIFS( 'Data Repository Table'!$J:$J, 'Data Repository Table'!$A:$A, "Financial Actual", 'Data Repository Table'!$C:$C, "Surjek", 'Data Repository Table'!$B:$B, "Expenses", 'Data Repository Table'!$G:$G, "Labour Costs", 'Data Repository Table'!$H:$H, "Labour-Costs (001)", 'Data Repository Table'!$D:$D, I$13 ) -> 3894195.4 | J34: =SUMIFS( 'Data Repository Table'!$J:$J, 'Data Repository Table'!$A:$A, "Financial Actual", 'Data Repository Table'!$C:$C, "Surjek", 'Data Repository Table'!$B:$B, "Expenses", 'Data Repository Table'!$G:$G, "Labour Costs", 'Data Repository Table'!$H:$H, "Labour-Costs (001)", 'Data Repository Table'!$D:$D, J$13 ) -> 5221215.6 | K34: =SUMIFS( 'Data Repository Table'!$J:$J, 'Data Repository Table'!$A:$A, "Financial Actual", 'Data Repository Table'!$C:$C, "Surjek", 'Data Repository Table'!$B:$B, "Expenses", 'Data Repository Table'!$G:$G, "Labour Costs", 'Data Repository Table'!$H:$H, "Labour-Costs (001)", 'Data Repository Table'!$D:$D, K$13 ) -> 5648075.6 | L34: =SUMIFS( 'Data Repository Table'!$J:$J, 'Data Repository Table'!$A:$A, "Financial Actual", 'Data Repository Table'!$C:$C, "Surjek", 'Data Repository Table'!$B:$B, "Expenses", 'Data Repository Table'!$G:$G, "Labour Costs", 'Data Repository Table'!$H:$H, "Labour-Costs (001)", 'Data Repository Table'!$D:$D, L$13 ) -> 2887464.9 | M34: =SUMIFS( 'Data Repository Table'!$J:$J, 'Data Repository Table'!$A:$A, "Financial Actual", 'Data Repository Table'!$C:$C, "Surjek", 'Data Repository Table'!$B:$B, "Expenses", 'Data Repository Table'!$G:$G, "Labour Costs", 'Data Repository Table'!$H:$H, "Labour-Costs (001)", 'Data Repository Table'!$D:$D, M$13 ) -> 2699761.9 | N34: =SUMIFS( 'Data Repository Table'!$J:$J, 'Data Repository Table'!$A:$A, "Financial Actual", 'Data Repository Table'!$C:$C, "Surjek", 'Data Repository Table'!$B:$B, "Expenses", 'Data Repository Table'!$G:$G, "Labour Costs", 'Data Repository Table'!$H:$H, "Labour-Costs (001)", 'Data Repository Table'!$D:$D, N$13 ) -> 3178632.1 | ... R34: =SUMIFS( 'Data Repository Table'!$J:$J, 'Data Repository Table'!$A:$A, "Financial Actual", 'Data Repository Table'!$C:$C, "Surjek", 'Data Repository Table'!$B:$B, "Expenses", 'Data Repository Table'!$G:$G, "Labour Costs", 'Data Repository Table'!$H:$H, "Labour-Costs (001)", 'Data Repository Table'!$D:$D, R$13 ) -> 1891504.3 | S34: =SUM(G34:R34) -> 42136369
A35: Water Production Actuals | B35: Surjek | G35: =SUMIFS( 'Data Repository Table'!$J:$J, 'Data Repository Table'!$A:$A, "Water Production Actuals", 'Data Repository Table'!$C:$C, "Surjek", 'Data Repository Table'!$D:$D, G$13 ) -> 214.969 | H35: =SUMIFS( 'Data Repository Table'!$J:$J, 'Data Repository Table'!$A:$A, "Water Production Actuals", 'Data Repository Table'!$C:$C, "Surjek", 'Data Repository Table'!$D:$D, H$13 ) -> 228.19905 | I35: =SUMIFS( 'Data Repository Table'!$J:$J, 'Data Repository Table'!$A:$A, "Water Production Actuals", 'Data Repository Table'!$C:$C, "Surjek", 'Data Repository Table'!$D:$D, I$13 ) -> 216.53647 | J35: =SUMIFS( 'Data Repository Table'!$J:$J, 'Data Repository Table'!$A:$A, "Water Production Actuals", 'Data Repository Table'!$C:$C, "Surjek", 'Data Repository Table'!$D:$D, J$13 ) -> 236.76028 | K35: =SUMIFS( 'Data Repository Table'!$J:$J, 'Data Repository Table'!$A:$A, "Water Production Actuals", 'Data Repository Table'!$C:$C, "Surjek", 'Data Repository Table'!$D:$D, K$13 ) -> 232.05286 | L35: =SUMIFS( 'Data Repository Table'!$J:$J, 'Data Repository Table'!$A:$A, "Water Production Actuals", 'Data Repository Table'!$C:$C, "Surjek", 'Data Repository Table'!$D:$D, L$13 ) -> 240.21016 | M35: =SUMIFS( 'Data Repository Table'!$J:$J, 'Data Repository Table'!$A:$A, "Water Production Actuals", 'Data Repository Table'!$C:$C, "Surjek", 'Data Repository Table'!$D:$D, M$13 ) -> 288.16055 | N35: =SUMIFS( 'Data Repository Table'!$J:$J, 'Data Repository Table'!$A:$A, "Water Production Actuals", 'Data Repository Table'!$C:$C, "Surjek", 'Data Repository Table'!$D:$D, N$13 ) -> 306.88452 | ... R35: =SUMIFS( 'Data Repository Table'!$J:$J, 'Data Repository Table'!$A:$A, "Water Production Actuals", 'Data Repository Table'!$C:$C, "Surjek", 'Data Repository Table'!$D:$D, R$13 ) -> 260.3123 | S35: =SUM(G35:R35) -> 3306.5484
E36: Desalination Cost to Produce ($/ML) | G36: =SUM(G$27:G$34)/(G$35 * 1000) -> 52.749704 | H36: =SUM(H$27:H$34)/(H$35 * 1000) -> 59.863879 | I36: =SUM(I$27:I$34)/(I$35 * 1000) -> 63.76269 | J36: =SUM(J$27:J$34)/(J$35 * 1000) -> 78.188473 | K36: =SUM(K$27:K$34)/(K$35 * 1000) -> 86.296565 | L36: =SUM(L$27:L$34)/(L$35 * 1000) -> 53.948354 | M36: =SUM(M$27:M$34)/(M$35 * 1000) -> 48.540532 | N36: =SUM(N$27:N$34)/(N$35 * 1000) -> 53.663485 | ... R36: =SUM(R$27:R$34)/(R$35 * 1000) -> 32.611103 | S36: =SUM(S27:S34)/S35 -> 54231.507
A38: Financial Actuals | B38: Jutik | C38: Expenses | D38: Chemical Costs | E38: Chem-Exp (001) | G38: =SUMIFS( 'Data Repository Table'!$J:$J, 'Data Repository Table'!$A:$A, "Financial Actual", 'Data Repository Table'!$C:$C, "Jutik", 'Data Repository Table'!$B:$B, "Expenses", 'Data Repository Table'!$G:$G, "Chemical Costs", 'Data Repository Table'!$H:$H, "Chem-Exp (001)", 'Data Repository Table'!$D:$D, G$13 ) -> 1625596.3 | H38: =SUMIFS( 'Data Repository Table'!$J:$J, 'Data Repository Table'!$A:$A, "Financial Actual", 'Data Repository Table'!$C:$C, "Jutik", 'Data Repository Table'!$B:$B, "Expenses", 'Data Repository Table'!$G:$G, "Chemical Costs", 'Data Repository Table'!$H:$H, "Chem-Exp (001)", 'Data Repository Table'!$D:$D, H$13 ) -> 1295067.8 | I38: =SUMIFS( 'Data Repository Table'!$J:$J, 'Data Repository Table'!$A:$A, "Financial Actual", 'Data Repository Table'!$C:$C, "Jutik", 'Data Repository Table'!$B:$B, "Expenses", 'Data Repository Table'!$G:$G, "Chemical Costs", 'Data Repository Table'!$H:$H, "Chem-Exp (001)", 'Data Repository Table'!$D:$D, I$13 ) -> 1750624.9 | J38: =SUMIFS( 'Data Repository Table'!$J:$J, 'Data Repository Table'!$A:$A, "Financial Actual", 'Data Repository Table'!$C:$C, "Jutik", 'Data Repository Table'!$B:$B, "Expenses", 'Data Repository Table'!$G:$G, "Chemical Costs", 'Data Repository Table'!$H:$H, "Chem-Exp (001)", 'Data Repository Table'!$D:$D, J$13 ) -> 1472529.4 | K38: =SUMIFS( 'Data Repository Table'!$J:$J, 'Data Repository Table'!$A:$A, "Financial Actual", 'Data Repository Table'!$C:$C, "Jutik", 'Data Repository Table'!$B:$B, "Expenses", 'Data Repository Table'!$G:$G, "Chemical Costs", 'Data Repository Table'!$H:$H, "Chem-Exp (001)", 'Data Repository Table'!$D:$D, K$13 ) -> 1252200.5 | L38: =SUMIFS( 'Data Repository Table'!$J:$J, 'Data Repository Table'!$A:$A, "Financial Actual", 'Data Repository Table'!$C:$C, "Jutik", 'Data Repository Table'!$B:$B, "Expenses", 'Data Repository Table'!$G:$G, "Chemical Costs", 'Data Repository Table'!$H:$H, "Chem-Exp (001)", 'Data Repository Table'!$D:$D, L$13 ) -> 1406782.7 | M38: =SUMIFS( 'Data Repository Table'!$J:$J, 'Data Repository Table'!$A:$A, "Financial Actual", 'Data Repository Table'!$C:$C, "Jutik", 'Data Repository Table'!$B:$B, "Expenses", 'Data Repository Table'!$G:$G, "Chemical Costs", 'Data Repository Table'!$H:$H, "Chem-Exp (001)", 'Data Repository Table'!$D:$D, M$13 ) -> 1877449.5 | N38: =SUMIFS( 'Data Repository Table'!$J:$J, 'Data Repository Table'!$A:$A, "Financial Actual", 'Data Repository Table'!$C:$C, "Jutik", 'Data Repository Table'!$B:$B, "Expenses", 'Data Repository Table'!$G:$G, "Chemical Costs", 'Data Repository Table'!$H:$H, "Chem-Exp (001)", 'Data Repository Table'!$D:$D, N$13 ) -> 1912219.2 | ... R38: =SUMIFS( 'Data Repository Table'!$J:$J, 'Data Repository Table'!$A:$A, "Financial Actual", 'Data Repository Table'!$C:$C, "Jutik", 'Data Repository Table'!$B:$B, "Expenses", 'Data Repository Table'!$G:$G, "Chemical Costs", 'Data Repository Table'!$H:$H, "Chem-Exp (001)", 'Data Repository Table'!$D:$D, R$13 ) -> 2274807.8 | S38: =SUM(G38:R38) -> 21961819
A39: Financial Actuals | B39: Jutik | C39: Expenses | D39: Facility Costs | E39: Utility-Exp (002) - Heating | G39: =SUMIFS( 'Data Repository Table'!$J:$J, 'Data Repository Table'!$A:$A, "Financial Actual", 'Data Repository Table'!$C:$C, "Jutik", 'Data Repository Table'!$B:$B, "Expenses", 'Data Repository Table'!$G:$G, "Facility Costs", 'Data Repository Table'!$H:$H, "Utility-Exp (002) - Heating", 'Data Repository Table'!$D:$D, G$13 ) -> 895736.76 | H39: =SUMIFS( 'Data Repository Table'!$J:$J, 'Data Repository Table'!$A:$A, "Financial Actual", 'Data Repository Table'!$C:$C, "Jutik", 'Data Repository Table'!$B:$B, "Expenses", 'Data Repository Table'!$G:$G, "Facility Costs", 'Data Repository Table'!$H:$H, "Utility-Exp (002) - Heating", 'Data Repository Table'!$D:$D, H$13 ) -> 713608.81 | I39: =SUMIFS( 'Data Repository Table'!$J:$J, 'Data Repository Table'!$A:$A, "Financial Actual", 'Data Repository Table'!$C:$C, "Jutik", 'Data Repository Table'!$B:$B, "Expenses", 'Data Repository Table'!$G:$G, "Facility Costs", 'Data Repository Table'!$H:$H, "Utility-Exp (002) - Heating", 'Data Repository Table'!$D:$D, I$13 ) -> 964630.04 | J39: =SUMIFS( 'Data Repository Table'!$J:$J, 'Data Repository Table'!$A:$A, "Financial Actual", 'Data Repository Table'!$C:$C, "Jutik", 'Data Repository Table'!$B:$B, "Expenses", 'Data Repository Table'!$G:$G, "Facility Costs", 'Data Repository Table'!$H:$H, "Utility-Exp (002) - Heating", 'Data Repository Table'!$D:$D, J$13 ) -> 811393.74 | K39: =SUMIFS( 'Data Repository Table'!$J:$J, 'Data Repository Table'!$A:$A, "Financial Actual", 'Data Repository Table'!$C:$C, "Jutik", 'Data Repository Table'!$B:$B, "Expenses", 'Data Repository Table'!$G:$G, "Facility Costs", 'Data Repository Table'!$H:$H, "Utility-Exp (002) - Heating", 'Data Repository Table'!$D:$D, K$13 ) -> 689988.03 | L39: =SUMIFS( 'Data Repository Table'!$J:$J, 'Data Repository Table'!$A:$A, "Financial Actual", 'Data Repository Table'!$C:$C, "Jutik", 'Data Repository Table'!$B:$B, "Expenses", 'Data Repository Table'!$G:$G, "Facility Costs", 'Data Repository Table'!$H:$H, "Utility-Exp (002) - Heating", 'Data Repository Table'!$D:$D, L$13 ) -> 775165.96 | M39: =SUMIFS( 'Data Repository Table'!$J:$J, 'Data Repository Table'!$A:$A, "Financial Actual", 'Data Repository Table'!$C:$C, "Jutik", 'Data Repository Table'!$B:$B, "Expenses", 'Data Repository Table'!$G:$G, "Facility Costs", 'Data Repository Table'!$H:$H, "Utility-Exp (002) - Heating", 'Data Repository Table'!$D:$D, M$13 ) -> 1034513 | N39: =SUMIFS( 'Data Repository Table'!$J:$J, 'Data Repository Table'!$A:$A, "Financial Actual", 'Data Repository Table'!$C:$C, "Jutik", 'Data Repository Table'!$B:$B, "Expenses", 'Data Repository Table'!$G:$G, "Facility Costs", 'Data Repository Table'!$H:$H, "Utility-Exp (002) - Heating", 'Data Repository Table'!$D:$D, N$13 ) -> 888365.67 | ... R39: =SUMIFS( 'Data Repository Table'!$J:$J, 'Data Repository Table'!$A:$A, "Financial Actual", 'Data Repository Table'!$C:$C, "Jutik", 'Data Repository Table'!$B:$B, "Expenses", 'Data Repository Table'!$G:$G, "Facility Costs", 'Data Repository Table'!$H:$H, "Utility-Exp (002) - Heating", 'Data Repository Table'!$D:$D, R$13 ) -> 1253465.5 | S39: =SUM(G39:R39) -> 10834064
A40: Financial Actuals | B40: Jutik | C40: Expenses | D40: Facility Costs | E40: Utility-Exp (002) - Electricity | G40: =SUMIFS( 'Data Repository Table'!$J:$J, 'Data Repository Table'!$A:$A, "Financial Actual", 'Data Repository Table'!$C:$C, "Jutik", 'Data Repository Table'!$B:$B, "Expenses", 'Data Repository Table'!$G:$G, "Facility Costs", 'Data Repository Table'!$H:$H, "Utility-Exp (002) - Electricity", 'Data Repository Table'!$D:$D, G$13 ) -> 829385.89 | H40: =SUMIFS( 'Data Repository Table'!$J:$J, 'Data Repository Table'!$A:$A, "Financial Actual", 'Data Repository Table'!$C:$C, "Jutik", 'Data Repository Table'!$B:$B, "Expenses", 'Data Repository Table'!$G:$G, "Facility Costs", 'Data Repository Table'!$H:$H, "Utility-Exp (002) - Electricity", 'Data Repository Table'!$D:$D, H$13 ) -> 660748.9 | I40: =SUMIFS( 'Data Repository Table'!$J:$J, 'Data Repository Table'!$A:$A, "Financial Actual", 'Data Repository Table'!$C:$C, "Jutik", 'Data Repository Table'!$B:$B, "Expenses", 'Data Repository Table'!$G:$G, "Facility Costs", 'Data Repository Table'!$H:$H, "Utility-Exp (002) - Electricity", 'Data Repository Table'!$D:$D, I$13 ) -> 893175.96 | J40: =SUMIFS( 'Data Repository Table'!$J:$J, 'Data Repository Table'!$A:$A, "Financial Actual", 'Data Repository Table'!$C:$C, "Jutik", 'Data Repository Table'!$B:$B, "Expenses", 'Data Repository Table'!$G:$G, "Facility Costs", 'Data Repository Table'!$H:$H, "Utility-Exp (002) - Electricity", 'Data Repository Table'!$D:$D, J$13 ) -> 751290.5 | K40: =SUMIFS( 'Data Repository Table'!$J:$J, 'Data Repository Table'!$A:$A, "Financial Actual", 'Data Repository Table'!$C:$C, "Jutik", 'Data Repository Table'!$B:$B, "Expenses", 'Data Repository Table'!$G:$G, "Facility Costs", 'Data Repository Table'!$H:$H, "Utility-Exp (002) - Electricity", 'Data Repository Table'!$D:$D, K$13 ) -> 638877.8 | L40: =SUMIFS( 'Data Repository Table'!$J:$J, 'Data Repository Table'!$A:$A, "Financial Actual", 'Data Repository Table'!$C:$C, "Jutik", 'Data Repository Table'!$B:$B, "Expenses", 'Data Repository Table'!$G:$G, "Facility Costs", 'Data Repository Table'!$H:$H, "Utility-Exp (002) - Electricity", 'Data Repository Table'!$D:$D, L$13 ) -> 717746.26 | M40: =SUMIFS( 'Data Repository Table'!$J:$J, 'Data Repository Table'!$A:$A, "Financial Actual", 'Data Repository Table'!$C:$C, "Jutik", 'Data Repository Table'!$B:$B, "Expenses", 'Data Repository Table'!$G:$G, "Facility Costs", 'Data Repository Table'!$H:$H, "Utility-Exp (002) - Electricity", 'Data Repository Table'!$D:$D, M$13 ) -> 957882.4 | N40: =SUMIFS( 'Data Repository Table'!$J:$J, 'Data Repository Table'!$A:$A, "Financial Actual", 'Data Repository Table'!$C:$C, "Jutik", 'Data Repository Table'!$B:$B, "Expenses", 'Data Repository Table'!$G:$G, "Facility Costs", 'Data Repository Table'!$H:$H, "Utility-Exp (002) - Electricity", 'Data Repository Table'!$D:$D, N$13 ) -> 822560.8 | ... R40: =SUMIFS( 'Data Repository Table'!$J:$J, 'Data Repository Table'!$A:$A, "Financial Actual", 'Data Repository Table'!$C:$C, "Jutik", 'Data Repository Table'!$B:$B, "Expenses", 'Data Repository Table'!$G:$G, "Facility Costs", 'Data Repository Table'!$H:$H, "Utility-Exp (002) - Electricity", 'Data Repository Table'!$D:$D, R$13 ) -> 1160616.2 | S40: =SUM(G40:R40) -> 10031541
A41: Financial Actuals | B41: Jutik | C41: Expenses | D41: Operational Maintenance Costs | E41: Plant Maintenance (001) | G41: =SUMIFS( 'Data Repository Table'!$J:$J, 'Data Repository Table'!$A:$A, "Financial Actual", 'Data Repository Table'!$C:$C, "Jutik", 'Data Repository Table'!$B:$B, "Expenses", 'Data Repository Table'!$G:$G, "Operational Maintenance Costs", 'Data Repository Table'!$H:$H, "Plant Maintenance (001)", 'Data Repository Table'!$D:$D, G$13 ) -> 716589.41 | H41: =SUMIFS( 'Data Repository Table'!$J:$J, 'Data Repository Table'!$A:$A, "Financial Actual", 'Data Repository Table'!$C:$C, "Jutik", 'Data Repository Table'!$B:$B, "Expenses", 'Data Repository Table'!$G:$G, "Operational Maintenance Costs", 'Data Repository Table'!$H:$H, "Plant Maintenance (001)", 'Data Repository Table'!$D:$D, H$13 ) -> 570887.05 | I41: =SUMIFS( 'Data Repository Table'!$J:$J, 'Data Repository Table'!$A:$A, "Financial Actual", 'Data Repository Table'!$C:$C, "Jutik", 'Data Repository Table'!$B:$B, "Expenses", 'Data Repository Table'!$G:$G, "Operational Maintenance Costs", 'Data Repository Table'!$H:$H, "Plant Maintenance (001)", 'Data Repository Table'!$D:$D, I$13 ) -> 771704.03 | J41: =SUMIFS( 'Data Repository Table'!$J:$J, 'Data Repository Table'!$A:$A, "Financial Actual", 'Data Repository Table'!$C:$C, "Jutik", 'Data Repository Table'!$B:$B, "Expenses", 'Data Repository Table'!$G:$G, "Operational Maintenance Costs", 'Data Repository Table'!$H:$H, "Plant Maintenance (001)", 'Data Repository Table'!$D:$D, J$13 ) -> 649115 | K41: =SUMIFS( 'Data Repository Table'!$J:$J, 'Data Repository Table'!$A:$A, "Financial Actual", 'Data Repository Table'!$C:$C, "Jutik", 'Data Repository Table'!$B:$B, "Expenses", 'Data Repository Table'!$G:$G, "Operational Maintenance Costs", 'Data Repository Table'!$H:$H, "Plant Maintenance (001)", 'Data Repository Table'!$D:$D, K$13 ) -> 551990.42 | L41: =SUMIFS( 'Data Repository Table'!$J:$J, 'Data Repository Table'!$A:$A, "Financial Actual", 'Data Repository Table'!$C:$C, "Jutik", 'Data Repository Table'!$B:$B, "Expenses", 'Data Repository Table'!$G:$G, "Operational Maintenance Costs", 'Data Repository Table'!$H:$H, "Plant Maintenance (001)", 'Data Repository Table'!$D:$D, L$13 ) -> 620132.77 | M41: =SUMIFS( 'Data Repository Table'!$J:$J, 'Data Repository Table'!$A:$A, "Financial Actual", 'Data Repository Table'!$C:$C, "Jutik", 'Data Repository Table'!$B:$B, "Expenses", 'Data Repository Table'!$G:$G, "Operational Maintenance Costs", 'Data Repository Table'!$H:$H, "Plant Maintenance (001)", 'Data Repository Table'!$D:$D, M$13 ) -> 827610.39 | N41: =SUMIFS( 'Data Repository Table'!$J:$J, 'Data Repository Table'!$A:$A, "Financial Actual", 'Data Repository Table'!$C:$C, "Jutik", 'Data Repository Table'!$B:$B, "Expenses", 'Data Repository Table'!$G:$G, "Operational Maintenance Costs", 'Data Repository Table'!$H:$H, "Plant Maintenance (001)", 'Data Repository Table'!$D:$D, N$13 ) -> 710692.53 | ... R41: =SUMIFS( 'Data Repository Table'!$J:$J, 'Data Repository Table'!$A:$A, "Financial Actual", 'Data Repository Table'!$C:$C, "Jutik", 'Data Repository Table'!$B:$B, "Expenses", 'Data Repository Table'!$G:$G, "Operational Maintenance Costs", 'Data Repository Table'!$H:$H, "Plant Maintenance (001)", 'Data Repository Table'!$D:$D, R$13 ) -> 1002772.4 | S41: =SUM(G41:R41) -> 8667251
A42: Financial Actuals | B42: Jutik | C42: Expenses | D42: Operational Maintenance Costs | E42: Plant Outages (002) | G42: =SUMIFS( 'Data Repository Table'!$J:$J, 'Data Repository Table'!$A:$A, "Financial Actual", 'Data Repository Table'!$C:$C, "Jutik", 'Data Repository Table'!$B:$B, "Expenses", 'Data Repository Table'!$G:$G, "Operational Maintenance Costs", 'Data Repository Table'!$H:$H, "Plant Outages (002)", 'Data Repository Table'!$D:$D, G$13 ) -> 251329.06 | H42: =SUMIFS( 'Data Repository Table'!$J:$J, 'Data Repository Table'!$A:$A, "Financial Actual", 'Data Repository Table'!$C:$C, "Jutik", 'Data Repository Table'!$B:$B, "Expenses", 'Data Repository Table'!$G:$G, "Operational Maintenance Costs", 'Data Repository Table'!$H:$H, "Plant Outages (002)", 'Data Repository Table'!$D:$D, H$13 ) -> 200226.94 | I42: =SUMIFS( 'Data Repository Table'!$J:$J, 'Data Repository Table'!$A:$A, "Financial Actual", 'Data Repository Table'!$C:$C, "Jutik", 'Data Repository Table'!$B:$B, "Expenses", 'Data Repository Table'!$G:$G, "Operational Maintenance Costs", 'Data Repository Table'!$H:$H, "Plant Outages (002)", 'Data Repository Table'!$D:$D, I$13 ) -> 270659.38 | J42: =SUMIFS( 'Data Repository Table'!$J:$J, 'Data Repository Table'!$A:$A, "Financial Actual", 'Data Repository Table'!$C:$C, "Jutik", 'Data Repository Table'!$B:$B, "Expenses", 'Data Repository Table'!$G:$G, "Operational Maintenance Costs", 'Data Repository Table'!$H:$H, "Plant Outages (002)", 'Data Repository Table'!$D:$D, J$13 ) -> 227663.79 | K42: =SUMIFS( 'Data Repository Table'!$J:$J, 'Data Repository Table'!$A:$A, "Financial Actual", 'Data Repository Table'!$C:$C, "Jutik", 'Data Repository Table'!$B:$B, "Expenses", 'Data Repository Table'!$G:$G, "Operational Maintenance Costs", 'Data Repository Table'!$H:$H, "Plant Outages (002)", 'Data Repository Table'!$D:$D, K$13 ) -> 193599.33 | L42: =SUMIFS( 'Data Repository Table'!$J:$J, 'Data Repository Table'!$A:$A, "Financial Actual", 'Data Repository Table'!$C:$C, "Jutik", 'Data Repository Table'!$B:$B, "Expenses", 'Data Repository Table'!$G:$G, "Operational Maintenance Costs", 'Data Repository Table'!$H:$H, "Plant Outages (002)", 'Data Repository Table'!$D:$D, L$13 ) -> 143549.25 | M42: =SUMIFS( 'Data Repository Table'!$J:$J, 'Data Repository Table'!$A:$A, "Financial Actual", 'Data Repository Table'!$C:$C, "Jutik", 'Data Repository Table'!$B:$B, "Expenses", 'Data Repository Table'!$G:$G, "Operational Maintenance Costs", 'Data Repository Table'!$H:$H, "Plant Outages (002)", 'Data Repository Table'!$D:$D, M$13 ) -> 153261.18 | N42: =SUMIFS( 'Data Repository Table'!$J:$J, 'Data Repository Table'!$A:$A, "Financial Actual", 'Data Repository Table'!$C:$C, "Jutik", 'Data Repository Table'!$B:$B, "Expenses", 'Data Repository Table'!$G:$G, "Operational Maintenance Costs", 'Data Repository Table'!$H:$H, "Plant Outages (002)", 'Data Repository Table'!$D:$D, N$13 ) -> 131609.73 | ... R42: =SUMIFS( 'Data Repository Table'!$J:$J, 'Data Repository Table'!$A:$A, "Financial Actual", 'Data Repository Table'!$C:$C, "Jutik", 'Data Repository Table'!$B:$B, "Expenses", 'Data Repository Table'!$G:$G, "Operational Maintenance Costs", 'Data Repository Table'!$H:$H, "Plant Outages (002)", 'Data Repository Table'!$D:$D, R$13 ) -> 232123.24 | S42: =SUM(G42:R42) -> 2219902.8
A43: Financial Actuals | B43: Jutik | C43: Expenses | D43: Operational Maintenance Costs | E43: Plant Op. Costs (003) | G43: =SUMIFS( 'Data Repository Table'!$J:$J, 'Data Repository Table'!$A:$A, "Financial Actual", 'Data Repository Table'!$C:$C, "Jutik", 'Data Repository Table'!$B:$B, "Expenses", 'Data Repository Table'!$G:$G, "Operational Maintenance Costs", 'Data Repository Table'!$H:$H, "Plant Op. Costs (003)", 'Data Repository Table'!$D:$D, G$13 ) -> 623296.06 | H43: =SUMIFS( 'Data Repository Table'!$J:$J, 'Data Repository Table'!$A:$A, "Financial Actual", 'Data Repository Table'!$C:$C, "Jutik", 'Data Repository Table'!$B:$B, "Expenses", 'Data Repository Table'!$G:$G, "Operational Maintenance Costs", 'Data Repository Table'!$H:$H, "Plant Op. Costs (003)", 'Data Repository Table'!$D:$D, H$13 ) -> 496562.81 | I43: =SUMIFS( 'Data Repository Table'!$J:$J, 'Data Repository Table'!$A:$A, "Financial Actual", 'Data Repository Table'!$C:$C, "Jutik", 'Data Repository Table'!$B:$B, "Expenses", 'Data Repository Table'!$G:$G, "Operational Maintenance Costs", 'Data Repository Table'!$H:$H, "Plant Op. Costs (003)", 'Data Repository Table'!$D:$D, I$13 ) -> 671235.27 | J43: =SUMIFS( 'Data Repository Table'!$J:$J, 'Data Repository Table'!$A:$A, "Financial Actual", 'Data Repository Table'!$C:$C, "Jutik", 'Data Repository Table'!$B:$B, "Expenses", 'Data Repository Table'!$G:$G, "Operational Maintenance Costs", 'Data Repository Table'!$H:$H, "Plant Op. Costs (003)", 'Data Repository Table'!$D:$D, J$13 ) -> 564606.2 | K43: =SUMIFS( 'Data Repository Table'!$J:$J, 'Data Repository Table'!$A:$A, "Financial Actual", 'Data Repository Table'!$C:$C, "Jutik", 'Data Repository Table'!$B:$B, "Expenses", 'Data Repository Table'!$G:$G, "Operational Maintenance Costs", 'Data Repository Table'!$H:$H, "Plant Op. Costs (003)", 'Data Repository Table'!$D:$D, K$13 ) -> 480126.35 | L43: =SUMIFS( 'Data Repository Table'!$J:$J, 'Data Repository Table'!$A:$A, "Financial Actual", 'Data Repository Table'!$C:$C, "Jutik", 'Data Repository Table'!$B:$B, "Expenses", 'Data Repository Table'!$G:$G, "Operational Maintenance Costs", 'Data Repository Table'!$H:$H, "Plant Op. Costs (003)", 'Data Repository Table'!$D:$D, L$13 ) -> 356002.15 | M43: =SUMIFS( 'Data Repository Table'!$J:$J, 'Data Repository Table'!$A:$A, "Financial Actual", 'Data Repository Table'!$C:$C, "Jutik", 'Data Repository Table'!$B:$B, "Expenses", 'Data Repository Table'!$G:$G, "Operational Maintenance Costs", 'Data Repository Table'!$H:$H, "Plant Op. Costs (003)", 'Data Repository Table'!$D:$D, M$13 ) -> 380087.74 | N43: =SUMIFS( 'Data Repository Table'!$J:$J, 'Data Repository Table'!$A:$A, "Financial Actual", 'Data Repository Table'!$C:$C, "Jutik", 'Data Repository Table'!$B:$B, "Expenses", 'Data Repository Table'!$G:$G, "Operational Maintenance Costs", 'Data Repository Table'!$H:$H, "Plant Op. Costs (003)", 'Data Repository Table'!$D:$D, N$13 ) -> 326392.13 | ... R43: =SUMIFS( 'Data Repository Table'!$J:$J, 'Data Repository Table'!$A:$A, "Financial Actual", 'Data Repository Table'!$C:$C, "Jutik", 'Data Repository Table'!$B:$B, "Expenses", 'Data Repository Table'!$G:$G, "Operational Maintenance Costs", 'Data Repository Table'!$H:$H, "Plant Op. Costs (003)", 'Data Repository Table'!$D:$D, R$13 ) -> 575665.64 | S43: =SUM(G43:R43) -> 5505359
A44: Financial Actuals | B44: Jutik | C44: Expenses | D44: Operational Maintenance Costs | E44: Plant Admin Costs (004) | G44: =SUMIFS( 'Data Repository Table'!$J:$J, 'Data Repository Table'!$A:$A, "Financial Actual", 'Data Repository Table'!$C:$C, "Jutik", 'Data Repository Table'!$B:$B, "Expenses", 'Data Repository Table'!$G:$G, "Operational Maintenance Costs", 'Data Repository Table'!$H:$H, "Plant Admin Costs (004)", 'Data Repository Table'!$D:$D, G$13 ) -> 211116.41 | H44: =SUMIFS( 'Data Repository Table'!$J:$J, 'Data Repository Table'!$A:$A, "Financial Actual", 'Data Repository Table'!$C:$C, "Jutik", 'Data Repository Table'!$B:$B, "Expenses", 'Data Repository Table'!$G:$G, "Operational Maintenance Costs", 'Data Repository Table'!$H:$H, "Plant Admin Costs (004)", 'Data Repository Table'!$D:$D, H$13 ) -> 168190.63 | I44: =SUMIFS( 'Data Repository Table'!$J:$J, 'Data Repository Table'!$A:$A, "Financial Actual", 'Data Repository Table'!$C:$C, "Jutik", 'Data Repository Table'!$B:$B, "Expenses", 'Data Repository Table'!$G:$G, "Operational Maintenance Costs", 'Data Repository Table'!$H:$H, "Plant Admin Costs (004)", 'Data Repository Table'!$D:$D, I$13 ) -> 227353.88 | J44: =SUMIFS( 'Data Repository Table'!$J:$J, 'Data Repository Table'!$A:$A, "Financial Actual", 'Data Repository Table'!$C:$C, "Jutik", 'Data Repository Table'!$B:$B, "Expenses", 'Data Repository Table'!$G:$G, "Operational Maintenance Costs", 'Data Repository Table'!$H:$H, "Plant Admin Costs (004)", 'Data Repository Table'!$D:$D, J$13 ) -> 191237.58 | K44: =SUMIFS( 'Data Repository Table'!$J:$J, 'Data Repository Table'!$A:$A, "Financial Actual", 'Data Repository Table'!$C:$C, "Jutik", 'Data Repository Table'!$B:$B, "Expenses", 'Data Repository Table'!$G:$G, "Operational Maintenance Costs", 'Data Repository Table'!$H:$H, "Plant Admin Costs (004)", 'Data Repository Table'!$D:$D, K$13 ) -> 162623.44 | L44: =SUMIFS( 'Data Repository Table'!$J:$J, 'Data Repository Table'!$A:$A, "Financial Actual", 'Data Repository Table'!$C:$C, "Jutik", 'Data Repository Table'!$B:$B, "Expenses", 'Data Repository Table'!$G:$G, "Operational Maintenance Costs", 'Data Repository Table'!$H:$H, "Plant Admin Costs (004)", 'Data Repository Table'!$D:$D, L$13 ) -> 120581.37 | M44: =SUMIFS( 'Data Repository Table'!$J:$J, 'Data Repository Table'!$A:$A, "Financial Actual", 'Data Repository Table'!$C:$C, "Jutik", 'Data Repository Table'!$B:$B, "Expenses", 'Data Repository Table'!$G:$G, "Operational Maintenance Costs", 'Data Repository Table'!$H:$H, "Plant Admin Costs (004)", 'Data Repository Table'!$D:$D, M$13 ) -> 128739.39 | N44: =SUMIFS( 'Data Repository Table'!$J:$J, 'Data Repository Table'!$A:$A, "Financial Actual", 'Data Repository Table'!$C:$C, "Jutik", 'Data Repository Table'!$B:$B, "Expenses", 'Data Repository Table'!$G:$G, "Operational Maintenance Costs", 'Data Repository Table'!$H:$H, "Plant Admin Costs (004)", 'Data Repository Table'!$D:$D, N$13 ) -> 110552.17 | ... R44: =SUMIFS( 'Data Repository Table'!$J:$J, 'Data Repository Table'!$A:$A, "Financial Actual", 'Data Repository Table'!$C:$C, "Jutik", 'Data Repository Table'!$B:$B, "Expenses", 'Data Repository Table'!$G:$G, "Operational Maintenance Costs", 'Data Repository Table'!$H:$H, "Plant Admin Costs (004)", 'Data Repository Table'!$D:$D, R$13 ) -> 194983.52 | S44: =SUM(G44:R44) -> 1864718.4
A45: Financial Actuals | B45: Jutik | C45: Expenses | D45: Labour Costs | E45: Labour-Costs (001) | G45: =SUMIFS( 'Data Repository Table'!$J:$J, 'Data Repository Table'!$A:$A, "Financial Actual", 'Data Repository Table'!$C:$C, "Jutik", 'Data Repository Table'!$B:$B, "Expenses", 'Data Repository Table'!$G:$G, "Labour Costs", 'Data Repository Table'!$H:$H, "Labour-Costs (001)", 'Data Repository Table'!$D:$D, G$13 ) -> 3015948.7 | H45: =SUMIFS( 'Data Repository Table'!$J:$J, 'Data Repository Table'!$A:$A, "Financial Actual", 'Data Repository Table'!$C:$C, "Jutik", 'Data Repository Table'!$B:$B, "Expenses", 'Data Repository Table'!$G:$G, "Labour Costs", 'Data Repository Table'!$H:$H, "Labour-Costs (001)", 'Data Repository Table'!$D:$D, H$13 ) -> 2402723.3 | I45: =SUMIFS( 'Data Repository Table'!$J:$J, 'Data Repository Table'!$A:$A, "Financial Actual", 'Data Repository Table'!$C:$C, "Jutik", 'Data Repository Table'!$B:$B, "Expenses", 'Data Repository Table'!$G:$G, "Labour Costs", 'Data Repository Table'!$H:$H, "Labour-Costs (001)", 'Data Repository Table'!$D:$D, I$13 ) -> 3247912.6 | J45: =SUMIFS( 'Data Repository Table'!$J:$J, 'Data Repository Table'!$A:$A, "Financial Actual", 'Data Repository Table'!$C:$C, "Jutik", 'Data Repository Table'!$B:$B, "Expenses", 'Data Repository Table'!$G:$G, "Labour Costs", 'Data Repository Table'!$H:$H, "Labour-Costs (001)", 'Data Repository Table'!$D:$D, J$13 ) -> 2731965.5 | K45: =SUMIFS( 'Data Repository Table'!$J:$J, 'Data Repository Table'!$A:$A, "Financial Actual", 'Data Repository Table'!$C:$C, "Jutik", 'Data Repository Table'!$B:$B, "Expenses", 'Data Repository Table'!$G:$G, "Labour Costs", 'Data Repository Table'!$H:$H, "Labour-Costs (001)", 'Data Repository Table'!$D:$D, K$13 ) -> 2323192 | L45: =SUMIFS( 'Data Repository Table'!$J:$J, 'Data Repository Table'!$A:$A, "Financial Actual", 'Data Repository Table'!$C:$C, "Jutik", 'Data Repository Table'!$B:$B, "Expenses", 'Data Repository Table'!$G:$G, "Labour Costs", 'Data Repository Table'!$H:$H, "Labour-Costs (001)", 'Data Repository Table'!$D:$D, L$13 ) -> 1722591 | M45: =SUMIFS( 'Data Repository Table'!$J:$J, 'Data Repository Table'!$A:$A, "Financial Actual", 'Data Repository Table'!$C:$C, "Jutik", 'Data Repository Table'!$B:$B, "Expenses", 'Data Repository Table'!$G:$G, "Labour Costs", 'Data Repository Table'!$H:$H, "Labour-Costs (001)", 'Data Repository Table'!$D:$D, M$13 ) -> 1839134.2 | N45: =SUMIFS( 'Data Repository Table'!$J:$J, 'Data Repository Table'!$A:$A, "Financial Actual", 'Data Repository Table'!$C:$C, "Jutik", 'Data Repository Table'!$B:$B, "Expenses", 'Data Repository Table'!$G:$G, "Labour Costs", 'Data Repository Table'!$H:$H, "Labour-Costs (001)", 'Data Repository Table'!$D:$D, N$13 ) -> 2579316.7 | ... R45: =SUMIFS( 'Data Repository Table'!$J:$J, 'Data Repository Table'!$A:$A, "Financial Actual", 'Data Repository Table'!$C:$C, "Jutik", 'Data Repository Table'!$B:$B, "Expenses", 'Data Repository Table'!$G:$G, "Labour Costs", 'Data Repository Table'!$H:$H, "Labour-Costs (001)", 'Data Repository Table'!$D:$D, R$13 ) -> 2785478.9 | S45: =SUM(G45:R45) -> 29638834
A46: Water Production Actuals | B46: Jutik | G46: =SUMIFS( 'Data Repository Table'!$J:$J, 'Data Repository Table'!$A:$A, "Water Production Actuals", 'Data Repository Table'!$C:$C, "Jutik", 'Data Repository Table'!$D:$D, G$13 ) -> 250.24199 | H46: =SUMIFS( 'Data Repository Table'!$J:$J, 'Data Repository Table'!$A:$A, "Water Production Actuals", 'Data Repository Table'!$C:$C, "Jutik", 'Data Repository Table'!$D:$D, H$13 ) -> 206.7407 | I46: =SUMIFS( 'Data Repository Table'!$J:$J, 'Data Repository Table'!$A:$A, "Water Production Actuals", 'Data Repository Table'!$C:$C, "Jutik", 'Data Repository Table'!$D:$D, I$13 ) -> 201.23546 | J46: =SUMIFS( 'Data Repository Table'!$J:$J, 'Data Repository Table'!$A:$A, "Water Production Actuals", 'Data Repository Table'!$C:$C, "Jutik", 'Data Repository Table'!$D:$D, J$13 ) -> 174.36957 | K46: =SUMIFS( 'Data Repository Table'!$J:$J, 'Data Repository Table'!$A:$A, "Water Production Actuals", 'Data Repository Table'!$C:$C, "Jutik", 'Data Repository Table'!$D:$D, K$13 ) -> 204.09105 | L46: =SUMIFS( 'Data Repository Table'!$J:$J, 'Data Repository Table'!$A:$A, "Water Production Actuals", 'Data Repository Table'!$C:$C, "Jutik", 'Data Repository Table'!$D:$D, L$13 ) -> 146.35667 | M46: =SUMIFS( 'Data Repository Table'!$J:$J, 'Data Repository Table'!$A:$A, "Water Production Actuals", 'Data Repository Table'!$C:$C, "Jutik", 'Data Repository Table'!$D:$D, M$13 ) -> 204.2025 | N46: =SUMIFS( 'Data Repository Table'!$J:$J, 'Data Repository Table'!$A:$A, "Water Production Actuals", 'Data Repository Table'!$C:$C, "Jutik", 'Data Repository Table'!$D:$D, N$13 ) -> 217.4302 | ... R46: =SUMIFS( 'Data Repository Table'!$J:$J, 'Data Repository Table'!$A:$A, "Water Production Actuals", 'Data Repository Table'!$C:$C, "Jutik", 'Data Repository Table'!$D:$D, R$13 ) -> 220.38033 | S46: =SUM(G46:R46) -> 2533.8792
E47: Desalination Cost to Produce ($/ML) | G47: =SUM(G$38:G$45)/(G$46 * 1000) -> 32.644396 | H47: =SUM(H$38:H$45)/(H$46 * 1000) -> 31.479124 | I47: =SUM(I$38:I$45)/(I$46 * 1000) -> 43.71643 | J47: =SUM(J$38:J$45)/(J$46 * 1000) -> 42.437461 | K47: =SUM(K$38:K$45)/(K$46 * 1000) -> 30.832307 | L47: =SUM(L$38:L$45)/(L$46 * 1000) -> 40.056607 | M47: =SUM(M$38:M$45)/(M$46 * 1000) -> 35.252643 | N47: =SUM(N$38:N$45)/(N$46 * 1000) -> 34.409705 | ... R47: =SUM(R$38:R$45)/(R$46 * 1000) -> 43.016149 | S47: =SUM(S38:S45)/S46 -> 35804.189
A48: Place your answer here
A51: You've now calculated the Desalinated Cost to Produce for each of the three desalination plants (Kootha, Surjek and Jutik). This has given you a micro view of the trends, but let's take a look at the macro view of the situation and look at how the aggregated cost to produce (Kootha + Surjek + Jutik) look.
A52: Q5. Aggregate the Cost Centre(s) for each Plant (i.e.Chemical Costs, Facility Costs, Operational Maintenance Costs, Labour Costs) in the table below. Subsequently, in one chart, plot out the Overall Cost to Produce, as well as the Cost to Produce for Kootha, Surjek and Jutik for comparison. What trends do you note when looking at the data in this way?
A54: Account Type | B54: Unit | C54: Value Driver | D54: Cost Centre | E54: Cost Centre Element | G54: 41456 | H54: 41487 | I54: 41518 | J54: 41548 | K54: 41579 | L54: 41609 | M54: 41640 | N54: 41671 | O54: 41699 | P54: 41730 | Q54: 41760 | R54: 41791
S55: Total
A56: Financial Actuals | B56: All | C56: Expenses | D56: Chemical Costs | E56: Chem-Exp (001) | G56: {=SUM(SUMIFS( 'Data Repository Table'!$J:$J, 'Data Repository Table'!$A:$A, "Financial Actual", 'Data Repository Table'!$C:$C, {"Kootha","Surjek","Jutik"}, 'Data Repository Table'!$B:$B, "Expenses", 'Data Repository Table'!$G:$G, "Chemical Costs", 'Data Repository Table'!$H:$H, "Chem-Exp (001)", 'Data Repository Table'!$D:$D, G$13 ))} -> 4752382.7 | H56: {=SUM(SUMIFS( 'Data Repository Table'!$J:$J, 'Data Repository Table'!$A:$A, "Financial Actual", 'Data Repository Table'!$C:$C, {"Kootha","Surjek","Jutik"}, 'Data Repository Table'!$B:$B, "Expenses", 'Data Repository Table'!$G:$G, "Chemical Costs", 'Data Repository Table'!$H:$H, "Chem-Exp (001)", 'Data Repository Table'!$D:$D, H$13 ))} -> 5167035 | I56: {=SUM(SUMIFS( 'Data Repository Table'!$J:$J, 'Data Repository Table'!$A:$A, "Financial Actual", 'Data Repository Table'!$C:$C, {"Kootha","Surjek","Jutik"}, 'Data Repository Table'!$B:$B, "Expenses", 'Data Repository Table'!$G:$G, "Chemical Costs", 'Data Repository Table'!$H:$H, "Chem-Exp (001)", 'Data Repository Table'!$D:$D, I$13 ))} -> 5477119.2 | J56: {=SUM(SUMIFS( 'Data Repository Table'!$J:$J, 'Data Repository Table'!$A:$A, "Financial Actual", 'Data Repository Table'!$C:$C, {"Kootha","Surjek","Jutik"}, 'Data Repository Table'!$B:$B, "Expenses", 'Data Repository Table'!$G:$G, "Chemical Costs", 'Data Repository Table'!$H:$H, "Chem-Exp (001)", 'Data Repository Table'!$D:$D, J$13 ))} -> 6217372.1 | K56: {=SUM(SUMIFS( 'Data Repository Table'!$J:$J, 'Data Repository Table'!$A:$A, "Financial Actual", 'Data Repository Table'!$C:$C, {"Kootha","Surjek","Jutik"}, 'Data Repository Table'!$B:$B, "Expenses", 'Data Repository Table'!$G:$G, "Chemical Costs", 'Data Repository Table'!$H:$H, "Chem-Exp (001)", 'Data Repository Table'!$D:$D, K$13 ))} -> 6351549.6 | L56: {=SUM(SUMIFS( 'Data Repository Table'!$J:$J, 'Data Repository Table'!$A:$A, "Financial Actual", 'Data Repository Table'!$C:$C, {"Kootha","Surjek","Jutik"}, 'Data Repository Table'!$B:$B, "Expenses", 'Data Repository Table'!$G:$G, "Chemical Costs", 'Data Repository Table'!$H:$H, "Chem-Exp (001)", 'Data Repository Table'!$D:$D, L$13 ))} -> 5473894 | M56: {=SUM(SUMIFS( 'Data Repository Table'!$J:$J, 'Data Repository Table'!$A:$A, "Financial Actual", 'Data Repository Table'!$C:$C, {"Kootha","Surjek","Jutik"}, 'Data Repository Table'!$B:$B, "Expenses", 'Data Repository Table'!$G:$G, "Chemical Costs", 'Data Repository Table'!$H:$H, "Chem-Exp (001)", 'Data Repository Table'!$D:$D, M$13 ))} -> 7073236.3 | N56: {=SUM(SUMIFS( 'Data Repository Table'!$J:$J, 'Data Repository Table'!$A:$A, "Financial Actual", 'Data Repository Table'!$C:$C, {"Kootha","Surjek","Jutik"}, 'Data Repository Table'!$B:$B, "Expenses", 'Data Repository Table'!$G:$G, "Chemical Costs", 'Data Repository Table'!$H:$H, "Chem-Exp (001)", 'Data Repository Table'!$D:$D, N$13 ))} -> 7645099.2 | ... R56: {=SUM(SUMIFS( 'Data Repository Table'!$J:$J, 'Data Repository Table'!$A:$A, "Financial Actual", 'Data Repository Table'!$C:$C, {"Kootha","Surjek","Jutik"}, 'Data Repository Table'!$B:$B, "Expenses", 'Data Repository Table'!$G:$G, "Chemical Costs", 'Data Repository Table'!$H:$H, "Chem-Exp (001)", 'Data Repository Table'!$D:$D, R$13 ))} -> 5712658.2 | S56: =SUM(G56:R56) -> 78413350
A57: Financial Actuals | B57: All | C57: Expenses | D57: Facility Costs | E57: Utility-Exp (002) - Heating | G57: {=SUM(SUMIFS( 'Data Repository Table'!$J:$J, 'Data Repository Table'!$A:$A, "Financial Actual", 'Data Repository Table'!$C:$C, {"Kootha","Surjek","Jutik"}, 'Data Repository Table'!$B:$B, "Expenses", 'Data Repository Table'!$G:$G,"Facility Costs", 'Data Repository Table'!$H:$H, "Utility-Exp (002) - Heating", 'Data Repository Table'!$D:$D, G$13 ))} -> 2439061.4 | H57: {=SUM(SUMIFS( 'Data Repository Table'!$J:$J, 'Data Repository Table'!$A:$A, "Financial Actual", 'Data Repository Table'!$C:$C, {"Kootha","Surjek","Jutik"}, 'Data Repository Table'!$B:$B, "Expenses", 'Data Repository Table'!$G:$G,"Facility Costs", 'Data Repository Table'!$H:$H, "Utility-Exp (002) - Heating", 'Data Repository Table'!$D:$D, H$13 ))} -> 2621863.5 | I57: {=SUM(SUMIFS( 'Data Repository Table'!$J:$J, 'Data Repository Table'!$A:$A, "Financial Actual", 'Data Repository Table'!$C:$C, {"Kootha","Surjek","Jutik"}, 'Data Repository Table'!$B:$B, "Expenses", 'Data Repository Table'!$G:$G,"Facility Costs", 'Data Repository Table'!$H:$H, "Utility-Exp (002) - Heating", 'Data Repository Table'!$D:$D, I$13 ))} -> 2806168.1 | J57: {=SUM(SUMIFS( 'Data Repository Table'!$J:$J, 'Data Repository Table'!$A:$A, "Financial Actual", 'Data Repository Table'!$C:$C, {"Kootha","Surjek","Jutik"}, 'Data Repository Table'!$B:$B, "Expenses", 'Data Repository Table'!$G:$G,"Facility Costs", 'Data Repository Table'!$H:$H, "Utility-Exp (002) - Heating", 'Data Repository Table'!$D:$D, J$13 ))} -> 3163209.6 | K57: {=SUM(SUMIFS( 'Data Repository Table'!$J:$J, 'Data Repository Table'!$A:$A, "Financial Actual", 'Data Repository Table'!$C:$C, {"Kootha","Surjek","Jutik"}, 'Data Repository Table'!$B:$B, "Expenses", 'Data Repository Table'!$G:$G,"Facility Costs", 'Data Repository Table'!$H:$H, "Utility-Exp (002) - Heating", 'Data Repository Table'!$D:$D, K$13 ))} -> 3218501.6 | L57: {=SUM(SUMIFS( 'Data Repository Table'!$J:$J, 'Data Repository Table'!$A:$A, "Financial Actual", 'Data Repository Table'!$C:$C, {"Kootha","Surjek","Jutik"}, 'Data Repository Table'!$B:$B, "Expenses", 'Data Repository Table'!$G:$G,"Facility Costs", 'Data Repository Table'!$H:$H, "Utility-Exp (002) - Heating", 'Data Repository Table'!$D:$D, L$13 ))} -> 2788369.1 | M57: {=SUM(SUMIFS( 'Data Repository Table'!$J:$J, 'Data Repository Table'!$A:$A, "Financial Actual", 'Data Repository Table'!$C:$C, {"Kootha","Surjek","Jutik"}, 'Data Repository Table'!$B:$B, "Expenses", 'Data Repository Table'!$G:$G,"Facility Costs", 'Data Repository Table'!$H:$H, "Utility-Exp (002) - Heating", 'Data Repository Table'!$D:$D, M$13 ))} -> 3593667.3 | N57: {=SUM(SUMIFS( 'Data Repository Table'!$J:$J, 'Data Repository Table'!$A:$A, "Financial Actual", 'Data Repository Table'!$C:$C, {"Kootha","Surjek","Jutik"}, 'Data Repository Table'!$B:$B, "Expenses", 'Data Repository Table'!$G:$G,"Facility Costs", 'Data Repository Table'!$H:$H, "Utility-Exp (002) - Heating", 'Data Repository Table'!$D:$D, N$13 ))} -> 3722191.5 | ... R57: {=SUM(SUMIFS( 'Data Repository Table'!$J:$J, 'Data Repository Table'!$A:$A, "Financial Actual", 'Data Repository Table'!$C:$C, {"Kootha","Surjek","Jutik"}, 'Data Repository Table'!$B:$B, "Expenses", 'Data Repository Table'!$G:$G,"Facility Costs", 'Data Repository Table'!$H:$H, "Utility-Exp (002) - Heating", 'Data Repository Table'!$D:$D, R$13 ))} -> 2932911.3 | S57: =SUM(G57:R57) -> 38717591
A58: Financial Actuals | B58: All | C58: Expenses | D58: Facility Costs | E58: Utility-Exp (002) - Electricity | G58: {=SUM(SUMIFS( 'Data Repository Table'!$J:$J, 'Data Repository Table'!$A:$A, "Financial Actual", 'Data Repository Table'!$C:$C, {"Kootha","Surjek","Jutik"}, 'Data Repository Table'!$B:$B, "Expenses", 'Data Repository Table'!$G:$G, "Facility Costs", 'Data Repository Table'!$H:$H, "Utility-Exp (002) - Electricity", 'Data Repository Table'!$D:$D, G$13 ))} -> 2300028 | H58: {=SUM(SUMIFS( 'Data Repository Table'!$J:$J, 'Data Repository Table'!$A:$A, "Financial Actual", 'Data Repository Table'!$C:$C, {"Kootha","Surjek","Jutik"}, 'Data Repository Table'!$B:$B, "Expenses", 'Data Repository Table'!$G:$G, "Facility Costs", 'Data Repository Table'!$H:$H, "Utility-Exp (002) - Electricity", 'Data Repository Table'!$D:$D, H$13 ))} -> 2505939.6 | I58: {=SUM(SUMIFS( 'Data Repository Table'!$J:$J, 'Data Repository Table'!$A:$A, "Financial Actual", 'Data Repository Table'!$C:$C, {"Kootha","Surjek","Jutik"}, 'Data Repository Table'!$B:$B, "Expenses", 'Data Repository Table'!$G:$G, "Facility Costs", 'Data Repository Table'!$H:$H, "Utility-Exp (002) - Electricity", 'Data Repository Table'!$D:$D, I$13 ))} -> 2627415.4 | J58: {=SUM(SUMIFS( 'Data Repository Table'!$J:$J, 'Data Repository Table'!$A:$A, "Financial Actual", 'Data Repository Table'!$C:$C, {"Kootha","Surjek","Jutik"}, 'Data Repository Table'!$B:$B, "Expenses", 'Data Repository Table'!$G:$G, "Facility Costs", 'Data Repository Table'!$H:$H, "Utility-Exp (002) - Electricity", 'Data Repository Table'!$D:$D, J$13 ))} -> 2900613.3 | K58: {=SUM(SUMIFS( 'Data Repository Table'!$J:$J, 'Data Repository Table'!$A:$A, "Financial Actual", 'Data Repository Table'!$C:$C, {"Kootha","Surjek","Jutik"}, 'Data Repository Table'!$B:$B, "Expenses", 'Data Repository Table'!$G:$G, "Facility Costs", 'Data Repository Table'!$H:$H, "Utility-Exp (002) - Electricity", 'Data Repository Table'!$D:$D, K$13 ))} -> 2940556.2 | L58: {=SUM(SUMIFS( 'Data Repository Table'!$J:$J, 'Data Repository Table'!$A:$A, "Financial Actual", 'Data Repository Table'!$C:$C, {"Kootha","Surjek","Jutik"}, 'Data Repository Table'!$B:$B, "Expenses", 'Data Repository Table'!$G:$G, "Facility Costs", 'Data Repository Table'!$H:$H, "Utility-Exp (002) - Electricity", 'Data Repository Table'!$D:$D, L$13 ))} -> 2582565 | M58: {=SUM(SUMIFS( 'Data Repository Table'!$J:$J, 'Data Repository Table'!$A:$A, "Financial Actual", 'Data Repository Table'!$C:$C, {"Kootha","Surjek","Jutik"}, 'Data Repository Table'!$B:$B, "Expenses", 'Data Repository Table'!$G:$G, "Facility Costs", 'Data Repository Table'!$H:$H, "Utility-Exp (002) - Electricity", 'Data Repository Table'!$D:$D, M$13 ))} -> 3446732.9 | N58: {=SUM(SUMIFS( 'Data Repository Table'!$J:$J, 'Data Repository Table'!$A:$A, "Financial Actual", 'Data Repository Table'!$C:$C, {"Kootha","Surjek","Jutik"}, 'Data Repository Table'!$B:$B, "Expenses", 'Data Repository Table'!$G:$G, "Facility Costs", 'Data Repository Table'!$H:$H, "Utility-Exp (002) - Electricity", 'Data Repository Table'!$D:$D, N$13 ))} -> 3483983.4 | ... R58: {=SUM(SUMIFS( 'Data Repository Table'!$J:$J, 'Data Repository Table'!$A:$A, "Financial Actual", 'Data Repository Table'!$C:$C, {"Kootha","Surjek","Jutik"}, 'Data Repository Table'!$B:$B, "Expenses", 'Data Repository Table'!$G:$G, "Facility Costs", 'Data Repository Table'!$H:$H, "Utility-Exp (002) - Electricity", 'Data Repository Table'!$D:$D, R$13 ))} -> 2923183.2 | S58: =SUM(G58:R58) -> 36414828
A59: Financial Actuals | B59: All | C59: Expenses | D59: Operational Maintenance Costs | E59: Plant Maintenance (001) | G59: {=SUM(SUMIFS( 'Data Repository Table'!$J:$J, 'Data Repository Table'!$A:$A, "Financial Actual", 'Data Repository Table'!$C:$C, {"Kootha","Surjek","Jutik"}, 'Data Repository Table'!$B:$B, "Expenses", 'Data Repository Table'!$G:$G, "Operational Maintenance Costs", 'Data Repository Table'!$H:$H, "Plant Maintenance (001)", 'Data Repository Table'!$D:$D, G$13 ))} -> 2073604.7 | H59: {=SUM(SUMIFS( 'Data Repository Table'!$J:$J, 'Data Repository Table'!$A:$A, "Financial Actual", 'Data Repository Table'!$C:$C, {"Kootha","Surjek","Jutik"}, 'Data Repository Table'!$B:$B, "Expenses", 'Data Repository Table'!$G:$G, "Operational Maintenance Costs", 'Data Repository Table'!$H:$H, "Plant Maintenance (001)", 'Data Repository Table'!$D:$D, H$13 ))} -> 2269539.8 | I59: {=SUM(SUMIFS( 'Data Repository Table'!$J:$J, 'Data Repository Table'!$A:$A, "Financial Actual", 'Data Repository Table'!$C:$C, {"Kootha","Surjek","Jutik"}, 'Data Repository Table'!$B:$B, "Expenses", 'Data Repository Table'!$G:$G, "Operational Maintenance Costs", 'Data Repository Table'!$H:$H, "Plant Maintenance (001)", 'Data Repository Table'!$D:$D, I$13 ))} -> 2374998.8 | J59: {=SUM(SUMIFS( 'Data Repository Table'!$J:$J, 'Data Repository Table'!$A:$A, "Financial Actual", 'Data Repository Table'!$C:$C, {"Kootha","Surjek","Jutik"}, 'Data Repository Table'!$B:$B, "Expenses", 'Data Repository Table'!$G:$G, "Operational Maintenance Costs", 'Data Repository Table'!$H:$H, "Plant Maintenance (001)", 'Data Repository Table'!$D:$D, J$13 ))} -> 2645968.1 | K59: {=SUM(SUMIFS( 'Data Repository Table'!$J:$J, 'Data Repository Table'!$A:$A, "Financial Actual", 'Data Repository Table'!$C:$C, {"Kootha","Surjek","Jutik"}, 'Data Repository Table'!$B:$B, "Expenses", 'Data Repository Table'!$G:$G, "Operational Maintenance Costs", 'Data Repository Table'!$H:$H, "Plant Maintenance (001)", 'Data Repository Table'!$D:$D, K$13 ))} -> 2691801.7 | L59: {=SUM(SUMIFS( 'Data Repository Table'!$J:$J, 'Data Repository Table'!$A:$A, "Financial Actual", 'Data Repository Table'!$C:$C, {"Kootha","Surjek","Jutik"}, 'Data Repository Table'!$B:$B, "Expenses", 'Data Repository Table'!$G:$G, "Operational Maintenance Costs", 'Data Repository Table'!$H:$H, "Plant Maintenance (001)", 'Data Repository Table'!$D:$D, L$13 ))} -> 2348808.3 | M59: {=SUM(SUMIFS( 'Data Repository Table'!$J:$J, 'Data Repository Table'!$A:$A, "Financial Actual", 'Data Repository Table'!$C:$C, {"Kootha","Surjek","Jutik"}, 'Data Repository Table'!$B:$B, "Expenses", 'Data Repository Table'!$G:$G, "Operational Maintenance Costs", 'Data Repository Table'!$H:$H, "Plant Maintenance (001)", 'Data Repository Table'!$D:$D, M$13 ))} -> 2879996.2 | N59: {=SUM(SUMIFS( 'Data Repository Table'!$J:$J, 'Data Repository Table'!$A:$A, "Financial Actual", 'Data Repository Table'!$C:$C, {"Kootha","Surjek","Jutik"}, 'Data Repository Table'!$B:$B, "Expenses", 'Data Repository Table'!$G:$G, "Operational Maintenance Costs", 'Data Repository Table'!$H:$H, "Plant Maintenance (001)", 'Data Repository Table'!$D:$D, N$13 ))} -> 2972957.9 | ... R59: {=SUM(SUMIFS( 'Data Repository Table'!$J:$J, 'Data Repository Table'!$A:$A, "Financial Actual", 'Data Repository Table'!$C:$C, {"Kootha","Surjek","Jutik"}, 'Data Repository Table'!$B:$B, "Expenses", 'Data Repository Table'!$G:$G, "Operational Maintenance Costs", 'Data Repository Table'!$H:$H, "Plant Maintenance (001)", 'Data Repository Table'!$D:$D, R$13 ))} -> 2363869.6 | S59: =SUM(G59:R59) -> 31752797
A60: Financial Actuals | B60: All | C60: Expenses | D60: Operational Maintenance Costs | E60: Plant Outages (002) | G60: {=SUM(SUMIFS( 'Data Repository Table'!$J:$J, 'Data Repository Table'!$A:$A, "Financial Actual", 'Data Repository Table'!$C:$C, {"Kootha","Surjek","Jutik"}, 'Data Repository Table'!$B:$B, "Expenses", 'Data Repository Table'!$G:$G, "Operational Maintenance Costs", 'Data Repository Table'!$H:$H, "Plant Outages (002)", 'Data Repository Table'!$D:$D, G$13 ))} -> 1347738.9 | H60: {=SUM(SUMIFS( 'Data Repository Table'!$J:$J, 'Data Repository Table'!$A:$A, "Financial Actual", 'Data Repository Table'!$C:$C, {"Kootha","Surjek","Jutik"}, 'Data Repository Table'!$B:$B, "Expenses", 'Data Repository Table'!$G:$G, "Operational Maintenance Costs", 'Data Repository Table'!$H:$H, "Plant Outages (002)", 'Data Repository Table'!$D:$D, H$13 ))} -> 1561170.4 | I60: {=SUM(SUMIFS( 'Data Repository Table'!$J:$J, 'Data Repository Table'!$A:$A, "Financial Actual", 'Data Repository Table'!$C:$C, {"Kootha","Surjek","Jutik"}, 'Data Repository Table'!$B:$B, "Expenses", 'Data Repository Table'!$G:$G, "Operational Maintenance Costs", 'Data Repository Table'!$H:$H, "Plant Outages (002)", 'Data Repository Table'!$D:$D, I$13 ))} -> 1574874.1 | J60: {=SUM(SUMIFS( 'Data Repository Table'!$J:$J, 'Data Repository Table'!$A:$A, "Financial Actual", 'Data Repository Table'!$C:$C, {"Kootha","Surjek","Jutik"}, 'Data Repository Table'!$B:$B, "Expenses", 'Data Repository Table'!$G:$G, "Operational Maintenance Costs", 'Data Repository Table'!$H:$H, "Plant Outages (002)", 'Data Repository Table'!$D:$D, J$13 ))} -> 1880373.5 | K60: {=SUM(SUMIFS( 'Data Repository Table'!$J:$J, 'Data Repository Table'!$A:$A, "Financial Actual", 'Data Repository Table'!$C:$C, {"Kootha","Surjek","Jutik"}, 'Data Repository Table'!$B:$B, "Expenses", 'Data Repository Table'!$G:$G, "Operational Maintenance Costs", 'Data Repository Table'!$H:$H, "Plant Outages (002)", 'Data Repository Table'!$D:$D, K$13 ))} -> 1968683.2 | L60: {=SUM(SUMIFS( 'Data Repository Table'!$J:$J, 'Data Repository Table'!$A:$A, "Financial Actual", 'Data Repository Table'!$C:$C, {"Kootha","Surjek","Jutik"}, 'Data Repository Table'!$B:$B, "Expenses", 'Data Repository Table'!$G:$G, "Operational Maintenance Costs", 'Data Repository Table'!$H:$H, "Plant Outages (002)", 'Data Repository Table'!$D:$D, L$13 ))} -> 1158623.1 | M60: {=SUM(SUMIFS( 'Data Repository Table'!$J:$J, 'Data Repository Table'!$A:$A, "Financial Actual", 'Data Repository Table'!$C:$C, {"Kootha","Surjek","Jutik"}, 'Data Repository Table'!$B:$B, "Expenses", 'Data Repository Table'!$G:$G, "Operational Maintenance Costs", 'Data Repository Table'!$H:$H, "Plant Outages (002)", 'Data Repository Table'!$D:$D, M$13 ))} -> 1176136.2 | N60: {=SUM(SUMIFS( 'Data Repository Table'!$J:$J, 'Data Repository Table'!$A:$A, "Financial Actual", 'Data Repository Table'!$C:$C, {"Kootha","Surjek","Jutik"}, 'Data Repository Table'!$B:$B, "Expenses", 'Data Repository Table'!$G:$G, "Operational Maintenance Costs", 'Data Repository Table'!$H:$H, "Plant Outages (002)", 'Data Repository Table'!$D:$D, N$13 ))} -> 1239117.6 | ... R60: {=SUM(SUMIFS( 'Data Repository Table'!$J:$J, 'Data Repository Table'!$A:$A, "Financial Actual", 'Data Repository Table'!$C:$C, {"Kootha","Surjek","Jutik"}, 'Data Repository Table'!$B:$B, "Expenses", 'Data Repository Table'!$G:$G, "Operational Maintenance Costs", 'Data Repository Table'!$H:$H, "Plant Outages (002)", 'Data Repository Table'!$D:$D, R$13 ))} -> 1040665.8 | S60: =SUM(G60:R60) -> 16735123
A61: Financial Actuals | B61: All | C61: Expenses | D61: Operational Maintenance Costs | E61: Plant Op. Costs (003) | G61: {=SUM(SUMIFS( 'Data Repository Table'!$J:$J, 'Data Repository Table'!$A:$A, "Financial Actual", 'Data Repository Table'!$C:$C, {"Kootha","Surjek","Jutik"}, 'Data Repository Table'!$B:$B, "Expenses", 'Data Repository Table'!$G:$G, "Operational Maintenance Costs", 'Data Repository Table'!$H:$H, "Plant Op. Costs (003)", 'Data Repository Table'!$D:$D, G$13 ))} -> 1800236.6 | H61: {=SUM(SUMIFS( 'Data Repository Table'!$J:$J, 'Data Repository Table'!$A:$A, "Financial Actual", 'Data Repository Table'!$C:$C, {"Kootha","Surjek","Jutik"}, 'Data Repository Table'!$B:$B, "Expenses", 'Data Repository Table'!$G:$G, "Operational Maintenance Costs", 'Data Repository Table'!$H:$H, "Plant Op. Costs (003)", 'Data Repository Table'!$D:$D, H$13 ))} -> 1959718.9 | I61: {=SUM(SUMIFS( 'Data Repository Table'!$J:$J, 'Data Repository Table'!$A:$A, "Financial Actual", 'Data Repository Table'!$C:$C, {"Kootha","Surjek","Jutik"}, 'Data Repository Table'!$B:$B, "Expenses", 'Data Repository Table'!$G:$G, "Operational Maintenance Costs", 'Data Repository Table'!$H:$H, "Plant Op. Costs (003)", 'Data Repository Table'!$D:$D, I$13 ))} -> 2069515.6 | J61: {=SUM(SUMIFS( 'Data Repository Table'!$J:$J, 'Data Repository Table'!$A:$A, "Financial Actual", 'Data Repository Table'!$C:$C, {"Kootha","Surjek","Jutik"}, 'Data Repository Table'!$B:$B, "Expenses", 'Data Repository Table'!$G:$G, "Operational Maintenance Costs", 'Data Repository Table'!$H:$H, "Plant Op. Costs (003)", 'Data Repository Table'!$D:$D, J$13 ))} -> 2330999.3 | K61: {=SUM(SUMIFS( 'Data Repository Table'!$J:$J, 'Data Repository Table'!$A:$A, "Financial Actual", 'Data Repository Table'!$C:$C, {"Kootha","Surjek","Jutik"}, 'Data Repository Table'!$B:$B, "Expenses", 'Data Repository Table'!$G:$G, "Operational Maintenance Costs", 'Data Repository Table'!$H:$H, "Plant Op. Costs (003)", 'Data Repository Table'!$D:$D, K$13 ))} -> 2376535.9 | L61: {=SUM(SUMIFS( 'Data Repository Table'!$J:$J, 'Data Repository Table'!$A:$A, "Financial Actual", 'Data Repository Table'!$C:$C, {"Kootha","Surjek","Jutik"}, 'Data Repository Table'!$B:$B, "Expenses", 'Data Repository Table'!$G:$G, "Operational Maintenance Costs", 'Data Repository Table'!$H:$H, "Plant Op. Costs (003)", 'Data Repository Table'!$D:$D, L$13 ))} -> 1447049.3 | M61: {=SUM(SUMIFS( 'Data Repository Table'!$J:$J, 'Data Repository Table'!$A:$A, "Financial Actual", 'Data Repository Table'!$C:$C, {"Kootha","Surjek","Jutik"}, 'Data Repository Table'!$B:$B, "Expenses", 'Data Repository Table'!$G:$G, "Operational Maintenance Costs", 'Data Repository Table'!$H:$H, "Plant Op. Costs (003)", 'Data Repository Table'!$D:$D, M$13 ))} -> 1483562.2 | N61: {=SUM(SUMIFS( 'Data Repository Table'!$J:$J, 'Data Repository Table'!$A:$A, "Financial Actual", 'Data Repository Table'!$C:$C, {"Kootha","Surjek","Jutik"}, 'Data Repository Table'!$B:$B, "Expenses", 'Data Repository Table'!$G:$G, "Operational Maintenance Costs", 'Data Repository Table'!$H:$H, "Plant Op. Costs (003)", 'Data Repository Table'!$D:$D, N$13 ))} -> 1516247.7 | ... R61: {=SUM(SUMIFS( 'Data Repository Table'!$J:$J, 'Data Repository Table'!$A:$A, "Financial Actual", 'Data Repository Table'!$C:$C, {"Kootha","Surjek","Jutik"}, 'Data Repository Table'!$B:$B, "Expenses", 'Data Repository Table'!$G:$G, "Operational Maintenance Costs", 'Data Repository Table'!$H:$H, "Plant Op. Costs (003)", 'Data Repository Table'!$D:$D, R$13 ))} -> 1452590.3 | S61: =SUM(G61:R61) -> 21090667
A62: Financial Actuals | B62: All | C62: Expenses | D62: Operational Maintenance Costs | E62: Plant Admin Costs (004) | G62: {=SUM(SUMIFS( 'Data Repository Table'!$J:$J, 'Data Repository Table'!$A:$A, "Financial Actual", 'Data Repository Table'!$C:$C, {"Kootha","Surjek","Jutik"}, 'Data Repository Table'!$B:$B, "Expenses", 'Data Repository Table'!$G:$G, "Operational Maintenance Costs", 'Data Repository Table'!$H:$H, "Plant Admin Costs (004)", 'Data Repository Table'!$D:$D, G$13 ))} -> 886197.6 | H62: {=SUM(SUMIFS( 'Data Repository Table'!$J:$J, 'Data Repository Table'!$A:$A, "Financial Actual", 'Data Repository Table'!$C:$C, {"Kootha","Surjek","Jutik"}, 'Data Repository Table'!$B:$B, "Expenses", 'Data Repository Table'!$G:$G, "Operational Maintenance Costs", 'Data Repository Table'!$H:$H, "Plant Admin Costs (004)", 'Data Repository Table'!$D:$D, H$13 ))} -> 1012646.7 | I62: {=SUM(SUMIFS( 'Data Repository Table'!$J:$J, 'Data Repository Table'!$A:$A, "Financial Actual", 'Data Repository Table'!$C:$C, {"Kootha","Surjek","Jutik"}, 'Data Repository Table'!$B:$B, "Expenses", 'Data Repository Table'!$G:$G, "Operational Maintenance Costs", 'Data Repository Table'!$H:$H, "Plant Admin Costs (004)", 'Data Repository Table'!$D:$D, I$13 ))} -> 1025398.9 | J62: {=SUM(SUMIFS( 'Data Repository Table'!$J:$J, 'Data Repository Table'!$A:$A, "Financial Actual", 'Data Repository Table'!$C:$C, {"Kootha","Surjek","Jutik"}, 'Data Repository Table'!$B:$B, "Expenses", 'Data Repository Table'!$G:$G, "Operational Maintenance Costs", 'Data Repository Table'!$H:$H, "Plant Admin Costs (004)", 'Data Repository Table'!$D:$D, J$13 ))} -> 1186611 | K62: {=SUM(SUMIFS( 'Data Repository Table'!$J:$J, 'Data Repository Table'!$A:$A, "Financial Actual", 'Data Repository Table'!$C:$C, {"Kootha","Surjek","Jutik"}, 'Data Repository Table'!$B:$B, "Expenses", 'Data Repository Table'!$G:$G, "Operational Maintenance Costs", 'Data Repository Table'!$H:$H, "Plant Admin Costs (004)", 'Data Repository Table'!$D:$D, K$13 ))} -> 1229462.3 | L62: {=SUM(SUMIFS( 'Data Repository Table'!$J:$J, 'Data Repository Table'!$A:$A, "Financial Actual", 'Data Repository Table'!$C:$C, {"Kootha","Surjek","Jutik"}, 'Data Repository Table'!$B:$B, "Expenses", 'Data Repository Table'!$G:$G, "Operational Maintenance Costs", 'Data Repository Table'!$H:$H, "Plant Admin Costs (004)", 'Data Repository Table'!$D:$D, L$13 ))} -> 749668.57 | M62: {=SUM(SUMIFS( 'Data Repository Table'!$J:$J, 'Data Repository Table'!$A:$A, "Financial Actual", 'Data Repository Table'!$C:$C, {"Kootha","Surjek","Jutik"}, 'Data Repository Table'!$B:$B, "Expenses", 'Data Repository Table'!$G:$G, "Operational Maintenance Costs", 'Data Repository Table'!$H:$H, "Plant Admin Costs (004)", 'Data Repository Table'!$D:$D, M$13 ))} -> 774322.05 | N62: {=SUM(SUMIFS( 'Data Repository Table'!$J:$J, 'Data Repository Table'!$A:$A, "Financial Actual", 'Data Repository Table'!$C:$C, {"Kootha","Surjek","Jutik"}, 'Data Repository Table'!$B:$B, "Expenses", 'Data Repository Table'!$G:$G, "Operational Maintenance Costs", 'Data Repository Table'!$H:$H, "Plant Admin Costs (004)", 'Data Repository Table'!$D:$D, N$13 ))} -> 795356.49 | ... R62: {=SUM(SUMIFS( 'Data Repository Table'!$J:$J, 'Data Repository Table'!$A:$A, "Financial Actual", 'Data Repository Table'!$C:$C, {"Kootha","Surjek","Jutik"}, 'Data Repository Table'!$B:$B, "Expenses", 'Data Repository Table'!$G:$G, "Operational Maintenance Costs", 'Data Repository Table'!$H:$H, "Plant Admin Costs (004)", 'Data Repository Table'!$D:$D, R$13 ))} -> 718766.35 | S62: =SUM(G62:R62) -> 10813425
A63: Financial Actuals | B63: All | C63: Expenses | D63: Labour Costs | E63: Labour-Costs (001) | G63: {=SUM(SUMIFS( 'Data Repository Table'!$J:$J, 'Data Repository Table'!$A:$A, "Financial Actual", 'Data Repository Table'!$C:$C, {"Kootha","Surjek","Jutik"}, 'Data Repository Table'!$B:$B, "Expenses", 'Data Repository Table'!$G:$G, "Labour Costs", 'Data Repository Table'!$H:$H, "Labour-Costs (001)", 'Data Repository Table'!$D:$D, G$13 ))} -> 7367588.7 | H63: {=SUM(SUMIFS( 'Data Repository Table'!$J:$J, 'Data Repository Table'!$A:$A, "Financial Actual", 'Data Repository Table'!$C:$C, {"Kootha","Surjek","Jutik"}, 'Data Repository Table'!$B:$B, "Expenses", 'Data Repository Table'!$G:$G, "Labour Costs", 'Data Repository Table'!$H:$H, "Labour-Costs (001)", 'Data Repository Table'!$D:$D, H$13 ))} -> 7849336 | I63: {=SUM(SUMIFS( 'Data Repository Table'!$J:$J, 'Data Repository Table'!$A:$A, "Financial Actual", 'Data Repository Table'!$C:$C, {"Kootha","Surjek","Jutik"}, 'Data Repository Table'!$B:$B, "Expenses", 'Data Repository Table'!$G:$G, "Labour Costs", 'Data Repository Table'!$H:$H, "Labour-Costs (001)", 'Data Repository Table'!$D:$D, I$13 ))} -> 8389760.6 | J63: {=SUM(SUMIFS( 'Data Repository Table'!$J:$J, 'Data Repository Table'!$A:$A, "Financial Actual", 'Data Repository Table'!$C:$C, {"Kootha","Surjek","Jutik"}, 'Data Repository Table'!$B:$B, "Expenses", 'Data Repository Table'!$G:$G, "Labour Costs", 'Data Repository Table'!$H:$H, "Labour-Costs (001)", 'Data Repository Table'!$D:$D, J$13 ))} -> 9137407.9 | K63: {=SUM(SUMIFS( 'Data Repository Table'!$J:$J, 'Data Repository Table'!$A:$A, "Financial Actual", 'Data Repository Table'!$C:$C, {"Kootha","Surjek","Jutik"}, 'Data Repository Table'!$B:$B, "Expenses", 'Data Repository Table'!$G:$G, "Labour Costs", 'Data Repository Table'!$H:$H, "Labour-Costs (001)", 'Data Repository Table'!$D:$D, K$13 ))} -> 9187416 | L63: {=SUM(SUMIFS( 'Data Repository Table'!$J:$J, 'Data Repository Table'!$A:$A, "Financial Actual", 'Data Repository Table'!$C:$C, {"Kootha","Surjek","Jutik"}, 'Data Repository Table'!$B:$B, "Expenses", 'Data Repository Table'!$G:$G, "Labour Costs", 'Data Repository Table'!$H:$H, "Labour-Costs (001)", 'Data Repository Table'!$D:$D, L$13 ))} -> 5779740.1 | M63: {=SUM(SUMIFS( 'Data Repository Table'!$J:$J, 'Data Repository Table'!$A:$A, "Financial Actual", 'Data Repository Table'!$C:$C, {"Kootha","Surjek","Jutik"}, 'Data Repository Table'!$B:$B, "Expenses", 'Data Repository Table'!$G:$G, "Labour Costs", 'Data Repository Table'!$H:$H, "Labour-Costs (001)", 'Data Repository Table'!$D:$D, M$13 ))} -> 6008311.5 | N63: {=SUM(SUMIFS( 'Data Repository Table'!$J:$J, 'Data Repository Table'!$A:$A, "Financial Actual", 'Data Repository Table'!$C:$C, {"Kootha","Surjek","Jutik"}, 'Data Repository Table'!$B:$B, "Expenses", 'Data Repository Table'!$G:$G, "Labour Costs", 'Data Repository Table'!$H:$H, "Labour-Costs (001)", 'Data Repository Table'!$D:$D, N$13 ))} -> 6995041 | ... R63: {=SUM(SUMIFS( 'Data Repository Table'!$J:$J, 'Data Repository Table'!$A:$A, "Financial Actual", 'Data Repository Table'!$C:$C, {"Kootha","Surjek","Jutik"}, 'Data Repository Table'!$B:$B, "Expenses", 'Data Repository Table'!$G:$G, "Labour Costs", 'Data Repository Table'!$H:$H, "Labour-Costs (001)", 'Data Repository Table'!$D:$D, R$13 ))} -> 6174477.1 | S63: =SUM(G63:R63) -> 87328632
A64: Water Production Actuals | B64: All | G64: {=SUM(SUMIFS( 'Data Repository Table'!$J:$J, 'Data Repository Table'!$A:$A, "Water Production Actuals", 'Data Repository Table'!$C:$C, {"Kootha","Surjek","Jutik"}, 'Data Repository Table'!$D:$D, G$13 ))} -> 647.14428 | H64: {=SUM(SUMIFS( 'Data Repository Table'!$J:$J, 'Data Repository Table'!$A:$A, "Water Production Actuals", 'Data Repository Table'!$C:$C, {"Kootha","Surjek","Jutik"}, 'Data Repository Table'!$D:$D, H$13 ))} -> 622.3837 | I64: {=SUM(SUMIFS( 'Data Repository Table'!$J:$J, 'Data Repository Table'!$A:$A, "Water Production Actuals", 'Data Repository Table'!$C:$C, {"Kootha","Surjek","Jutik"}, 'Data Repository Table'!$D:$D, I$13 ))} -> 602.54558 | J64: {=SUM(SUMIFS( 'Data Repository Table'!$J:$J, 'Data Repository Table'!$A:$A, "Water Production Actuals", 'Data Repository Table'!$C:$C, {"Kootha","Surjek","Jutik"}, 'Data Repository Table'!$D:$D, J$13 ))} -> 602.67093 | K64: {=SUM(SUMIFS( 'Data Repository Table'!$J:$J, 'Data Repository Table'!$A:$A, "Water Production Actuals", 'Data Repository Table'!$C:$C, {"Kootha","Surjek","Jutik"}, 'Data Repository Table'!$D:$D, K$13 ))} -> 534.23998 | L64: {=SUM(SUMIFS( 'Data Repository Table'!$J:$J, 'Data Repository Table'!$A:$A, "Water Production Actuals", 'Data Repository Table'!$C:$C, {"Kootha","Surjek","Jutik"}, 'Data Repository Table'!$D:$D, L$13 ))} -> 571.87368 | M64: {=SUM(SUMIFS( 'Data Repository Table'!$J:$J, 'Data Repository Table'!$A:$A, "Water Production Actuals", 'Data Repository Table'!$C:$C, {"Kootha","Surjek","Jutik"}, 'Data Repository Table'!$D:$D, M$13 ))} -> 679.26449 | N64: {=SUM(SUMIFS( 'Data Repository Table'!$J:$J, 'Data Repository Table'!$A:$A, "Water Production Actuals", 'Data Repository Table'!$C:$C, {"Kootha","Surjek","Jutik"}, 'Data Repository Table'!$D:$D, N$13 ))} -> 682.90149 | ... R64: {=SUM(SUMIFS( 'Data Repository Table'!$J:$J, 'Data Repository Table'!$A:$A, "Water Production Actuals", 'Data Repository Table'!$C:$C, {"Kootha","Surjek","Jutik"}, 'Data Repository Table'!$D:$D, R$13 ))} -> 623.20135 | S64: =SUM(G64:R64) -> 7889.2679
E65: Desalination Cost to Produce ($/ML) | G65: =SUM(G$56:G$63)/(G$64 * 1000) -> 35.489518 | H65: =SUM(H$56:H$63)/(H$64 * 1000) -> 40.083392 | I65: =SUM(I$56:I$63)/(I$64 * 1000) -> 43.723249 | J65: =SUM(J$56:J$63)/(J$64 * 1000) -> 48.886636 | K65: =SUM(K$56:K$63)/(K$64 * 1000) -> 56.088102 | L65: =SUM(L$56:L$63)/(L$64 * 1000) -> 39.044842 | M65: =SUM(M$56:M$63)/(M$64 * 1000) -> 38.918514 | N65: =SUM(N$56:N$63)/(N$64 * 1000) -> 41.54332 | ... R65: =SUM(R$56:R$63)/(R$64 * 1000) -> 37.418279 | S65: =SUM(S56:S63)/S64 -> 40721.955
A84: In Economics, we care about our overall Cost to Produce Desalinated Water as it gives us an indication of how cost-effective our plants are. It's important in our Economic Data Analysis to also interpret this price point with respect to the volume of water that is produced. This touches upon a concept known as economies of scale. Essentially, the more water we produce - the cheaper we should see our production costs. On the other hand, the less water we produce, the more our Cost to Produce will increase on scaled basis.
A85: Q6. Using the Monthly Cost to Produce you've calculated for each Plant (Kootha, Surjek and Jutik), create a scatter-plot which shows the Cost to Produce (Y-Axis) against the Total Volume of Water produced(X-Axis). You will end up with three Scatter Plots that will let you see whether a relationship exists between Cost to Produce and the Volume of Water produced. Does there appear to be a relationship between Cost to Produce and Volume of Water Produced? If yes, why do you believe this is the case? If no, why do you believe this is the case?
A105: We've now analysed our Cost to Produce and we can clearly see the following trends emerge: A) There are differences in cost effectiveness between desalination units which are largely influenced by the costs and the volume of water produced B) We can pick up a relationship between the Cost to Produce and Quantity of Water being produced. This brings us to our last questions for the Economic Cost Analysis. How does our Cost of Production compare to the Market Price at which water is being sold? In other words, if our production costs are HIGHER than the price at which we can sell our water - we won't be making any real profit...!
A106: Now we'll close off the Economic Cost Analysis with an understanding of comparing the Market Price against the Cost to Produce ($/ML) of our desalination units. Q7. Completing the table below, create a clustered column chart showing the Overall Desalination Cost to Produce $/ML versus Overall Average WBMP Market Price.
A107: Note: We've included an example of how the chart might look once you've completed this!
A108: Unit | B108: Overall Desalination Cost to Produce ($/ML) | C108: Overall Average WBMP Market Price
A109: Kootha | B109: =SUM(S16:S23)/(S24 * 1000) -> 25.001374 | C109: =AVERAGEIFS('Water Trading Repository Table'!C:C, 'Data Repository Table'!C:C, "Kootha") -> 55.517133
A110: Surjek | B110: =SUM(S27:S34)/(S35 * 1000) -> 54.231507 | C110: =AVERAGEIFS('Water Trading Repository Table'!C:C, 'Data Repository Table'!C:C, "Surjek") -> 55.735352
A111: Jutik | B111: =SUM(S38:S45)/(S46 * 1000) -> 35.804189 | C111: =AVERAGEIFS('Water Trading Repository Table'!C:C, 'Data Repository Table'!C:C, "Jutik") -> 56.66766

Sheet Variance Analysis
A1: Budget - Actual Analysis (Variance).
